Workbook
Name Slicer_Zone: #N/A

Sheet Qs)Part-3
A3: Count of Evaluation_ID | B3: Column Labels
A4: Row Labels | B4: Average Performer | C4: Bottom Performer | D4: High Performer | E4: Low Performer | F4: Grand Total
A5: East | B5: 0.14285714 | C5: 0.14285714 | D5: 0.28571429 | E5: 0.42857143 | F5: 1
A6: North | B6: 0.47368421 | C6: 0.052631579 | D6: 0.21052632 | E6: 0.26315789 | F6: 1
A7: South | B7: 0.38888889 | C7: 0.16666667 | D7: 0.11111111 | E7: 0.33333333 | F7: 1
A8: West | B8: 0.58823529 | C8: 0.17647059 | D8: 0.11764706 | E8: 0.11764706 | F8: 1
A9: Grand Total | B9: 0.44262295 | C9: 0.13114754 | D9: 0.16393443 | E9: 0.26229508 | F9: 1

Sheet Qs)Part-4 Visualizations-1
A1: Row Labels | B1: Average of Evaluation_Score
A2: East | B2: 71.571429
A3: North | B3: 76.736842
A4: South | B4: 66.611111
A5: West | B5: 71.823529
A6: Grand Total | B6: 71.786885

Sheet CX_Junior BI Analyst_Test
A1: Evaluation_ID | B1: Evaluation_Date | C1: Evaluation_Score | D1: STORE AMBIANCE | E1: FIRST IMPRESSIONS | F1: DISCOVERY | G1: RECOMMENDATIONS | H1: TRIAL EXPERIENCE & UPSELL | I1: OBJECTION HANDLING | J1: CLOSURE & CARE | K1: OVERALL EXPERIENCE | L1: Location_City | M1: Location_State | N1: Zone | O1: Location_Country | P1: Time of entry: | Q1: Time of exit: | R1: Duration of visit: | S1: How many Style Advisors were present in the store during your visit? | T1: How many customers were present in the store during your visit? | U1: Age of the Auditor: | V1: Gender of Auditor: | W1: Please describe what you were wearing during your visit. | X1: Name of the Style Advisor who attended to you: | Y1: Please provide a detailed physical description (gender, approx. height, complexion, hair colour, wore spectacles, wearing Company branded t-shirt, plain jeans, shoes, proper shave and hairstyle done, etc.) | Z1: 1.1 - Was the exterior signage clean and well lit? | AA1: 1.2 - Was the store threshold, entrance and overall look inviting? | AB1: 1.3 - Were all the fixtures and other tangibles in good condition (walls, lights, floor, etc.)? | AC1: 1.4 - Was there any music playing at the store? | AD1: 1.5 - Was the digital screen in the store operational during your visit? | AE1: 1.6 - Did you see any cartons, etc. lying around? | AF1: 1.7 - Was the merchandise displayed and arranged well on the drawers/shelves/display tables? | AG1: 1.8 - Was the merchandise arranged according to the brand and frame type? | AH1: 1.9 - Upon your entrance, did you feel welcomed to freely move and explore the store? | AI1: 1.10 - Additional remarks, if any. | AJ1: 2.1 - What was your first impression when you entered the store? Please mention the details. | AK1: 2.1.1 Please justify your reason for the above marking. | AL1: 2.2 - Were you acknowledged and greeted with the following: | AM1: 2.3 - How long did you have to wait to receive service from the Style Advisor (from the moment you entered the store until you received service from the advisor)? | AN1: 2.4 - Was the store temperature maintained at a comfortable level? | AO1: 2.5 - Was there a pleasant aroma inside the store? | AP1: 2.6 - Were the racks and signages for offers neat and clean, and was the cashier desk neat and well stocked? | AQ1: 2.7 - Were you proactively approached by the Style Advisor to initiate in an icebreaking, non transactional conversation? (Eg: "Nice shades/watch/denims!", "I must say you have great taste") | AR1: 2.8 - Were you given assistance with your bags, if you had any? (mark N/A if you did not have any bags) | AS1: 3.1 - Did Style Advisor proactively engage you in a conversation to understand your needs and wants? Questions may include occasion/reason for purchase, lifestyle, choice of colour, style, material, volume, function, size, etc. | AT1: 3.2 - Did Style Advisor genuinely show an interest in your needs and listen to you empathically? | AU1: 3.3 - What were the questions asked by the Style Advisor to discover your needs? | AV1: 3.4 - While presenting the product, did the Style Advisor tell you about the brand? | AW1: 3.5 - Additional remarks, if any. | AX1: 3.6 - When you stated your interest in a specific brand, did the Style Advisor respond by asking you questions about your product needs? | AY1: 3.6.1 - If yes, what were the questions asked pertaining to that brand? | AZ1: 4.1 - Were multiple options introduced across the brands as per your needs? | BA1: 4.2 - Did Style Advisor share the current season's inspiration or craftsmanship of the product? | BB1: 4.3 - While showing the options, did the Style Advisor talk about the characteristics of the product and how it will benefit you and meet your needs? (This may include the name of the product, their style, quality or type of material, comfort, etc.) | BC1: 4.4 - Did they briefly share the brand story with you? | BD1: 5.1 - Were you encouraged to touch/feel and try the products? | BE1: 5.2 - Did Style Advisor offer compliments/corrections post-trial? | BF1: 5.3 - Did the Style Advisor offer appropriate recommendations as per your facial characteristics and anatomy? | BG1: 5.4 - Did the Style Advisor clean the sunglasses before the trial? | BH1: 5.5 - Did the Style Advisor use the styling tray and microfiber cloth during the trial and demonstration? | BI1: 5.6 - Did the Style Advisor try to get your feedback as well as give suggestions about the products being shown and tried on? | BJ1: 5.7 - Did the Style Advisor try to up-sell products from different categories? (Recommend product eg New arrivals, festive collections etc)? | BK1: 5.8 - Please mention the details of the product recommended. | BL1: 5.9 - Please share your overall trial experience. | BM1: 6.1 - What objection did you raise during the visit for the recommended product/brand? | BN1: 6.1.1 - If other, please elaborate | BO1: 6.2 - If you raised an objection on a product, did the Style Advisor make an effort to understand the reason for your hesitation? | BP1: 6.3 - Did the Style Advisor answer your objection appropriately and address the concern that you brought up? | BQ1: 6.4 - Did the Style Advisor show you any other product to match your need? | BR1: 7.1 - At the end of the interaction, did the Style Advisor do any of the following? | BS1: 7.1.1 - If other, please specify. | BT1: 7.2 - Did the Style Advisor try to close the sale in a pleasant and positive manner? | BU1: 7.3 - Did the Style Advisor talk about the ongoing offers during the conversation? | BV1: 7.4 - Did the Style Advisor talk about the "Sun Perks" loyalty program? | BW1: 7.5 - Did the Style Advisor talk about the benefits of "Perfect Pair Promise"? | BX1: 7.6 - Did the Style Advisor's attitude change when he/she realized that you would not be buying the product on the same day? | BY1: 7.7 - Did Style Advisor share a reason to come back (possibly including dates for an upcoming collection, any events or offers)? | BZ1: 7.8 - Did the Style Advisor thank you for visiting the store? | CA1: 7.9 - Did Style Advisor accompany you to the exit, bid you farewell in warm manner, and invite you to come back? | CB1: 8.1 - On a scale of 1 to 10, how likely is it that you will come back to the Sunglass Hut? | CC1: 8.2 - Did you find Style Advisor engaging & displaying positive body language during entire conversation? | CD1: 8.3 - On a scale of 1 to 10, rate the Style Advisor on his/her overall assistance during the visit.
A2: 11078689 | B2: 2022-10-01 | C2: 58 | D2: 100 | E2: 56 | F2: 80 | G2: 17 | H2: 50 | I2: 0 | J2: 57 | K2: 100 | L2: Delhi | M2: Delhi (UT) | N2: North | O2: IN | P2: 12:25 | Q2: 12:42 | R2: 1020 | S2: 2 | T2: 5 | U2: 23 | V2: Male | W2: I was wearing a formal shirt and trousers. | X2: Kamal | Y2: Male, approximately 5'10' in height, black hair, wore no spectacles and was wearing an orange coloured branded t-shirt, blue jeansY2:Y61 with casual shoes, clean-shaven and was wearing a mask. | Z2: Yes | AA2: Yes | AB2: Yes | AC2: Yes | AD2: Yes | AE2: No | AF2: Yes | AG2: Yes | AH2: Yes | AI2: The store had a completely wide entrance which made it overall look very appealing. All the sunglasses were arranged correctly with the brand tags. The store was well-lit and did not have any fuse bulbs. The display screens were working and had marketing running for Sunglass Hut. No cartons were seen in the store. Overall, the entire look and feel of the store were very good and I was able to access it freely and explore the same. | AJ2: WOW! Very appealing | AL2: Smile^Eye contact | AM2: After 2 minutes | AN2: Yes | AO2: Yes | AP2: Yes | AQ2: No | AR2: N/A | AS2: Yes | AT2: Yes | AU2: As I mentioned that I was looking for sunglasses for daily wear, the style advisor asked for my preference for sunglasses. I was asked whether I would prefer an aviator or wayfarer or any other style. He also asked if I was looking for any particular brand to which I mentioned that I was open to suggestions and not looking for any specific brand. | AV2: Yes | AW2: The style advisor informed me about the brand name while showing the sunglasses. | AX2: No | AZ2: Yes | BA2: No | BB2: No | BC2: No | BD2: Yes | BE2: No | BF2: Yes | BG2: No | BH2: No | BI2: Yes | BJ2: No | BK2: The products recommended by the style advisor were Aviator from Ray-Ban, Wayfarer from Ray-Ban, Wayfarer from Dolce & Gabbana, and Giorgio Armani. | BL2: The store was busy with 5 customers and only 2 style advisors. Hence, the style advisor was not able to provide complete attention to any customer considering the rush. They were assisting multiple customers in one go. He showed me 3 sunglasses and offered to try them but did not clean them before the trial. When I told him to have a look over more sunglasses, he offered one from Giorgio Armani. After the trial, he confirmed if I liked the same. However, he did not give any remarks on the look from his end. He did not use the styling tray and microfiber cloth during the trial and demonstration. He did not recommend any additional product. | BM2: Discount on the first pair | BO2: No | BP2: No | BQ2: No | BR2: Gave information about the price, payment options | BT2: Yes | BU2: Yes | BV2: No | BW2: No | BX2: No | BY2: N/A | BZ2: Yes | CA2: No | CB2: 8 | CC2: Yes | CD2: 7
A3: 11083235 | B3: 2022-10-08 | C3: 86 | D3: 100 | E3: 100 | F3: 100 | G3: 67 | H3: 75 | I3: 100 | J3: 63 | K3: 100 | L3: Ahmedabad | M3: Gujarat | N3: West | O3: IN | P3: 14:43 | Q3: 15:05 | R3: 1320 | S3: 2 | T3: 3 | U3: 35 | V3: Male | W3: I was wearing a white shirt with blue strips along with blue jeans and casual shoes. | X3: Sanket Patel | Y3: Male, approximately 5'8'' in height, wheatish complexion, black hair, was wearing spectacles, wore the Company branded t-shirt, plain light blue jeans, closed shoes, properly shaved and hairstyle was done in a proper manner. | Z3: Yes | AA3: Yes | AB3: Yes | AC3: Yes | AD3: Yes | AE3: No | AF3: Yes | AG3: Yes | AH3: Yes | AI3: The store exterior signage was clean and well-lit. The store threshold and entrance were looking inviting to customers. All the fixtures, walls, floor, and lights in the store were in good condition. There was light background music playing in the store. There was a digital screen kept outside the store in a proper manner. There were no cartons found lying on the floor in the store. The merchandise was displayed and arranged well on the shelves and display tables. All the merchandise was arranged according to the brand and frame type. At the entrance, I did feel welcomed and the style advisor allowed me to freely move around to explore the store. | AJ3: Good, looks interesting | AL3: Smile^Eye contact^Verbal greeting within 15 seconds | AM3: Within 2 minutes | AN3: Yes | AO3: Yes | AP3: Yes | AQ3: Yes | AR3: N/A | AS3: Yes | AT3: Yes | AU3: The style advisor tried to find my needs by asking which brand I would prefer and if there was any specific style or shape of sunglasses that I was looking for. | AV3: Yes | AW3: The style advisor mentioned the brand like Burberry brand which was a British fashion brand that provided a two-year international warranty. For the Prada brand, the style advisor mentioned that they had two different categories like Prada style and Prada sportswear collection. The style advisor informed me that Prada sunglasses were made in Italy and offered a two-year international warranty. | AX3: Yes | AY3: On showing my interest in the Prada brand of sunglasses, the style advisor tried to find which type, shape, and color shade I would prefer on the sunglasses that I was looking for. The style advisor showcased a couple of options in the Prada brand of sunglasses and offered to try them along with complimenting the looks in a positive manner. | AZ3: Yes | BA3: No | BB3: Yes | BC3: Yes | BD3: Yes | BE3: Yes | BF3: Yes | BG3: Yes | BH3: No | BI3: Yes | BJ3: No | BK3: The style advisor offered different brands like Ray-Ban, Burberry, Prada, and Emporio Armani. The style advisor mentioned the brand like Burberry brand which was a British fashion brand that provided a two-year international warranty. For the Prada brand, the style advisor mentioned that they had two different categories like Prada style and Prada sportswear collection. The style advisor informed me that Prada sunglasses were made in Italy and offered a two-year international warranty. The style advisor showcased the products according to my preference like style, shape, and comfort. | BL3: The style advisor encouraged me to touch and try the products. The style advisor complimented the tried products and offered suggestions looking at my face look. The style advisor cleaned the sunglasses before offering a trial using a microfiber cloth, but there was no styling tray used during the visit. The feedback about the shape and fitting of the sunglasses was captured by the style advisor during the trial. No additional product was offered by the style advisor to complete the look. | BM3: Discount on the first pair | BO3: Yes | BP3: Yes | BQ3: Yes | BR3: Asked if you were ready to purchase today^Offered information on another product to help you decide^Gave information about the price, payment options | BT3: Yes | BU3: Yes | BV3: No | BW3: No | BX3: Yes | BY3: Yes | BZ3: Yes | CA3: Yes | CB3: 8 | CC3: Yes | CD3: 8
A4: 11083324 | B4: 2022-10-14 | C4: 72 | D4: 100 | E4: 100 | F4: 80 | G4: 17 | H4: 75 | I4: 100 | J4: 25 | K4: 100 | L4: Gurgoan | M4: Haryana | N4: North | O4: IN | P4: 12:59 | Q4: 13:17 | R4: 1080 | S4: 3 | T4: 4 | U4: 34 | V4: Male | W4: I was wearing a yellow t-shirt with jeans. | X4: Mahesh | Y4: Male, approximately 5'5' in height, medium build with black hair, and was wearing a branded t-shirt with jeans. | Z4: Yes | AA4: Yes | AB4: Yes | AC4: Yes | AD4: Yes | AE4: No | AF4: Yes | AG4: Yes | AH4: Yes | AI4: The store's ambiance was good and all the lights were working properly. The store looked clean and neat with all the displays arranged properly. The style advisors welcomed the customers properly. | AJ4: WOW! Very appealing | AL4: Smile^Eye contact^Verbal greeting within 15 seconds | AM4: Within 2 minutes | AN4: Yes | AO4: Yes | AP4: Yes | AQ4: Yes | AR4: Yes | AS4: Yes | AT4: Yes | AU4: The style advisor understood my needs properly and asked what I was looking for and whether I was looking for men's or women's sunglasses. | AV4: Yes | AW4: When I showed an interest in Rayban and Bvlgari brands, he showed me various collections from both brands and informed me of their 2-year international warranty. | AX4: No | AZ4: Yes | BA4: No | BB4: No | BC4: No | BD4: Yes | BE4: Yes | BF4: Yes | BG4: Yes | BH4: Yes | BI4: No | BJ4: No | BK4: The style advisor recommended Rayban and Bvlgari sunglasses and told me of their offers and schemes. | BL4: The trial experience was good. He gave me appropriate compliments based on how all the products made me look. He showed me all the models that I had wanted to look at and try. Before the trial, he cleaned all the glasses. No feedback was taken. No additional products were mentioned. | BM4: Expensive products | BO4: Yes | BP4: Yes | BQ4: Yes | BR4: Offered information on another product to help you decide | BT4: Yes | BU4: Yes | BV4: No | BW4: No | BX4: Yes | BY4: No | BZ4: No | CA4: No | CB4: 7 | CC4: Yes | CD4: 8
A5: 11083483 | B5: 2022-10-06 | C5: 84 | D5: 89 | E5: 80 | F5: 80 | G5: 100 | H5: 63 | I5: 100 | J5: 88 | K5: 100 | L5: Jaipur | M5: Rajasthan | N5: North | O5: IN | P5: 15:35 | Q5: 16:06 | R5: 1860 | S5: 2 | T5: 1 | U5: 28 | V5: Male | W5: I was wearing a black shirt with pants. | X5: Sonali | Y5: Female, approximately 5ft in height, fair complexion with medium-length black hair, sdid not wear spectacles and was wearing an orange t-shirt, in her 20s, medium build. | Z5: Yes | AA5: Yes | AB5: Yes | AC5: No | AD5: Yes | AE5: No | AF5: Yes | AG5: Yes | AH5: Yes | AI5: The exterior signage of the outlet was clean and well-lit. The fixtures and other tangibles were in good condition. Music was not played. There was a digital screen outside the store which was operational and there were no cartons lying around the store. The style advisor immediately greeted me as soon as I entered the outlet. | AJ5: WOW! Very appealing | AL5: Smile^Eye contact^Verbal greeting within 15 seconds | AM5: Within 2 minutes | AN5: Yes | AO5: Yes | AP5: Yes | AQ5: No | AR5: No | AS5: Yes | AT5: Yes | AU5: The style advisor asked about my profession and asked whether I was looking at the glasses for myself or for my family members. | AV5: Yes | AW5: N/A | AX5: No | AZ5: Yes | BA5: Yes | BB5: Yes | BC5: Yes | BD5: Yes | BE5: Yes | BF5: Yes | BG5: No | BH5: No | BI5: No | BJ5: Yes | BK5: The style advisor recommended glasses from brands like Versace, Prada, Burberry, Ray-Ban, etc. | BL5: The trial experience could have been more effective had the style advisor helped clean the glasses before the trial but the style advisor did not do so and did not use the styling tray as well. During the trial, the style advisor tried to upsell the products but did not try to get my feedback. | BM5: Expensive products | BO5: Yes | BP5: Yes | BQ5: Yes | BR5: Asked if you were ready to purchase today^Offered information on another product to help you decide^Summarized your needs and matched them to the product recommended^Asked if you had any further questions | BT5: Yes | BU5: Yes | BV5: Yes | BW5: No | BX5: No | BY5: Yes | BZ5: Yes | CA5: Yes | CB5: 10 | CC5: Yes | CD5: 8
A6: 11083490 | B6: 2022-10-18 | C6: 84 | D6: 89 | E6: 80 | F6: 80 | G6: 100 | H6: 63 | I6: 100 | J6: 88 | K6: 100 | L6: Udaipur | M6: Rajasthan | N6: North | O6: IN | P6: 13:55 | Q6: 14:30 | R6: 2100 | S6: 1 | T6: 1 | U6: 28 | V6: Male | W6: I was wearing a grey formal shirt with pants. | X6: Jateen | Y6: Male, approximately 5'5' in height, wheatish complexion, black short hair, did not wear spectacles and was wearing an orange t-shirt, in his 20s, medium build. | Z6: Yes | AA6: Yes | AB6: Yes | AC6: No | AD6: Yes | AE6: No | AF6: Yes | AG6: Yes | AH6: Yes | AI6: The exterior signage of the outlet was clean and well-lit. The fixtures and other tangibles were in good condition. Music was not played. There was no digital screen outside the outlet and there were no cartons lying around. The style advisor immediately greeted me as soon as I entered the store. | AJ6: WOW! Very appealing | AL6: Smile^Eye contact^Verbal greeting within 15 seconds | AM6: Within 2 minutes | AN6: Yes | AO6: Yes | AP6: Yes | AQ6: No | AR6: No | AS6: Yes | AT6: Yes | AU6: The style advisor asked about my profession and also asked if I was looking at the glasses for myself or for my family members. | AV6: Yes | AW6: No additional remarks were made. | AX6: No | AZ6: Yes | BA6: Yes | BB6: Yes | BC6: Yes | BD6: Yes | BE6: No | BF6: Yes | BG6: Yes | BH6: No | BI6: No | BJ6: Yes | BK6: The style advisor recommended sunglasses from the brands like Versace, Prada, Burberry, Ray-Ban, etc. | BL6: The trial experience could have been more effective if the style advisor had used the styling tray and the micro-fiber cloth to clean the glasses before and after the trial. The style advisor did not try to get my feedback after the trial or any time in between the trial as well and neither did the style advisor compliment me on any of the products I had tried on. | BM6: Expensive products | BO6: Yes | BP6: Yes | BQ6: Yes | BR6: Asked if you were ready to purchase today^Offered information on another product to help you decide^Gave information about the price, payment options^Invited you back for more information or another demonstration or test. Gave you their business card or contact information. | BT6: Yes | BU6: Yes | BV6: Yes | BW6: No | BX6: No | BY6: Yes | BZ6: Yes | CA6: Yes | CB6: 9 | CC6: Yes | CD6: 9
A7: 11083658 | B7: 2022-10-12 | C7: 90 | D7: 100 | E7: 100 | F7: 100 | G7: 83 | H7: 88 | I7: 100 | J7: 63 | K7: 100 | L7: Chennai | M7: Tamil Nadu | N7: South | O7: IN | P7: 12:17 | Q7: 12:33 | R7: 960 | S7: 1 | T7: 1 | U7: 60 | V7: Female | W7: I was wearing dark blue jeans with a long maroon-colored top. | X7: Rizwan | Y7: Male, in his mid-late 20s, approximately 5'6' in height, fair complexion, clean-shaven, well-built with black short hair, and was wearing the Company branded orange t-shirt with plain jeans and shoes He had his name tag on. | Z7: Yes | AA7: Yes | AB7: Yes | AC7: Yes | AD7: Yes | AE7: No | AF7: Yes | AG7: Yes | AH7: Yes | AI7: The store was well-maintained and all the frames were arranged according to type and brand. There were no Cartons seen in the customer area, the store was cleaned meticulously. | AJ7: WOW! Very appealing | AL7: Smile^Eye contact^Verbal greeting within 15 seconds | AM7: Within 2 minutes | AN7: Yes | AO7: Yes | AP7: Yes | AQ7: Yes | AR7: N/A | AS7: Yes | AT7: Yes | AU7: The style advisor asked whether I was looking for sunglasses for myself or for someone else. | AV7: Yes | AW7: The style advisor mentioned about brands such as Armani, Prada, Oakley, and more. | AX7: Yes | AY7: The style advisor asked for the type of glasses I was looking for and since I wore progressive glasses, he wanted to know if I could have the lens done at an optic store. | AZ7: Yes | BA7: Yes | BB7: Yes | BC7: No | BD7: Yes | BE7: Yes | BF7: Yes | BG7: Yes | BH7: Yes | BI7: Yes | BJ7: No | BK7: The style advisor recommended shell frames across different brands and showed me Ray-Ban aviators, Prada, D&G, Oakley, Bvlgari, and Oakley. | BL7: The overall trial experience was good. The style advisor recommended shell frames across different brands and showed me Ray-Ban aviators, Prada, D&G, Oakley, Bvlgari, and Oakley. Some of them were oversized; he also mentioned that customizing of the power lenses was not done at the store. The style advisor was very patient and handled all my queries well. I had asked for magnetic frames as well, they had only one from Armani which he showed to me. It was a set of 2 different colored outer frames, red and blue to put on the mainframe. Since the brands were all international brands, he informed me that they were expensive and that they came with an international warranty of 2 years. An additional product was not shown. | BM7: Expensive products | BO7: Yes | BP7: Yes | BQ7: Yes | BR7: Gave information about the price, payment options | BT7: Yes | BU7: Yes | BV7: No | BW7: No | BX7: No | BY7: No | BZ7: Yes | CA7: Yes | CB7: 8 | CC7: Yes | CD7: 8
A8: 11083773 | B8: 2022-10-06 | C8: 36 | D8: 78 | E8: 90 | F8: 0 | G8: 0 | H8: 0 | I8: 0 | J8: 25 | K8: 0 | L8: Mumbai | M8: Maharashtra | N8: West | O8: IN | P8: 17:45 | Q8: 18:00 | R8: 900 | S8: 1 | T8: 1 | U8: 32 | V8: Male | W8: I was wearing formals during my visit. | X8: Mohsin | Y8: Male, approximately 5'5' in height, fair complexion, black hair, was wearing the Company branded t-shirt, plain jeans, shoes, and was not clean shaven. | Z8: Yes | AA8: Yes | AB8: Yes | AC8: No | AD8: No | AE8: No | AF8: Yes | AG8: Yes | AH8: Yes | AI8: The store was clean and well-lit. | AJ8: Good, looks interesting | AL8: Smile^Eye contact^Verbal greeting within 15 seconds | AM8: Within 2 minutes | AN8: Yes | AO8: Yes | AP8: Yes | AQ8: Yes | AR8: No | AS8: No | AT8: No | AU8: The style advisor did not ask me any questions specific to my requirements. | AV8: No | AW8: The product features were not discussed. | AX8: No | AZ8: No | BA8: No | BB8: No | BC8: No | BD8: No | BE8: No | BF8: No | BG8: No | BH8: No | BI8: No | BJ8: No | BK8: The style advisor was just presenting the product. When I asked him if they could customize glasses for my eye power, he said they would not do it. | BL8: The style advisor was unable to solve my questions like customizing eye frames according to my eye power and anti-reflection glasses. | BM8: Discount on the first pair | BO8: No | BP8: No | BQ8: No | BR8: None of the above | BT8: No | BU8: No | BV8: No | BW8: No | BX8: Yes | BY8: No | BZ8: Yes | CA8: Yes | CB8: 5 | CC8: No | CD8: 2
A9: 11083777 | B9: 2022-10-11 | C9: 34 | D9: 78 | E9: 60 | F9: 40 | G9: 0 | H9: 0 | I9: 33 | J9: 13 | K9: 0 | L9: Mumbai | M9: Maharashtra | N9: West | O9: IN | P9: 12:00 | Q9: 12:15 | R9: 900 | S9: 2 | T9: 1 | U9: 32 | V9: Male | W9: I was wearing a black t-shirt with blue colored denim. | X9: Keneth | Y9: Male, approximately 5'9' in height, fair complexion, black hair, clean-shaven, and was wearing a jacket with shoes. | Z9: Yes | AA9: Yes | AB9: Yes | AC9: No | AD9: No | AE9: No | AF9: Yes | AG9: Yes | AH9: Yes | AI9: The store was clean and well-lit. The store did not have a digital screen and there were no cartons lying around the store. Music was not played at the store. | AJ9: Good, looks interesting | AL9: Verbal greeting within 15 seconds | AM9: Within 2 minutes | AN9: Yes | AO9: Yes | AP9: Yes | AQ9: No | AR9: No | AS9: Yes | AT9: No | AU9: The style advisor asked how he could assist me. | AV9: No | AW9: Product features were not discussed. | AX9: No | AZ9: No | BA9: No | BB9: No | BC9: No | BD9: No | BE9: No | BF9: No | BG9: No | BH9: No | BI9: No | BJ9: No | BK9: The style advisor did not recommend anything. | BL9: The style advisor was quite hostile throughout the trial trying to belittle me. The style advisor's behavior was equal to that of a fired employee or even worse than that. | BM9: Discount on the first pair | BO9: No | BP9: Yes | BQ9: No | BR9: None of the above | BT9: No | BU9: No | BV9: No | BW9: No | BX9: No | BY9: No | BZ9: No | CA9: No | CB9: 1 | CC9: No | CD9: 1
A10: 11083778 | B10: 2022-10-12 | C10: 74 | D10: 78 | E10: 90 | F10: 40 | G10: 50 | H10: 100 | I10: 100 | J10: 50 | K10: 100 | L10: Mumbai | M10: Maharashtra | N10: West | O10: IN | P10: 12:00 | Q10: 12:15 | R10: 900 | S10: 1 | T10: 1 | U10: 32 | V10: Male | W10: I was wearing a t-shirt with jeans. | X10: Rakesh | Y10: Male, approximately 5'2' in height, fair complexion with black hair, not shaven, and was wearing the Company branded t-shirt with plain jeans and shoes. | Z10: Yes | AA10: Yes | AB10: Yes | AC10: No | AD10: No | AE10: No | AF10: Yes | AG10: Yes | AH10: Yes | AI10: The store was clean and well-lit. It did not have a digital screen and there was no music playing at the store. | AJ10: Good, looks interesting | AL10: Smile^Eye contact^Verbal greeting within 15 seconds | AM10: Within 2 minutes | AN10: Yes | AO10: Yes | AP10: Yes | AQ10: Yes | AR10: No | AS10: No | AT10: Yes | AU10: The style advisor asked how he could help with my requirements. | AV10: No | AW10: The style advisor mentioned the names of the brand only. | AX10: Yes | AY10: The style advisor asked what type of frames I would be interested in. | AZ10: Yes | BA10: No | BB10: Yes | BC10: No | BD10: Yes | BE10: Yes | BF10: Yes | BG10: Yes | BH10: Yes | BI10: Yes | BJ10: Yes | BK10: The style advisor recommended sunglasses in different frames suitable for my facial structure. | BL10: The style advisor was energetic in their approach and was eager to assist; he presented a variety of frames to try however, more information on the brands could have been provided while presenting the products for trial. The style advisor made use of the styling tray and the micro-fiber cloth to clean the glasses before and even after the trial. | BM10: Discount on the first pair | BO10: Yes | BP10: Yes | BQ10: Yes | BR10: Summarized your needs and matched them to the product recommended | BT10: Yes | BU10: No | BV10: No | BW10: No | BX10: No | BY10: No | BZ10: Yes | CA10: Yes | CB10: 8 | CC10: Yes | CD10: 8
A11: 11083780 | B11: 2022-10-08 | C11: 74 | D11: 78 | E11: 90 | F11: 60 | G11: 17 | H11: 100 | I11: 100 | J11: 63 | K11: 100 | L11: Mumbai | M11: Maharashtra | N11: West | O11: IN | P11: 17:30 | Q11: 17:45 | R11: 900 | S11: 3 | T11: 0 | U11: 32 | V11: Male | W11: T-shirt and jeans | X11: Rashid | Y11: Male, approximately 5'5' in height, fair complexion, black hair, and wore the Company branded t-shirt with plain jeans and shoes. Did not shave. | Z11: Yes | AA11: Yes | AB11: Yes | AC11: No | AD11: No | AE11: No | AF11: Yes | AG11: Yes | AH11: Yes | AI11: The store was clean and well-lit. | AJ11: Good, looks interesting | AL11: Smile^Eye contact^Verbal greeting within 15 seconds | AM11: Within 2 minutes | AN11: Yes | AO11: Yes | AP11: Yes | AQ11: Yes | AR11: No | AS11: Yes | AT11: Yes | AU11: The style advisor asked me how he could help me. | AV11: No | AW11: The product features were not discussed. | AX11: No | AZ11: Yes | BA11: No | BB11: No | BC11: No | BD11: Yes | BE11: Yes | BF11: Yes | BG11: Yes | BH11: Yes | BI11: Yes | BJ11: Yes | BK11: The Style Advisor gave me additional sunglass pairs when I was checking the frames. | BL11: The Style Advisor was energetic in his approach and eager to assist. More information on brands could be provided when he presented the products. | BM11: Discount on the first pair | BO11: Yes | BP11: Yes | BQ11: Yes | BR11: Gave information about the price, payment options | BT11: Yes | BU11: No | BV11: Yes | BW11: No | BX11: No | BY11: No | BZ11: Yes | CA11: Yes | CB11: 8 | CC11: Yes | CD11: 8
A12: 11083781 | B12: 2022-10-12 | C12: 86 | D12: 78 | E12: 80 | F12: 100 | G12: 100 | H12: 100 | I12: 100 | J12: 63 | K12: 100 | L12: Mumbai | M12: Maharashtra | N12: West | O12: IN | P12: 13:34 | Q12: 14:00 | R12: 1560 | S12: 2 | T12: 1 | U12: 32 | V12: Male | W12: I was wearing a t-shirt with denims. | X12: Gaurav | Y12: Male, approximately 5'5' in height, brown complexion, black hair, was wearing a shirt with plain jeans, shoes, and no shave. | Z12: Yes | AA12: Yes | AB12: Yes | AC12: No | AD12: No | AE12: No | AF12: Yes | AG12: Yes | AH12: Yes | AI12: The store was clean and well-lit. The store did not have a digital screen. Music was not played at the store and there were no cartons lying around. | AJ12: Good, looks interesting | AL12: Eye contact^Verbal greeting within 15 seconds | AM12: Within 2 minutes | AN12: Yes | AO12: Yes | AP12: Yes | AQ12: Yes | AR12: No | AS12: Yes | AT12: Yes | AU12: The style advisor asked how he could help me with my requirements. | AV12: Yes | AW12: The style advisor informed me that they had the manufacturing license for Ray-ban. | AX12: Yes | AY12: The style advisor asked if I had any particular product in mind or was looking for from the specific brand. | AZ12: Yes | BA12: Yes | BB12: Yes | BC12: Yes | BD12: Yes | BE12: Yes | BF12: Yes | BG12: Yes | BH12: Yes | BI12: Yes | BJ12: Yes | BK12: The style advisor recommended sunglasses in different frames that would be suitable for my facial structure. | BL12: The style advisor gave additional sunglass pairs for the trial along with the ones I had requested. During the trial, the style advisor used the styling tray and even made sure to clean the glasses with the micro-fiber cloth before handing them to me for the trial. During the trial process, the style advisor even provided proper feedback for each glass. | BM12: Expensive products | BO12: Yes | BP12: Yes | BQ12: Yes | BR12: Summarized your needs and matched them to the product recommended | BT12: Yes | BU12: Yes | BV12: No | BW12: No | BX12: No | BY12: No | BZ12: Yes | CA12: Yes | CB12: 8 | CC12: Yes | CD12: 8
A13: 11083783 | B13: 2022-10-11 | C13: 70 | D13: 78 | E13: 60 | F13: 100 | G13: 50 | H13: 88 | I13: 100 | J13: 38 | K13: 100 | L13: Mumbai | M13: Maharashtra | N13: West | O13: IN | P13: 14:25 | Q13: 14:40 | R13: 900 | S13: 2 | T13: 1 | U13: 32 | V13: Male | W13: I was wearing a t-shirt with denims. | X13: Kiran | Y13: Male, approximately 5'6' in height, fair complexion, black hair, and was wearing the Company brand t-shirt, plain jeans, shoes, and no shave. | Z13: Yes | AA13: Yes | AB13: Yes | AC13: No | AD13: No | AE13: No | AF13: Yes | AG13: Yes | AH13: Yes | AI13: The store was clean and well-lit as the area manager was present in the store. The store did not have a digital screen and did not have any music playing inside. There were no cartons lying around. | AJ13: Good, looks interesting | AL13: Verbal greeting within 15 seconds | AM13: Within 2 minutes | AN13: Yes | AO13: Yes | AP13: Yes | AQ13: No | AR13: No | AS13: Yes | AT13: Yes | AU13: The style advisor asked how he could help me. | AV13: Yes | AW13: The style advisor informed me about the Ferrari and Ray-ban collaboration. | AX13: Yes | AY13: The style advisor asked about my specific requirements. | AZ13: Yes | BA13: No | BB13: Yes | BC13: No | BD13: Yes | BE13: Yes | BF13: Yes | BG13: Yes | BH13: Yes | BI13: Yes | BJ13: No | BK13: The product details were not mentioned. The current season's inspiration was not shared. | BL13: Since the area manager was present, there was no issue with the trial. The style advisor was energetic and eager to assist. The style advisor gave me multiple sunglasses for the trial while I checked the frames. The style advisor could work on providing more information about the products when presenting them for the trial. The style advisor used the styling tray and cleaned the glasses before and after the trial as well. | BM13: Discount on the first pair | BO13: Yes | BP13: Yes | BQ13: Yes | BR13: Summarized your needs and matched them to the product recommended | BT13: Yes | BU13: Yes | BV13: No | BW13: No | BX13: No | BY13: No | BZ13: No | CA13: No | CB13: 8 | CC13: Yes | CD13: 8
A14: 11083867 | B14: 2022-10-08 | C14: 84 | D14: 89 | E14: 89 | F14: 80 | G14: 83 | H14: 100 | I14: 100 | J14: 50 | K14: 100 | L14: Bangalore | M14: Karnataka | N14: South | O14: IN | P14: 16:39 | Q14: 17:04 | R14: 1500 | S14: 2 | T14: 3 | U14: 40 | V14: Male | W14: I was wearing a black jeans with red and blue shorts. | X14: Sanit Saji | Y14: Male, tall in height, fair complexion, clean-shaven, was wearing an orange t-shirt, thin build. | Z14: Yes | AA14: Yes | AB14: Yes | AC14: No | AD14: Yes | AE14: No | AF14: Yes | AG14: Yes | AH14: Yes | AI14: It was easy to locate the store. The exterior and the interior of the store were well maintained and the signage of the store was visible even from a certain distance. It was well-lit and the exterior was neat and clean. Overall, the store looked very appealing. There was no music playing in the store and also there was a digital screen being played behind the cash counter area. There were no unwanted and unattended cartons seen at the store. The sunglass merchandise was displayed and organized very well. There was enough space to move and look around the displayed merchandise. The product was arranged according to the brand and the arrangement was also done according to the pattern. | AJ14: WOW! Very appealing | AL14: Smile^Eye contact^Verbal greeting within 15 seconds | AM14: Within 2 minutes | AN14: Yes | AO14: Yes | AP14: Yes | AQ14: No | AR14: N/A | AS14: Yes | AT14: Yes | AU14: The style advisor asked me about the style of frame I would prefer and whether the purchase was for formal or casual wear. The style advisor also inquired if I had any budget constraints and asked about my preference for the glass shades. | AV14: Yes | AW14: No additional remarks were made. | AX14: No | AZ14: Yes | BA14: Yes | BB14: Yes | BC14: No | BD14: Yes | BE14: Yes | BF14: Yes | BG14: Yes | BH14: Yes | BI14: Yes | BJ14: Yes | BK14: The style advisor recommended the Armani glasses in a blue shade with silver rims and a black shade with an adjustable nose bridge. | BL14: The style advisor encouraged me to touch and try the shortlisted products. The style advisor even wiped them with the micro-fiber cloth before handing the products to me. The Armani glass was in size XL which was a little loose but the style advisor assured me that the nose pads were adjustable. The style advisor then proceeded to show me the Ray-Ban aviator glasses which the style advisor suggested that I should try as they were the best suited for my facial structure. | BM14: Expensive products | BO14: Yes | BP14: Yes | BQ14: Yes | BR14: Offered information on another product to help you decide^Summarized your needs and matched them to the product recommended | BT14: Yes | BU14: Yes | BV14: No | BW14: No | BX14: No | BY14: No | BZ14: Yes | CA14: No | CB14: 9 | CC14: Yes | CD14: 9
A15: 11083988 | B15: 2022-10-15 | C15: 78 | D15: 78 | E15: 100 | F15: 80 | G15: 83 | H15: 50 | I15: 100 | J15: 63 | K15: 100 | L15: Hyderabad | M15: Telangana | N15: South | O15: IN | P15: 17:41 | Q15: 18:15 | R15: 2040 | S15: 2 | T15: 1 | U15: 28 | V15: Male | W15: I was wearing a t-shirt with jeans. | X15: Asif | Y15: Male, approximately 5'6' in height, thin and medium build with a fair complexion, black hair, and a beard. He must have been around 28years old. He was wearing the Company branded t-shirt with plain jeans and he did not have any spectacles on. | Z15: Yes | AA15: Yes | AB15: Yes | AC15: No | AD15: No | AE15: No | AF15: Yes | AG15: Yes | AH15: Yes | AI15: The store was small but the arrangement of the furniture and merchandise was set in a way that made it possible to roam around the store freely. There was no music playing and the digital screen at the entrance was not operational. | AJ15: Good, looks interesting | AL15: Smile^Eye contact^Verbal greeting within 15 seconds | AM15: Within 2 minutes | AN15: Yes | AO15: Yes | AP15: Yes | AQ15: Yes | AR15: N/A | AS15: Yes | AT15: Yes | AU15: The style advisor did not ask any questions, he simply answered to the ones I asked | AV15: Yes | AW15: The style advisor was proactive and tried to convince me to buy the sunglasses. | AX15: No | AZ15: Yes | BA15: Yes | BB15: Yes | BC15: No | BD15: Yes | BE15: Yes | BF15: Yes | BG15: No | BH15: No | BI15: No | BJ15: No | BK15: No additional products were recommended to me. | BL15: I tried around 4 to 5 spectacles, which the style advisor did not clean before the trial. I had asked him which one of the spectacles suited me the best, to which he recommended that the Ray-Ban spectacles were the best for my facial structure. | BM15: Discount on the first pair | BO15: Yes | BP15: Yes | BQ15: Yes | BR15: Offered information on another product to help you decide^Gave information about the price, payment options^Other (please specify) | BS15: The style advisor gave the details of discounts and offers. | BT15: Yes | BU15: Yes | BV15: No | BW15: No | BX15: No | BY15: No | BZ15: Yes | CA15: Yes | CB15: 9 | CC15: Yes | CD15: 8
A16: 11084277 | B16: 2022-10-08 | C16: 61 | D16: 78 | E16: 67 | F16: 60 | G16: 83 | H16: 38 | I16: 67 | J16: 38 | K16: 100 | L16: Pune | M16: Maharashtra | N16: West | O16: IN | P16: 14:23 | Q16: 14:51 | R16: 1680 | S16: 3 | T16: 1 | U16: 31 | V16: Male | W16: I was wearing a black t-shirt with blue jeans. | X16: Yasin Kaif | Y16: Male, approximately 5'7'' in height, fair complexion, and was wearing the Company branded t-shirt. | Z16: Yes | AA16: Yes | AB16: Yes | AC16: No | AD16: No | AE16: No | AF16: Yes | AG16: Yes | AH16: Yes | AI16: The Sunglass Hut store was present on the ground floor of the Westend Mall. The signage was well-lit and hence it was visible from a long distance. The entrance had a standee that mentioned the ongoing offer which was a 25% off on the 2nd pair. The exterior of the store façade was all glass and smudge-free. I did not observe any kind of litter in the store. The store looked well-maintained and clean. All the products were arranged according to their brand. However, I was not sure whether they were arranged according to the frame or not. | AJ16: Good, looks interesting | AL16: Smile^Verbal greeting within 15 seconds | AM16: Within 2 minutes | AN16: Yes | AO16: No | AP16: Yes | AQ16: No | AR16: N/A | AS16: Yes | AT16: Yes | AU16: There were no questions asked by the style advisor. | AV16: No | AW16: The style advisor informed us about the 2-year warranty that the product would come with 6 months of replacement coverage, and also informed us that the warranty was applicable across the globe. | AX16: No | AZ16: Yes | BA16: Yes | BB16: Yes | BC16: No | BD16: Yes | BE16: No | BF16: No | BG16: Yes | BH16: Yes | BI16: No | BJ16: No | BK16: The style advisor recommended two products. One was from Versace and another one was from Micheal Kors. Regarding the Versace shades, the style advisor said that they were made of specially engineered material that made them lightweight. Also, that was the reason for it being expensive. Moreover, they were offering an international warranty on it too. It was manufactured by Luxottica. Not many details were given for the Michael Kors one since we were interested in them. | BL16: Since there were no questions from the style advisor, we proactively mentioned that we were looking for cat-eyed frames. After this, the style advisor recommended us multiple products, including products from the brands like Michael Kors and Versace. There were no budget or style-related questions from the style advisor as well. The style advisor encouraged us to touch/feel and try the products only after we had asked if we could try them on. He did not proactively initiate it. The style advisor also told us about the materials that were used in the products and their durability as well. | BM16: Expensive products | BO16: Yes | BP16: Yes | BQ16: No | BR16: Gave information about the price, payment options | BT16: Yes | BU16: Yes | BV16: No | BW16: No | BX16: No | BY16: No | BZ16: No | CA16: No | CB16: 8 | CC16: Yes | CD16: 8
A17: 11084762 | B17: 2022-10-06 | C17: 78 | D17: 89 | E17: 100 | F17: 80 | G17: 50 | H17: 88 | I17: 67 | J17: 50 | K17: 100 | L17: Mumbai | M17: Maharashtra | N17: West | O17: IN | P17: 16:52 | Q17: 17:30 | R17: 2280 | S17: 02 | T17: 1 | U17: 57 | V17: Male | W17: I was wearing a red and black check shirt, pants, shoes, and spectacles. | X17: Bablu | Y17: Male, approximately 5'6' in height, fair complexion, black hair, was wearing the Company branded t-shirt, plain jeans, shoes, clean shaven and hairstyle done. | Z17: Yes | AA17: Yes | AB17: Yes | AC17: Yes | AD17: No | AE17: No | AF17: Yes | AG17: Yes | AH17: Yes | AI17: The store was neat and clean during the visit. The exterior signage was clean and shiny. Overall, the various brands of sunglasses were displayed beautifully brand-wise. | AJ17: Good, looks interesting | AL17: Smile^Eye contact^Verbal greeting within 15 seconds | AM17: Within 2 minutes | AN17: Yes | AO17: Yes | AP17: Yes | AQ17: Yes | AR17: N/A | AS17: Yes | AT17: Yes | AU17: The style advisor asked me what I was looking for. | AV17: Yes | AW17: No additional remarks were made. | AX17: No | AZ17: Yes | BA17: No | BB17: Yes | BC17: No | BD17: Yes | BE17: Yes | BF17: Yes | BG17: No | BH17: Yes | BI17: Yes | BJ17: Yes | BK17: The style advisor mainly recommended Prada sunglass in different colors and shapes. He showed me the products and asked for a trial of the sunglasses and I did the same. The Prada sunglass was gray and dark in color. The RayBan sunglass was light grey. | BL17: The style advisor assisted me properly during the visit. He encouraged me to try on different sunglasses during the visit and I made the trial of sunglasses accordingly. The focused brand was Prada sunglasses from the style advisor's side. As per my discussion, the style advisor also showed me RayBan sunglasses. Overall, my experience was good. | BM17: Expensive products | BO17: Yes | BP17: No | BQ17: Yes | BR17: Offered information on another product to help you decide^Gave information about the price, payment options | BT17: Yes | BU17: No | BV17: No | BW17: Yes | BX17: No | BY17: No | BZ17: Yes | CA17: No | CB17: 8 | CC17: Yes | CD17: 8
A18: 11084763 | B18: 2022-10-11 | C18: 89 | D18: 89 | E18: 100 | F18: 80 | G18: 83 | H18: 88 | I18: 67 | J18: 100 | K18: 100 | L18: Mumbai | M18: Maharashtra | N18: West | O18: IN | P18: 17:24 | Q18: 18:04 | R18: 2400 | S18: 2 | T18: 1 | U18: 57 | V18: Male | W18: I was wearing a colorful shirt with pants and shoes. | X18: Nagraj | Y18: Male, approximately 5'5' in height, light fair complexion, black hair, and was wearing the Sunglass branded t-shirt, pants, and shoes, clean-shaven, with a proper hairstyle, style advisor had an ID card. | Z18: Yes | AA18: Yes | AB18: Yes | AC18: No | AD18: Yes | AE18: No | AF18: Yes | AG18: Yes | AH18: Yes | AI18: The store looked attractive and appealing to the eyes. The store was spacious enough to move freely. There was no music being played and no cartons were lying around. | AJ18: Good, looks interesting | AL18: Smile^Eye contact^Verbal greeting within 15 seconds | AM18: Within 2 minutes | AN18: Yes | AO18: Yes | AP18: Yes | AQ18: Yes | AR18: N/A | AS18: Yes | AT18: Yes | AU18: The Style Advisor asked if I was looking for sunglasses for someone in particular. | AV18: Yes | AW18: The Style Advisor mentioned that the sunglasses were of good quality. | AX18: No | AZ18: Yes | BA18: Yes | BB18: Yes | BC18: No | BD18: Yes | BE18: Yes | BF18: Yes | BG18: Yes | BH18: Yes | BI18: Yes | BJ18: No | BK18: Sunglasses from Ray-Ban and Prada were recommended. | BL18: The overall trial experience for the sunglasses was very nice and I was happy with it. The style advisor offered Ray-ban sunglasses for the trial and mentioned that they were the perfect high-quality UV-protected sunglasses that provided clarity as well. The style advisor showed me different sunglasses in colors such as wine red, brown, green, etc in metal as well as the fiber material. The next item, the style advisor offered for the trial was from the luxury brand, Prada, it had a rich feel to it. The glasses looked good when I checked in the mirror at the store. An additional product to purchase that would complete the look was not recommended to me. The brand story was not told to me. The styling tray was used and the glasses were cleaned before and after the trial. | BM18: Discount on the first pair | BO18: No | BP18: Yes | BQ18: Yes | BR18: Asked if you were ready to purchase today^Gave information about the price, payment options^Invited you back for more information or another demonstration or test. Gave you their business card or contact information. | BT18: Yes | BU18: Yes | BV18: Yes | BW18: Yes | BX18: No | BY18: N/A | BZ18: Yes | CA18: N/A | CB18: 8 | CC18: Yes | CD18: 8
A19: 11084781 | B19: 2022-10-13 | C19: 65 | D19: 89 | E19: 89 | F19: 80 | G19: 50 | H19: 25 | I19: 33 | J19: 63 | K19: 100 | L19: Cochin | M19: Kerala | N19: South | O19: IN | P19: 15:05 | Q19: 15:30 | R19: 1500 | S19: 2 | T19: 1 | U19: 42 | V19: Male | W19: I was wearing a formal shirt and trousers. | X19: Ashish | Y19: Male approximately 5'11'' in height, wore spectacles, fair complexion with black hair, and was wearing a casual shirt with blue jeans. | Z19: Yes | AA19: Yes | AB19: Yes | AC19: No | AD19: Yes | AE19: No | AF19: Yes | AG19: Yes | AH19: Yes | AI19: The store signage was clean and well-maintained. The store was cluttered-free, and the entrance and fixtures were all in good condition. There was no music playing but the digital screen at the entrance worked well and all the merchandise was arranged and displayed properly in the drawers and shelves. | AJ19: Good, looks interesting | AL19: Smile^Eye contact^Verbal greeting within 15 seconds | AM19: Within 2 minutes | AN19: Yes | AO19: Yes | AP19: Yes | AQ19: No | AR19: N/A | AS19: Yes | AT19: Yes | AU19: The style advisor asked about the particular brand I was looking for. | AV19: Yes | AW19: While suggesting the products, the style advisor mentioned only the brand names. | AX19: No | AZ19: Yes | BA19: Yes | BB19: No | BC19: No | BD19: Yes | BE19: No | BF19: No | BG19: No | BH19: No | BI19: No | BJ19: Yes | BK19: Since the aviators from Ray-Ban that I mentioned were out of stock, the style advisor recommended aviator glasses from other brands. | BL19: The style advisor had me try on the glasses that I had shown an interest in. During the trial, he did not use the styling tray or the micro-fiber cloth to clean the glasses before or even after the trial. The style advisor did not give any suggestions or compliments during the trial session. I was not offered compliments. Appropriate recommendations were not offered as per my facial characteristics. | BM19: Discount on the first pair | BO19: No | BP19: No | BQ19: Yes | BR19: Offered information on another product to help you decide^Gave information about the price, payment options | BT19: Yes | BU19: Yes | BV19: No | BW19: No | BX19: No | BY19: Yes | BZ19: Yes | CA19: No | CB19: 6 | CC19: Yes | CD19: 6
A20: 11084784 | B20: 2022-10-06 | C20: 76 | D20: 89 | E20: 89 | F20: 80 | G20: 50 | H20: 75 | I20: 100 | J20: 63 | K20: 0 | L20: Ludhiana | M20: Punjab | N20: North | O20: IN | P20: 12:45 | Q20: 13:10 | R20: 1500 | S20: 1 | T20: 1 | U20: 43 | V20: Male | W20: I was wearing a off white shirt with brown trousers. | X20: Sunil | Y20: Male, approximately 5'7' in height, fair complexion, black hair, wore no spectacles, was wearing the Company branded t-shirt, plain jeans, shoes, was clean shaven and hairstyle done. | Z20: Yes | AA20: Yes | AB20: Yes | AC20: Yes | AD20: No | AE20: No | AF20: Yes | AG20: Yes | AH20: Yes | AI20: The exterior signage was clean and well lit. All the fixtures and other tangibles were in good condition. The merchandise was displayed and arranged well. | AJ20: Good, looks interesting | AL20: Smile^Eye contact^Verbal greeting within 15 seconds | AM20: Within 2 minutes | AN20: Yes | AO20: Yes | AP20: Yes | AQ20: No | AR20: N/A | AS20: Yes | AT20: Yes | AU20: The style advisor asked me about my brand choice and colour. | AV20: Yes | AW20: None | AX20: No | AZ20: Yes | BA20: No | BB20: Yes | BC20: No | BD20: Yes | BE20: No | BF20: Yes | BG20: Yes | BH20: Yes | BI20: No | BJ20: Yes | BK20: The style advisor recommended goggles in case of different types of shapes. | BL20: My trial experience was good because the style advisor offered me proactively different brands and color goggles for the trial. | BM20: Discount on the first pair | BO20: Yes | BP20: Yes | BQ20: Yes | BR20: Asked if you were ready to purchase today^Summarized your needs and matched them to the product recommended^Asked if you had any further questions^Gave information about the price, payment options | BT20: Yes | BU20: Yes | BV20: No | BW20: No | BX20: No | BY20: Yes | BZ20: Yes | CA20: No | CB20: 8 | CC20: No | CD20: 8
A21: 11084789 | B21: 2022-10-10 | C21: 82 | D21: 89 | E21: 90 | F21: 80 | G21: 50 | H21: 88 | I21: 100 | J21: 75 | K21: 100 | L21: Amritsar | M21: Punjab | N21: North | O21: IN | P21: 12:55 | Q21: 13:16 | R21: 1260 | S21: 3 | T21: 1 | U21: 43 | V21: Male | W21: I was wearing a navy pant and shirt. | X21: Kamal | Y21: Male, approximately 5'7'' in height, fair complexion, black hair, wore no spectacles, was wearing the Company branded uniform with plain jeans and shoes, clean-shaven, the hairstyle was done in a proper manner. | Z21: Yes | AA21: Yes | AB21: Yes | AC21: Yes | AD21: No | AE21: No | AF21: Yes | AG21: Yes | AH21: Yes | AI21: The store ambiance was good and there were no cartons lying around. The store did not have a digital screen. | AJ21: Good, looks interesting | AL21: Smile^Eye contact^Verbal greeting within 15 seconds | AM21: Within 2 minutes | AN21: Yes | AO21: Yes | AP21: Yes | AQ21: Yes | AR21: No | AS21: Yes | AT21: Yes | AU21: The style advisor asked about my choice of brands, style and my glass preference for the purchase. | AV21: Yes | AW21: The style advisor showed me goggles from the Ray-ban, Emporio Armani, D&G, and Prada brands in polaroid and UV glasses and in different types of shapes. | AX21: No | AZ21: Yes | BA21: No | BB21: Yes | BC21: No | BD21: Yes | BE21: Yes | BF21: Yes | BG21: Yes | BH21: Yes | BI21: No | BJ21: Yes | BK21: The style advisor recommended the goggles cleaning kits in different types of shapes. | BL21: My overall trial experience was good. The style advisor encouraged me to touch/feel and try the products from the different brands. The style advisor offered appropriate recommendations for goggles as per my facial structure but did not try to get my feedback on them. The style advisor used the styling tray and microfiber cloth during the trial and demonstration. The style advisor did not try to get my feedback. | BM21: Expensive products | BO21: Yes | BP21: Yes | BQ21: Yes | BR21: Offered information on another product to help you decide^Gave information about the price, payment options^Invited you back for more information or another demonstration or test. Gave you their business card or contact information. | BT21: Yes | BU21: Yes | BV21: No | BW21: No | BX21: No | BY21: Yes | BZ21: Yes | CA21: Yes | CB21: 9 | CC21: Yes | CD21: 9
A22: 11084792 | B22: 2022-10-10 | C22: 88 | D22: 89 | E22: 100 | F22: 100 | G22: 83 | H22: 88 | I22: 100 | J22: 63 | K22: 100 | L22: Amritsar | M22: Punjab | N22: North | O22: IN | P22: 14:10 | Q22: 14:35 | R22: 1500 | S22: 3 | T22: 1 | U22: 40 | V22: Male | W22: I was wearing a blue trouser and shirt. | X22: Neeraj | Y22: Male, approximately 5'7'' in height, wheatish complexion, black hair, did not wear spectacles, was wearing the Company branded shirt with plain jeans and shoes, had no beard, and the hairstyle was done in a proper manner. | Z22: Yes | AA22: Yes | AB22: Yes | AC22: Yes | AD22: No | AE22: No | AF22: Yes | AG22: Yes | AH22: Yes | AI22: The store did not have a digital screen. The exterior signage was clean and well-lit. All the fixtures and other tangibles were in good condition. The merchandise was displayed and arranged well. | AJ22: Good, looks interesting | AL22: Smile^Eye contact^Verbal greeting within 15 seconds | AM22: Within 2 minutes | AN22: Yes | AO22: Yes | AP22: Yes | AQ22: Yes | AR22: Yes | AS22: Yes | AT22: Yes | AU22: The style advisor asked what brands, and styles I was interested in and my preference for the goggles. | AV22: Yes | AW22: No additional remarks were made. | AX22: Yes | AY22: The style advisor asked the reason for my choice regarding the brand and wanted to know what type and color of glasses I would like to see for the purchase. | AZ22: Yes | BA22: Yes | BB22: Yes | BC22: No | BD22: Yes | BE22: Yes | BF22: Yes | BG22: Yes | BH22: Yes | BI22: No | BJ22: Yes | BK22: The style advisor recommended the goggle cleaning kit that came in different shapes. | BL22: My overall trial experience was very good because the style advisor encouraged me to touch and try the products. The style advisor even offered appropriate recommendations as per my facial structure but did not try to get my feedback. During the trial period, he made sure to use the styling tray and the micro-fiber cloth to clean the products as well. | BM22: Discount on the first pair | BO22: Yes | BP22: Yes | BQ22: Yes | BR22: Asked if you were ready to purchase today^Offered information on another product to help you decide^Summarized your needs and matched them to the product recommended^Gave information about the price, payment options^Invited you back for more information or another demonstration or test. Gave you their business card or contact information. | BT22: Yes | BU22: Yes | BV22: No | BW22: No | BX22: Yes | BY22: Yes | BZ22: Yes | CA22: Yes | CB22: 9 | CC22: Yes | CD22: 9
A23: 11084844 | B23: 2022-10-08 | C23: 71 | D23: 100 | E23: 67 | F23: 80 | G23: 50 | H23: 88 | I23: 0 | J23: 57 | K23: 100 | L23: Delhi | M23: Delhi (UT) | N23: North | O23: IN | P23: 17:15 | Q23: 17:43 | R23: 1680 | S23: 4 | T23: 2 | U23: 52 | V23: Male | W23: I wore a polo t-shirt along with jeans and sneakers. | X23: Sanjeev | Y23: Male, approximately 5'11' in height, fair complexion, black hair, was wearing a black and white suit, wore spectacles, and had a beard. | Z23: Yes | AA23: Yes | AB23: Yes | AC23: Yes | AD23: Yes | AE23: No | AF23: Yes | AG23: Yes | AH23: Yes | AI23: The exterior, signage, and windows of the store were well-maintained and properly set. It had a good appealing look. There was light music playing in the store. There were no cartons or clutter lying in the store. All the merchandise was completely set with proper brand tagging and the store had a wide entrance making it very easy to explore the store. | AJ23: WOW! Very appealing | AL23: Eye contact | AM23: Within 2 minutes | AN23: Yes | AO23: Yes | AP23: Yes | AQ23: No | AR23: N/A | AS23: Yes | AT23: Yes | AU23: I asked about the style of the sunglasses, colour and the shade of the lens. | AV23: Yes | AW23: Only the brand names were informed. | AX23: No | AZ23: Yes | BA23: No | BB23: Yes | BC23: No | BD23: Yes | BE23: Yes | BF23: Yes | BG23: Yes | BH23: Yes | BI23: Yes | BJ23: No | BK23: The products recommended were Ray-Ban aviators, Burberry wayfarer, and Dolce & Gabbana wayfarer. | BL23: Based on my face cut, the style advisor suggested Ray-Ban and also mentioned that I would get the best money value if I would go for Aviators, especially with the wide variety of options that were available. He showed me 2 of them, cleaned them, and offered to try them. He also cleaned the Burberry and D&C glasses and offered to try them as well. He complimented me that Ray Ban looked the best on me and asked if I felt the same. He used the microfiber cloth and tray during the interaction. | BM23: Discount on the first pair | BO23: No | BP23: No | BQ23: No | BR23: Asked if you were ready to purchase today^Gave information about the price, payment options | BT23: Yes | BU23: No | BV23: No | BW23: No | BX23: No | BY23: N/A | BZ23: Yes | CA23: Yes | CB23: 8 | CC23: Yes | CD23: 8
A24: 11084845 | B24: 2022-10-08 | C24: 67 | D24: 89 | E24: 78 | F24: 80 | G24: 50 | H24: 75 | I24: 0 | J24: 43 | K24: 100 | L24: Delhi | M24: Delhi (UT) | N24: North | O24: IN | P24: 16:35 | Q24: 16:52 | R24: 1020 | S24: 4 | T24: 2 | U24: 52 | V24: Male | W24: I wore a polo t-shirt along with jeans and sneakers. | X24: Neeraj | Y24: Male, approximately 5'9' in height, fair complexion, black hair, wore an orange t-shirt with plain jeans and casual shoes, wore no spectacles, and had a light beard. | Z24: Yes | AA24: Yes | AB24: Yes | AC24: No | AD24: Yes | AE24: No | AF24: Yes | AG24: Yes | AH24: Yes | AI24: The ambiance and exterior of the store were very good. All the fixtures were in working condition without any issues. All the shelves and racks were properly set and had an attractive look. All the merchandise had the proper brand signage. The store was very open and airy. I was able to feel and explore the store easily. There was no music playing in the store. Also, there were no cartons or clutter lying in the store. | AJ24: WOW! Very appealing | AL24: Smile^Eye contact | AM24: Within 2 minutes | AN24: Yes | AO24: Yes | AP24: Yes | AQ24: No | AR24: N/A | AS24: Yes | AT24: Yes | AU24: The style advisor asked about my requirements and asked whether I was looking for any specific brand. He also asked about my preferred style of sunglasses. | AV24: Yes | AW24: The style advisor informed me about the brand while showing the glasses. | AX24: No | AZ24: Yes | BA24: No | BB24: Yes | BC24: No | BD24: Yes | BE24: Yes | BF24: Yes | BG24: Yes | BH24: Yes | BI24: No | BJ24: No | BK24: The style advisor recommended the Burberry, Gucci & Ray Ban brands. He encouraged me to touch/feel and try the products. The style advisor cleaned the sunglasses before the trial. | BL24: The style advisor recommended Burberry and mentioned its price. After that, he showed me sunglasses from Prada and mentioned their price as well. After that, he asked to confirm what my budget would be to which I assured him that my budget would not be a concern and that I was open to suggestions. After this, he suggested the Gucci glasses as well as the Ray-Ban. After showing them all, he kept them on the tray and offered them for me to try the same. He cleaned them before keeping them back on the tray. After the trial, he complimented me that Ray-Ban would look the best on me based on my facial structure and also informed me that the lens quality was awesome and that I should consider it. | BM24: Discount on the first pair | BO24: No | BP24: No | BQ24: No | BR24: Summarized your needs and matched them to the product recommended^Gave information about the price, payment options | BT24: Yes | BU24: No | BV24: No | BW24: No | BX24: No | BY24: N/A | BZ24: Yes | CA24: No | CB24: 8 | CC24: Yes | CD24: 8
A25: 11084846 | B25: 2022-10-08 | C25: 60 | D25: 78 | E25: 78 | F25: 60 | G25: 50 | H25: 38 | I25: 67 | J25: 43 | K25: 100 | L25: Delhi | M25: Delhi (UT) | N25: North | O25: IN | P25: 13:30 | Q25: 13:46 | R25: 960 | S25: 2 | T25: 1 | U25: 52 | V25: Male | W25: Wore a polo t-shirt along with jeans & sneakers | X25: Ajeet | Y25: Male, approximately 5'10' in height, was slim with black hair set in a proper hairstyle. He wore an orange Company uniform t-shirt and he did not have any specs on. | Z25: Yes | AA25: Yes | AB25: Yes | AC25: No | AD25: No | AE25: No | AF25: Yes | AG25: Yes | AH25: Yes | AI25: The store was clean, well-lit, and well-maintained. The store had a wide entrance and had a good first impression. I did not observe any digital board during my visit. There was no music playing in the store during my visit. The lights, fixtures, and furniture were in good condition without any issues. Overall, the merchandise arrangement was good and the store did not have any clutter. The glasses were arranged as per the brands and frame types. | AJ25: WOW! Very appealing | AL25: Smile^Eye contact | AM25: Within 2 minutes | AN25: Yes | AO25: Yes | AP25: Yes | AQ25: No | AR25: N/A | AS25: Yes | AT25: Yes | AU25: The style advisor asked me about the style of glasses that I was interested in such as Aviator or Wayfarer and also the colour of the lenses and whether I wanted polaroid or non-polaroid glasses. | AV25: No | AW25: While the style advisor showed me the glasses, he did not introduce the brand name. I had to proactively ask about the same from him. | AX25: No | AZ25: Yes | BA25: No | BB25: Yes | BC25: No | BD25: Yes | BE25: No | BF25: Yes | BG25: No | BH25: No | BI25: No | BJ25: No | BK25: The style advisor recommended the Rayban Wayfarer, Burberry & Armani glasses. He encouraged me to touch/feel and try the products. | BL25: The style advisor offered me Ray Ban Aviator sunglasses and told me that these were light-colored polaroid glasses which were very rare and looked very good. He offered them for me to try but did not clean the same before the trial. He did not suggest/compliment me after trying. However, he did inform me that based on my facial structure, I should go with Wayfarer or Aviator. He informed me that they had multiple options and showed me Wayfarer glasses as well. He also told me that they would go very well with a formal look. He did not recommend me any additional product. The style advisor did not use any tray while showing me glasses during my visit. After this, he offered me to try Ray-Ban, Wayfarer but again did not clean the same. He also informed me that they had Gucci, and Armani as well which were more premium but Ray-Ban had a better perspective as they made sunglasses and the lens of the best quality. He also showed me sunglasses from the new Burberry collection but did not offer me to try them. | BM25: Discount on the first pair | BO25: Yes | BP25: Yes | BQ25: No | BR25: Asked if you were ready to purchase today^Summarized your needs and matched them to the product recommended^Gave information about the price, payment options | BT25: Yes | BU25: No | BV25: No | BW25: No | BX25: No | BY25: N/A | BZ25: Yes | CA25: No | CB25: 8 | CC25: Yes | CD25: 8
A26: 11084847 | B26: 2022-10-08 | C26: 81 | D26: 89 | E26: 89 | F26: 80 | G26: 83 | H26: 75 | I26: 67 | J26: 71 | K26: 100 | L26: Delhi | M26: Delhi (UT) | N26: North | O26: IN | P26: 15:18 | Q26: 15:38 | R26: 1200 | S26: 3 | T26: 1 | U26: 52 | V26: Male | W26: I wore a polo t-shirt along with jeans and sneakers. | X26: Deepak | Y26: Male, approximately 5'8' in height, fair complexion, black hair, wore an orange t-shirt with plain jeans. | Z26: Yes | AA26: Yes | AB26: Yes | AC26: No | AD26: Yes | AE26: No | AF26: Yes | AG26: Yes | AH26: Yes | AI26: The store was neat, clean, and well-lit. All the lightings and fixtures were in good condition and did not have any issues. All the merchandising was done appropriately and the glasses were placed as per branding with proper signage. There was no music playing in the store and there were no cartons or clutter lying in the store. The store entrance was wide and I was able to freely explore the store. The store was well lit which helped me have a good look at the display. | AJ26: WOW! Very appealing | AL26: Smile^Eye contact^Verbal greeting within 15 seconds | AM26: Within 2 minutes | AN26: Yes | AO26: Yes | AP26: Yes | AQ26: No | AR26: N/A | AS26: Yes | AT26: Yes | AU26: The style advisor asked me about the shape, and color of the sunglasses and if there was any specific brand I was looking for. | AV26: Yes | AW26: While showing the first product of Ray-Ban, the style advisor informed me that this was the Ray-Ban Aviator with Gun Metal shade since 1952. | AX26: No | AZ26: Yes | BA26: Yes | BB26: Yes | BC26: No | BD26: Yes | BE26: No | BF26: Yes | BG26: Yes | BH26: Yes | BI26: Yes | BJ26: No | BK26: The style advisor suggested the Gucci, Giorgio Armani, and Burberry brands. He encouraged me to touch/feel and try the products. The style advisor cleaned the sunglasses before the trial. | BL26: The style advisor used the microfiber cloth to clean the sunglasses and offered to try the same post-cleaning all the glasses. He first offered me Ray Ban Aviator sunglasses and cleaned them and offered me for trial. He told me that these were classic sunglasses and would look good based on my facial structure. He kept them on a tray and offered me other sunglasses such as Burberry Wayfarer, Gucci Wayfarer, and D&C Wayfarer. He cleaned all of them one by one and kept them all in the tray and offered me to have a look together. He also confirmed which one I liked the most and also asked for my feedback. The style advisor did not recommend any additional product. | BM26: Discount on the first pair | BO26: Yes | BP26: Yes | BQ26: No | BR26: Summarized your needs and matched them to the product recommended^Asked if you had any further questions^Gave information about the price, payment options | BT26: Yes | BU26: No | BV26: No | BW26: Yes | BX26: No | BY26: N/A | BZ26: Yes | CA26: Yes | CB26: 9 | CC26: Yes | CD26: 9
A27: 11084985 | B27: 2022-10-11 | C27: 78 | D27: 89 | E27: 89 | F27: 80 | G27: 83 | H27: 63 | I27: 100 | J27: 50 | K27: 100 | L27: Bangalore | M27: Karnataka | N27: South | O27: IN | P27: 13:23 | Q27: 13:55 | R27: 1920 | S27: 1 | T27: 1 | U27: 39 | V27: Male | W27: I was wearing a lavender shirt with blue jeans. | X27: Rajiv | Y27: Male, medium build and height, aged somewhere between 30-35 years with neatly groomed black hair and was wearing a yellow t-shirt with blue jeans and was clean-shaven. | Z27: Yes | AA27: Yes | AB27: Yes | AC27: No | AD27: Yes | AE27: No | AF27: Yes | AG27: Yes | AH27: Yes | AI27: The store ambiance was great and the exterior was well-maintained and presentable. The interior of the store looked appealing and all the store lights and fixtures were in good condition. The store did not have any bad smell, music was not being played at the store. All the merchandise was stacked and arranged neatly according to the brands. | AJ27: WOW! Very appealing | AL27: Smile^Eye contact^Verbal greeting within 15 seconds | AM27: Within 2 minutes | AN27: Yes | AO27: Yes | AP27: Yes | AQ27: No | AR27: N/A | AS27: Yes | AT27: Yes | AU27: The Style Advisor asked if I needed the glasses for casual or formal wear. He also enquired if I had any budget constraints. He asked for my preference for the frames and the color of the glass. He also asked how often I use glasses and asked if I used different types of lenses. | AV27: Yes | AW27: The Style Advisor recommended Ray-Ban as it suited my requirements for daily wear and also because they looked trendy. | AX27: No | AZ27: Yes | BA27: Yes | BB27: Yes | BC27: No | BD27: Yes | BE27: Yes | BF27: Yes | BG27: Yes | BH27: No | BI27: No | BJ27: No | BK27: The Style Advisor recommended the RayBan aviator glasses as they featured an enhanced brow bar with crystal lenses in gray with a gold metal frame with adjustable nose pads in a full range of XL sizes. He added that it looked best in oval or square-shaped facial structure. The adjustable nose pads could be widened or narrowed accordingly to fit the nose shape. The Style Advisor also recommended the Armani glasses in black color with rims made up of gunmetal along with the Prada glasses which were styled in a contemporary design for men with trendy looks. | BL27: During the trial, the Style Advisor gave me different styles and patterns of frames and he proactively suggested that I try the shortlisted items. He advised that based on the structure of my face, the Ray-Ban glasses were best suited for me. The Style Advisor suggested I also try the Armani glasses as they were the latest ongoing trend along with the Prada glasses which were the best in terms of the frame design. | BM27: Expensive products | BO27: Yes | BP27: Yes | BQ27: Yes | BR27: Summarized your needs and matched them to the product recommended^Gave information about the price, payment options | BT27: Yes | BU27: Yes | BV27: No | BW27: No | BX27: No | BY27: No | BZ27: Yes | CA27: No | CB27: 8 | CC27: Yes | CD27: 9
A28: 11085599 | B28: 2022-10-08 | C28: 92 | D28: 78 | E28: 100 | F28: 100 | G28: 100 | H28: 100 | I28: 100 | J28: 75 | K28: 100 | L28: Pune | M28: Maharashtra | N28: West | O28: IN | P28: 15:05 | Q28: 15:30 | R28: 1500 | S28: 3 | T28: 3 | U28: 35 | V28: Male | W28: I was wearing a t-shirt and jeans. | X28: Satyam | Y28: Male, approximately 5'7' in height, wheatish complexion and medium build. | Z28: Yes | AA28: Yes | AB28: Yes | AC28: No | AD28: No | AE28: No | AF28: Yes | AG28: Yes | AH28: Yes | AI28: All the merchandise was arranged as per the brand and frame types. The store was clean and well-maintained. | AJ28: WOW! Very appealing | AL28: Smile^Eye contact^Verbal greeting within 15 seconds | AM28: Within 2 minutes | AN28: Yes | AO28: Yes | AP28: Yes | AQ28: Yes | AR28: N/A | AS28: Yes | AT28: Yes | AU28: The style advisor asked me about the type of frames I was looking for and whether I wanted aviator or fiber-made. | AV28: Yes | AW28: The style advisor mentioned that they were the official distributor and manufacturer of the sunglasses. | AX28: Yes | AY28: The style advisor asked me about the type of designs I was looking for and whether I wanted aviator glasses or fiber frame sunglasses. | AZ28: Yes | BA28: Yes | BB28: Yes | BC28: Yes | BD28: Yes | BE28: Yes | BF28: Yes | BG28: Yes | BH28: Yes | BI28: Yes | BJ28: Yes | BK28: The products recommended were sunglasses in Rayban, Oakley, Armani, and different types of makes in fiber, and aviators. I was also informed that many of the designs were unisex in nature. These brands were medically tested in terms of their use of UV rays, scratch-proof, and polarized make. | BL28: The overall trial experience was nice as the style advisor gave me proper information on the styles and types of sunglasses. The style advisor also gave a proper statement when I tried the sunglasses on. The style advisor used the microfiber cloth to clean the sunglasses before use for better clarity. | BM28: Expensive products | BO28: Yes | BP28: Yes | BQ28: Yes | BR28: Gave information about the price, payment options | BT28: Yes | BU28: Yes | BV28: No | BW28: No | BX28: No | BY28: Yes | BZ28: Yes | CA28: Yes | CB28: 10 | CC28: Yes | CD28: 10
A29: 11085892 | B29: 2022-10-08 | C29: 59 | D29: 89 | E29: 78 | F29: 80 | G29: 17 | H29: 38 | I29: 100 | J29: 25 | K29: 100 | L29: Coimatore | M29: Tamil Nadu | N29: South | O29: IN | P29: 12:45 | Q29: 12:55 | R29: 600 | S29: 2 | T29: 1 | U29: 37 | V29: Male | W29: I was wearing a casual dress. | X29: Hari | Y29: Male, approximately 5'7' in height, fair complexion, black hair and wore a branded t-shirt. | Z29: Yes | AA29: Yes | AB29: Yes | AC29: No | AD29: Yes | AE29: No | AF29: Yes | AG29: Yes | AH29: Yes | AI29: The ambiance of the store was good. The exterior signage was clean and well-lit. All the fixtures and other tangibles were in good condition. The Sunglass Hut merchandise was displayed and arranged well on the drawers/shelves/display tables. The style advisor was very friendly. | AJ29: WOW! Very appealing | AL29: Eye contact | AM29: Within 2 minutes | AN29: Yes | AO29: Yes | AP29: Yes | AQ29: Yes | AR29: N/A | AS29: Yes | AT29: Yes | AU29: The style advisor asked me about the purpose for the glasses and any specific brands I was looking for. | AV29: Yes | AW29: No additional remarks were made. | AX29: No | AZ29: Yes | BA29: No | BB29: No | BC29: No | BD29: Yes | BE29: No | BF29: No | BG29: Yes | BH29: Yes | BI29: No | BJ29: No | BK29: I asked the style advisor for an anti-reflection glass which I would be using while I worked in front of the computer. The style advisor showed me Ray-ban's anti-reflection glasses and recommended them to me. They were old in terms of style and were not trendy to which he suggested that I could try other brands like Oakley. | BL29: The style advisor was very polite and showed me the product which I had inquired about. He asked me to try them on. | BM29: Expensive products | BO29: Yes | BP29: Yes | BQ29: Yes | BR29: Offered information on another product to help you decide^Summarized your needs and matched them to the product recommended | BT29: Yes | BU29: No | BV29: No | BW29: No | BX29: No | BY29: No | BZ29: No | CA29: No | CB29: 7 | CC29: Yes | CD29: 7
A30: 11085982 | B30: 2022-10-08 | C30: 33 | D30: 100 | E30: 33 | F30: 20 | G30: 0 | H30: 0 | I30: 33 | J30: 25 | K30: 0 | L30: Guwahati | M30: Assam | N30: North | O30: IN | P30: 12:17 | Q30: 12:27 | R30: 600 | S30: 1 | T30: 0 | U30: 43 | V30: Male | W30: I was wearing casual jeans with a shirt and Adidas shoes. | X30: Probin | Y30: Male, approximately 5'6' in height, black hair, fair complexion. He was well dressed and was wearing the Company uniform. with plain jeans and shoes, clean-shaven with combed hair. | Z30: Yes | AA30: Yes | AB30: Yes | AC30: Yes | AD30: Yes | AE30: No | AF30: Yes | AG30: Yes | AH30: Yes | AI30: The ambiance of the store was good. The signage was clean and tidy. The store entrance was appealing and catchy. The store was well-lit. The digital screen at the back side of the cash counter was also visible even from outside the store. All merchandise was kept in order according to the brand and frame. | AJ30: Good, looks interesting | AL30: Not greeted at all | AM30: After 2 minutes | AN30: Yes | AO30: Yes | AP30: Yes | AQ30: No | AR30: N/A | AS30: No | AT30: No | AU30: Nothing was asked about my requirements. I proactively approached the style advisor and asked for the sunglasses. | AV30: Yes | AW30: The style advisor was not proactive with the sales and mentioned only the brand names of the sunglasses I was looking for. | AX30: No | AZ30: No | BA30: No | BB30: No | BC30: No | BD30: No | BE30: No | BF30: No | BG30: No | BH30: No | BI30: No | BJ30: No | BK30: The style advisor recommended Ray-Ban, Oakley, and Emporio Armani at my request. He did not make an effort to ask about my preference for glasses. I had to proactively ask for lightweight sunglasses based on the first recommendation made by him which was the Emporia Armani as it was made of Polycarbonate, and later moved on to Ray-Ban and lastly to Oakley. | BL30: As the trial was proactively initiated by me, there was not much to share about the trial experience. The style advisor made no comments on the post-trial as well and neither did he use the styling tray or even offered to clean the glasses before and after the trial. | BM30: Expensive products | BO30: No | BP30: Yes | BQ30: No | BR30: None of the above | BT30: No | BU30: No | BV30: No | BW30: No | BX30: No | BY30: No | BZ30: Yes | CA30: No | CB30: 6 | CC30: No | CD30: 7
A31: 11086048 | B31: 2022-10-10 | C31: 64 | D31: 89 | E31: 80 | F31: 0 | G31: 83 | H31: 38 | I31: 100 | J31: 63 | K31: 0 | L31: Kolkatta | M31: West Bengal | N31: East | O31: IN | P31: 16:28 | Q31: 16:52 | R31: 1440 | S31: 2 | T31: 1 | U31: 27 | V31: Female | W31: I was wearing a grey kurti with the white palazzo and black flat shoes and had a side bag. | X31: Raj Roushan | Y31: Male, approximately 5'5' in height, fair complexion, black hair, was wearing the Company branded t-shirt along with the ID card and wore jeans with black shoes, clean-shaven and hairstyle was done in a nice manner. | Z31: Yes | AA31: Yes | AB31: Yes | AC31: No | AD31: Yes | AE31: No | AF31: Yes | AG31: Yes | AH31: Yes | AI31: The location was easy to find via Google Maps. The products were arranged well on the drawers and the overall ambiance of the store was pleasant. The store was neat, clean, and well-lit. | AJ31: Good, looks interesting | AL31: Smile^Eye contact^Verbal greeting within 15 seconds | AM31: Within 2 minutes | AN31: Yes | AO31: Yes | AP31: Yes | AQ31: No | AR31: No | AS31: No | AT31: No | AU31: The style advisor did not ask me any questions to discover my needs or my requirements. I had to push the conversation to continue it. | AV31: No | AW31: The style advisor did not provide any information about any of the brands. | AX31: No | AZ31: Yes | BA31: Yes | BB31: Yes | BC31: No | BD31: Yes | BE31: No | BF31: No | BG31: Yes | BH31: No | BI31: No | BJ31: Yes | BK31: The style advisor recommended the Prada Milano product and mentioned that it was a luxury brand and one of the best sellers. He did not provide any further details about it. | BL31: Though the style advisor did not provide the details about the brands, he did however encourage me to touch and feel the products that were kept in the store. I tried on multiple sunglasses from different brands, out of which he mentioned the gradient feature for two of the sunglasses only. He proactively gave me different glasses for the trial. | BM31: Expensive products | BO31: Yes | BP31: Yes | BQ31: Yes | BR31: Gave information about the price, payment options | BT31: Yes | BU31: Yes | BV31: No | BW31: No | BX31: No | BY31: No | BZ31: Yes | CA31: Yes | CB31: 7 | CC31: No | CD31: 7
A32: 11086368 | B32: 2022-10-22 | C32: 69 | D32: 89 | E32: 78 | F32: 100 | G32: 50 | H32: 38 | I32: 100 | J32: 50 | K32: 100 | L32: Bangalore | M32: Karnataka | N32: South | O32: IN | P32: 13:50 | Q32: 14:25 | R32: 2100 | S32: 1 | T32: 1 | U32: 42 | V32: Male | W32: I was wearing a formal shirt and trousers. | X32: Lukman | Y32: Male, approximately 5'10' in height, fair complexion, black hair, was wearing the Company t-shirt and blue jeans, had a beard. | Z32: Yes | AA32: Yes | AB32: Yes | AC32: No | AD32: Yes | AE32: No | AF32: Yes | AG32: Yes | AH32: Yes | AI32: The store was clean and well-maintained. The store entrance, fixtures, and the other tangibles were in good condition. Music was not played at the store. The digital screen was operational at the store entrance. The merchandise was stacked and displayed neatly on shelves. The store was spacious enough to browse around. There were no cartons lying around. | AJ32: Good, looks interesting | AL32: Smile^Eye contact^Verbal greeting within 15 seconds | AM32: Within 2 minutes | AN32: Yes | AO32: No | AP32: Yes | AQ32: No | AR32: N/A | AS32: Yes | AT32: Yes | AU32: The style advisor asked if I had any particular model in mind. | AV32: Yes | AW32: While presenting each of the products, the style advisor informed me about the brand details. | AX32: Yes | AY32: I had shown an interest in Ray-Ban so the style advisor asked if I would like to look at any particular model or frame type. | AZ32: Yes | BA32: Yes | BB32: No | BC32: No | BD32: Yes | BE32: No | BF32: No | BG32: Yes | BH32: No | BI32: No | BJ32: Yes | BK32: The style advisor recommended Ray-Ban Aviator with extra padding in the frame top and an additional product with a different frame type was recommended. | BL32: The style advisor cleaned the sunglasses before the trial and handed them to me but not with the micro-fiber cloth to clean them. The style advisor did not use the styling tray as well. The style advisor did not make appropriate recommendations nor did the style advisor give any compliments during the trial. The style advisor did not try to get my feedback as well. | BM32: Discount on the first pair | BO32: Yes | BP32: Yes | BQ32: Yes | BR32: Offered information on another product to help you decide^Summarized your needs and matched them to the product recommended^Gave information about the price, payment options | BT32: Yes | BU32: Yes | BV32: No | BW32: No | BX32: No | BY32: No | BZ32: Yes | CA32: No | CB32: 7 | CC32: Yes | CD32: 7
A33: 11086637 | B33: 2022-10-07 | C33: 83 | D33: 89 | E33: 67 | F33: 100 | G33: 100 | H33: 75 | I33: 100 | J33: 71 | K33: 100 | L33: Kolkatta | M33: West Bengal | N33: East | O33: IN | P33: 17:45 | Q33: 18:10 | R33: 1500 | S33: 2 | T33: 1 | U33: 40 | V33: Female | W33: I was wearing a yellow printed kurta with a beige coloured dupatta. | X33: Rohit | Y33: Male, average height, fair complexion, short black hair, around 30 years old, and medium build. | Z33: Yes | AA33: Yes | AB33: Yes | AC33: No | AD33: Yes | AE33: No | AF33: Yes | AG33: Yes | AH33: Yes | AI33: The presentation of the outlet was very well done. It was attractive. | AJ33: WOW! Very appealing | AL33: Smile^Eye contact | AM33: Within 2 minutes | AN33: Yes | AO33: No | AP33: Yes | AQ33: No | AR33: N/A | AS33: Yes | AT33: Yes | AU33: The style advisor asked me about the brand or any particular shape of eye wear that I was looking for. | AV33: Yes | AW33: The style advisor was supportive and took care of the purchase need well. | AX33: Yes | AY33: I showed an interest in the international brands and the style advisor showed the products as per my interest. He updated me on the ongoing offer which was flat 25% off on the second pair. | AZ33: Yes | BA33: Yes | BB33: Yes | BC33: Yes | BD33: Yes | BE33: Yes | BF33: Yes | BG33: No | BH33: No | BI33: Yes | BJ33: Yes | BK33: The sunglasses from the brands Prada, Burberry, TB, and Versace were recommended. | BL33: The trial was offered proactively. The style advisor encouraged me to touch and feel the products and try them all. He briefly discussed the brand and the products. He mentioned the brand came under the International Luxury brand and the frames were good enough for regular use. He also mentioned the glasses were to protect from the harsh UV rays. | BM33: Discount on the first pair | BO33: Yes | BP33: Yes | BQ33: Yes | BR33: Offered information on another product to help you decide^Gave information about the price, payment options | BT33: Yes | BU33: Yes | BV33: No | BW33: No | BX33: No | BY33: N/A | BZ33: Yes | CA33: Yes | CB33: 8 | CC33: Yes | CD33: 8
A34: 11087027 | B34: 2022-10-07 | C34: 94 | D34: 100 | E34: 89 | F34: 100 | G34: 100 | H34: 100 | I34: 100 | J34: 75 | K34: 100 | L34: Chennai | M34: Tamil Nadu | N34: South | O34: IN | P34: 20:31 | Q34: 20:52 | R34: 1260 | S34: 1 | T34: 2 | U34: 60 | V34: Female | W34: I was wearing a pale blue jeans top and dark blue jeggings. | X34: Santosh | Y34: Male, 5'4'' in height, wheatish complexion, black hair, was wearing the Company branded orange t-shirt with the name tag, medium build, in his late 20's/early30's. | Z34: Yes | AA34: Yes | AB34: Yes | AC34: Yes | AD34: Yes | AE34: No | AF34: Yes | AG34: Yes | AH34: Yes | AI34: The store was clean and extremely well-maintained. I did not notice any cartons lying around. All the glasses were displayed well according to their respective frame categories and brands too. The store looked inviting. The display was good. | AJ34: WOW! Very appealing | AL34: Smile^Eye contact^Verbal greeting within 15 seconds | AM34: Within 2 minutes | AN34: Yes | AO34: Yes | AP34: Yes | AQ34: No | AR34: N/A | AS34: Yes | AT34: Yes | AU34: The style advisor asked if I was looking for anything in particular or if I had a brand in mind. | AV34: Yes | AW34: The style advisor did talk in brief about the products on display. | AX34: Yes | AY34: The style advisor asked me if I was looking to buy sunglasses for myself or for gifting. I said it was for myself, but my daughter may use it too. The style advisor asked what kind of Sunglasses I was looking for. I said I wanted something simple and sturdy. Nothing flashy. He showed me quite a few pieces in Prada, Burberry, Oakley, Dolce & Gabanna, Armani, and RayBan. The style advisor informed me that they were all top international fashion brands of high quality with 2 years international warranty. The style advisor also saw that I was wearing progressive glasses and let me know that the facility to make power glass was not available at the store and that I had to get it done in any other Optical store. The style advisor assumed I was aware of these International brands and did not go into them in detail. | AZ34: Yes | BA34: Yes | BB34: Yes | BC34: Yes | BD34: Yes | BE34: Yes | BF34: Yes | BG34: Yes | BH34: Yes | BI34: Yes | BJ34: Yes | BK34: The style advisor allowed me to handle the products and try them on too. He did clean the glasses before and after use. He did recommend other products to me from other brands. He spoke about the uniqueness of each product and explained them to me. | BL34: The style advisor spoke about the following UV brand sunglasses. The discount was 25% off only on the second purchase. They had a small section of glasses that had a 20% off on Ray Ban Aviator sunglasses. The style advisor showed me just one clip-on glass magnetic in the Armani brand. There was no option to get the frame converted to my power glass. He suggested that I should buy the frame from here and take it to any optical shop and get it converted to my power, as they did not have this facility in the store. We also saw Cat Eyeglasses and the large frames of Prada, Burberry, Oakley, Dolce & Gabanna, Armani, and RayBan. The style advisor showed me the animal print frames too. He explained the 'Reduce Redness Reflection' which balanced the contrast in Ray-Ban. Oakley had the same feature but in sports-style glasses. Oakley had a Prism lens. | BM34: Expensive products | BO34: Yes | BP34: Yes | BQ34: Yes | BR34: Gave information about the price, payment options | BT34: Yes | BU34: Yes | BV34: No | BW34: No | BX34: No | BY34: Yes | BZ34: Yes | CA34: Yes | CB34: 9 | CC34: Yes | CD34: 9
A35: 11087195 | B35: 2022-10-07 | C35: 80 | D35: 100 | E35: 70 | F35: 80 | G35: 83 | H35: 100 | I35: 100 | J35: 38 | K35: 100 | L35: Pune | M35: Maharashtra | N35: West | O35: IN | P35: 14:58 | Q35: 15:32 | R35: 2040 | S35: 3 | T35: 7 | U35: 40 | V35: Female | W35: I was wearing a t-shirt with pants. | X35: Samir Pathan | Y35: Male, approximately 5'6'' in height, black hair, was wearing a plain blue jeans with black colour shoes, was wearing a mask, and medium build. | Z35: Yes | AA35: Yes | AB35: Yes | AC35: Yes | AD35: Yes | AE35: No | AF35: Yes | AG35: Yes | AH35: Yes | AI35: The store was well maintained. All merchandise was well arranged as per the brand. The style advisor was knowledgeable and helpful. | AJ35: Good, looks interesting | AL35: Smile^Eye contact | AM35: Within 2 minutes | AN35: Yes | AO35: Yes | AP35: Yes | AQ35: No | AR35: No | AS35: Yes | AT35: Yes | AU35: The style advisor asked me what kind of eyeglasses I was looking. | AV35: Yes | AW35: I carried one bag with myself but the style advisor did not tell me to keep it aside. | AX35: No | AZ35: Yes | BA35: Yes | BB35: Yes | BC35: No | BD35: Yes | BE35: Yes | BF35: Yes | BG35: Yes | BH35: Yes | BI35: Yes | BJ35: Yes | BK35: The style advisor encouraged me to touch, feel and try the products. He cleaned all trial products before and after the trial. He behaved professionally. He suggested I should carry the lens cleaner spray along with spectacular. After the trial, he asked me for the feedback. | BL35: Overall, my experience was good. The basic range of products started from 10k. Here I saw multiple brands under one roof. The store did have a unique design collection in spectacular. All available options were good and the latest. The style advisor was knowledgeable and was aware of the availability of sizes, designs, and colors. | BM35: Expensive products | BO35: Yes | BP35: Yes | BQ35: Yes | BR35: Summarized your needs and matched them to the product recommended^Invited you back for more information or another demonstration or test. Gave you their business card or contact information. | BT35: Yes | BU35: Yes | BV35: No | BW35: No | BX35: No | BY35: No | BZ35: No | CA35: No | CB35: 7 | CC35: Yes | CD35: 10
A36: 11090138 | B36: 2022-10-20 | C36: 82 | D36: 78 | E36: 89 | F36: 60 | G36: 100 | H36: 88 | I36: 100 | J36: 63 | K36: 100 | L36: Kanpur | M36: Uttar Pradesh | N36: North | O36: IN | P36: 16:05 | Q36: 16:36 | R36: 1860 | S36: 3 | T36: 3 | U36: 33 | V36: Female | W36: I was wearing a palazzo and Kurti. | X36: Sagar Prathak | Y36: Male, approximately 5'88' in height, fair complexion, light brown hair color, was not wearing spectacles and was wearing the Company uniform, clean-shaven and their hairstyle was done properly. | Z36: Yes | AA36: Yes | AB36: Yes | AC36: No | AD36: Yes | AE36: Yes | AF36: Yes | AG36: Yes | AH36: Yes | AI36: The store entrance was attractive and inviting, and all the windows and facade were clean and well except for the cartons that were lying around. Music was not played at the store. | AJ36: WOW! Very appealing | AL36: Smile^Eye contact | AM36: Within 2 minutes | AN36: Yes | AO36: Yes | AP36: Yes | AQ36: Yes | AR36: N/A | AS36: Yes | AT36: Yes | AU36: The style advisor asked which type of shades I was looking for. | AV36: No | AW36: N/A | AX36: No | AZ36: Yes | BA36: Yes | BB36: Yes | BC36: Yes | BD36: Yes | BE36: Yes | BF36: Yes | BG36: Yes | BH36: Yes | BI36: Yes | BJ36: No | BK36: The style advisor showed me many sunglasses from different brands that they had at the store with the price range starting from 4000/-. The style advisor showed me different shades of black, purple, and rose gold and all the UV-protected aviators. | BL36: My overall trial experience was very good. They had a good collection of different brands and the style advisor offered 10 to 15 shades of every brand during the trial. The style advisor used the styling tray and cleaned the glasses before and after the trial as well. The style advisor did not try to upsell the sunglasses from different brands but kept suggesting glasses that would look good on me. | BM36: Expensive products | BO36: Yes | BP36: Yes | BQ36: Yes | BR36: Asked if you were ready to purchase today^Offered information on another product to help you decide^Asked if you had any further questions^Gave information about the price, payment options | BT36: Yes | BU36: Yes | BV36: No | BW36: No | BX36: No | BY36: No | BZ36: Yes | CA36: Yes | CB36: 9 | CC36: Yes | CD36: 9
A37: 11095309 | B37: 2022-10-15 | C37: 84 | D37: 78 | E37: 89 | F37: 80 | G37: 100 | H37: 75 | I37: 100 | J37: 75 | K37: 100 | L37: Surat | M37: Gujarat | N37: West | O37: IN | P37: 17:48 | Q37: 18:20 | R37: 1920 | S37: 3 | T37: 1 | U37: 35 | V37: Female | W37: I was wearing a kurti with leggings. | X37: Santosh Jadhav | Y37: Male, approximately 5'5' in height, wheatish complexion, black short hair, did not wear spectacles, was wearing an orange t-shirt with jeans, in his 20s, and medium build. | Z37: Yes | AA37: Yes | AB37: Yes | AC37: No | AD37: No | AE37: No | AF37: Yes | AG37: Yes | AH37: Yes | AI37: The exterior signage of the store was clean and well-lit. The fixtures and other tangibles were in good condition. Music was not played. There was no digital screen outside the store and there were no cartons lying outside as well. The style advisor immediately greeted me as soon as I entered the store. | AJ37: Good, looks interesting | AL37: Smile^Eye contact^Verbal greeting within 15 seconds | AM37: Within 2 minutes | AN37: Yes | AO37: Yes | AP37: Yes | AQ37: No | AR37: N/A | AS37: Yes | AT37: Yes | AU37: The style advisor asked about my profession and also asked if I was looking at the sunglasses for myself or my family members. | AV37: Yes | AW37: No additional remarks were made. | AX37: No | AZ37: Yes | BA37: Yes | BB37: Yes | BC37: Yes | BD37: Yes | BE37: Yes | BF37: Yes | BG37: No | BH37: No | BI37: Yes | BJ37: Yes | BK37: The style advisor recommended sunglasses from the brands such as Versace, Prada, Burberry, ray ban, etc. | BL37: The trial experience could have been more effective if the style advisor had used the styling tray and the micro-fiber cloth to clean the glasses before and after the trial. The style advisor gave appropriate comments during the trial and even asked for my feedback based on the products tried during the trial. | BM37: Expensive products | BO37: Yes | BP37: Yes | BQ37: Yes | BR37: Asked if you were ready to purchase today^Gave information about the price, payment options | BT37: Yes | BU37: Yes | BV37: Yes | BW37: No | BX37: Yes | BY37: Yes | BZ37: Yes | CA37: Yes | CB37: 9 | CC37: Yes | CD37: 9
A38: 11095478 | B38: 2022-10-18 | C38: 73 | D38: 89 | E38: 89 | F38: 80 | G38: 50 | H38: 63 | I38: 100 | J38: 50 | K38: 100 | L38: Hyderabad | M38: Telangana | N38: South | O38: IN | P38: 16:00 | Q38: 16:29 | R38: 1740 | S38: 2 | T38: 2 | U38: 45 | V38: Female | W38: I was wearing a saree. | X38: Suresh | Y38: Male, approximately 5'5' in height, fair complexion, did not wear spectacles, was wearing the Company branded t-shirt with jeans, had a beard, in his 30s, medium build. | Z38: Yes | AA38: Yes | AB38: Yes | AC38: No | AD38: Yes | AE38: No | AF38: Yes | AG38: Yes | AH38: Yes | AI38: The store was neatly maintained and the style advisors were very helpful and professional. Music was not played and there were no cartons lying around the store. | AJ38: Good, looks interesting | AL38: Eye contact^Verbal greeting within 15 seconds | AM38: Within 2 minutes | AN38: Yes | AO38: Yes | AP38: Yes | AQ38: Yes | AR38: N/A | AS38: Yes | AT38: Yes | AU38: The style advisor asked me about my preferences like the color of the lenses and the brand. | AV38: Yes | AW38: The style advisor mentioned only the brand names but he showed enthusiasm. He was very proactive and helpful. | AX38: No | AZ38: Yes | BA38: No | BB38: Yes | BC38: No | BD38: Yes | BE38: Yes | BF38: Yes | BG38: No | BH38: No | BI38: Yes | BJ38: No | BK38: The style advisor showed me more models from Prada than the other brands. | BL38: When I asked for the latest collection, the style advisor showed me a few designs and asked me if I had any particular brand in my mind. I asked for Prada so the style advisor showed me more models in Prada and when I asked for a particular color of glasses, the style advisor checked the entire store for that color but could not get the green colored sunglasses with black frames that I wanted. The style advisor tried their best to look for it so I was happy with the effort put into it. | BM38: Expensive products | BO38: Yes | BP38: Yes | BQ38: Yes | BR38: Offered information on another product to help you decide^Gave information about the price, payment options | BT38: Yes | BU38: Yes | BV38: No | BW38: No | BX38: No | BY38: No | BZ38: Yes | CA38: No | CB38: 9 | CC38: Yes | CD38: 9
A39: 11095494 | B39: 2022-10-18 | C39: 39 | D39: 78 | E39: 67 | F39: 0 | G39: 17 | H39: 13 | I39: 67 | J39: 25 | K39: 0 | L39: Hyderabad | M39: Telangana | N39: South | O39: IN | P39: 15:30 | Q39: 15:55 | R39: 1500 | S39: 1 | T39: 1 | U39: 55 | V39: Male | W39: I was wearing a trouser and sweatshirt. | X39: The style advisor did not mention his name. | Y39: Male, approximately 5'10' in height, fair complexion, and was wearing an orange t-shirt, jeans, and shoes, had a beard, was around 24 years and medium build. | Z39: Yes | AA39: Yes | AB39: Yes | AC39: No | AD39: Yes | AE39: No | AF39: Yes | AG39: No | AH39: Yes | AI39: The sunglasses were not arranged according to the brand and frame type. Some of the sunglasses were kept under a different brand. There were no cartons lying around the store. Music was not played at the store. | AJ39: Good, looks interesting | AL39: Eye contact | AM39: Within 2 minutes | AN39: Yes | AO39: Yes | AP39: Yes | AQ39: No | AR39: N/A | AS39: No | AT39: No | AU39: The style advisor did not ask any questions. | AV39: No | AW39: The style adviser was not very active. The style advisor even refused to tell his name. | AX39: No | AZ39: Yes | BA39: No | BB39: No | BC39: No | BD39: Yes | BE39: No | BF39: No | BG39: No | BH39: No | BI39: No | BJ39: No | BK39: The style advisor did not recommend any products. No additional product was recommended to complete the look. | BL39: As the style advisor did not recommend any of the products, I had to pick out a few to try for myself. During the trial, the style advisor did not use the styling tray or even cleaned the glasses. The style advisor did not compliment me or provide any corrections post-trial. The style advisor did not try to get my feedback on the products that were tried on. | BM39: Discount on the first pair | BO39: Yes | BP39: No | BQ39: Yes | BR39: Gave information about the price, payment options | BT39: No | BU39: Yes | BV39: No | BW39: No | BX39: No | BY39: No | BZ39: No | CA39: No | CB39: 5 | CC39: No | CD39: 5
A40: 11095498 | B40: 2022-10-21 | C40: 71 | D40: 89 | E40: 78 | F40: 60 | G40: 50 | H40: 75 | I40: 67 | J40: 63 | K40: 100 | L40: Hyderabad | M40: Telangana | N40: South | O40: IN | P40: 13:08 | Q40: 13:36 | R40: 1680 | S40: 2 | T40: 1 | U40: 56 | V40: Male | W40: I was wearing chinos with sweatshirt. | X40: Ali | Y40: Male, approximately 5'6' in height, fair complexion, and was wearing an orange t-shirt, and jeans, had a beard, and a slim build, in his 30s. | Z40: Yes | AA40: Yes | AB40: Yes | AC40: No | AD40: Yes | AE40: No | AF40: Yes | AG40: Yes | AH40: Yes | AI40: Strategically placed store in the double corner of the floor in the mall. Excellent visibility. Music was not played and there were no cartons lying around. | AJ40: WOW! Very appealing | AL40: Verbal greeting within 15 seconds | AM40: Within 2 minutes | AN40: Yes | AO40: Yes | AP40: Yes | AQ40: Yes | AR40: N/A | AS40: Yes | AT40: Yes | AU40: The style adviser did not ask any questions but only answered questions by me. | AV40: No | AW40: N/A | AX40: No | AZ40: Yes | BA40: No | BB40: Yes | BC40: No | BD40: Yes | BE40: Yes | BF40: Yes | BG40: Yes | BH40: Yes | BI40: No | BJ40: No | BK40: The style adviser did not recommend any products but showed me the models that I preferred. | BL40: The style advisor showed me a few designs, out of which I selected a few and asked if I could try them. After the first trial, the style advisor did not bother to clean the sunglasses with the cloth. The style advisor stood beside me and assisted me in everything. The style advisor did not try to get my feedback after the trial or try to upsell products from different brands. | BM40: Discount on the first pair | BO40: Yes | BP40: Yes | BQ40: No | BR40: Offered information on another product to help you decide^Asked if you had any further questions^Gave information about the price, payment options | BT40: Yes | BU40: Yes | BV40: Yes | BW40: Yes | BX40: No | BY40: No | BZ40: No | CA40: No | CB40: 10 | CC40: Yes | CD40: 10
A41: 11095574 | B41: 2022-10-08 | C41: 100 | D41: 100 | E41: 100 | F41: 100 | G41: 100 | H41: 100 | I41: 100 | J41: 100 | K41: 100 | L41: Lucknow | M41: Uttar Pradesh | N41: North | O41: IN | P41: 15:45 | Q41: 16:07 | R41: 1320 | S41: 1 | T41: 1 | U41: 39 | V41: Female | W41: I was wearing green color jeggings with a black polka dot top. | X41: Fariz | Y41: Male, approximately 5'8' in height, wheatish complexion with black hair was wearing a proper uniform and wore no spectacles. | Z41: Yes | AA41: Yes | AB41: Yes | AC41: Yes | AD41: Yes | AE41: No | AF41: Yes | AG41: Yes | AH41: Yes | AI41: The store exterior was well maintained and it had a standee that displayed the offers to attract customers. The store ambiance was nice and the products at the store were all well-displayed. The store also had a huge digital screen behind the cash counter that had the product advertisement displayed on it and there were no cartons lying around the store. | AJ41: Good, looks interesting | AL41: Smile^Eye contact^Verbal greeting within 15 seconds | AM41: Within 2 minutes | AN41: Yes | AO41: Yes | AP41: Yes | AQ41: Yes | AR41: Yes | AS41: Yes | AT41: Yes | AU41: The style advisor asked if I was looking at the sunglasses for myself or for someone else. | AV41: Yes | AW41: The style advisor had good knowledge about the brands. | AX41: Yes | AY41: The style advisor asked what type of glasses I was looking for in Ray-ban. | AZ41: Yes | BA41: Yes | BB41: Yes | BC41: Yes | BD41: Yes | BE41: Yes | BF41: Yes | BG41: Yes | BH41: Yes | BI41: Yes | BJ41: Yes | BK41: The style advisor recommended the different-shaped glasses from Ray-Ban and picked the ones that he thought would look good on me based on my facial structure. | BL41: The style advisor offered various glasses for me to try on and he even cleaned each of the glasses before the trial. He was very proactive and offered various options based on my preference, and gave genuine feedback on all the glasses that I had tried on. | BM41: Expensive products | BO41: Yes | BP41: Yes | BQ41: Yes | BR41: Offered information on another product to help you decide^Summarized your needs and matched them to the product recommended^Shared a personal/customer's story about the product to reassure you about your purchase^Gave information about the price, payment options | BT41: Yes | BU41: Yes | BV41: Yes | BW41: Yes | BX41: No | BY41: Yes | BZ41: Yes | CA41: Yes | CB41: 9 | CC41: Yes | CD41: 9
A42: 11095575 | B42: 2022-10-11 | C42: 94 | D42: 89 | E42: 90 | F42: 100 | G42: 100 | H42: 100 | I42: 100 | J42: 88 | K42: 100 | L42: Lucknow | M42: Uttar Pradesh | N42: North | O42: IN | P42: 14:00 | Q42: 14:24 | R42: 1440 | S42: 2 | T42: 1 | U42: 39 | V42: Female | W42: I was wearing green-shaded jeggings and a black polka-dot top. | X42: Abhay | Y42: Male, approximately 5'7' in height, with no spectacles, wheatish complexion with black hair, and was wearing a proper uniform. | Z42: Yes | AA42: Yes | AB42: Yes | AC42: No | AD42: Yes | AE42: No | AF42: Yes | AG42: Yes | AH42: Yes | AI42: The store exterior, as well as interior, were well maintained. The store was not playing any music. | AJ42: Good, looks interesting | AL42: Smile^Eye contact^Verbal greeting within 15 seconds | AM42: Within 2 minutes | AN42: Yes | AO42: Yes | AP42: Yes | AQ42: Yes | AR42: No | AS42: Yes | AT42: Yes | AU42: The style advisor enquired if I was looking for a specific brand. | AV42: Yes | AW42: The style advisor mentioned the brand names only. | AX42: Yes | AY42: The style advisor asked me for the type of glasses I was looking for in Ray-Ban. | AZ42: Yes | BA42: Yes | BB42: Yes | BC42: Yes | BD42: Yes | BE42: Yes | BF42: Yes | BG42: Yes | BH42: Yes | BI42: Yes | BJ42: Yes | BK42: The style advisor recommended the different shaped glasses from Ray-Ban. | BL42: During the trial, the style advisor recommended various options for me to try on and offered genuine suggestions. He even used the styling tray and cleaned the glasses before and after the trial as well. | BM42: Expensive products | BO42: Yes | BP42: Yes | BQ42: Yes | BR42: Offered information on another product to help you decide^Gave information about the price, payment options | BT42: Yes | BU42: Yes | BV42: No | BW42: Yes | BX42: No | BY42: Yes | BZ42: Yes | CA42: Yes | CB42: 8 | CC42: Yes | CD42: 8
A43: 11095640 | B43: 2022-10-19 | C43: 52 | D43: 78 | E43: 33 | F43: 40 | G43: 50 | H43: 25 | I43: 100 | J43: 57 | K43: 100 | L43: Chennai | M43: Tamil Nadu | N43: South | O43: IN | P43: 17:10 | Q43: 17:35 | R43: 1500 | S43: 1 | T43: 1 | U43: 27 | V43: Male | W43: I was wearing a blue t-shirt with black jeans. | X43: Rafi | Y43: Male, short in height, brown complexion and was wearing the Company uniform, well groomed, medium build, did not have a name tag on. | Z43: Yes | AA43: Yes | AB43: Yes | AC43: No | AD43: Yes | AE43: No | AF43: Yes | AG43: Yes | AH43: No | AI43: Music was not played at the store. There were no cartons lying around. Products were neatly arranged based on the brands. I did not feel welcome upon entering the store. | AJ43: Good, looks interesting | AL43: Not greeted at all | AM43: After 2 minutes | AN43: Yes | AO43: Yes | AP43: Yes | AQ43: No | AR43: N/A | AS43: No | AT43: Yes | AU43: The specific brand I was interested in. | AV43: Yes | AW43: None. | AX43: No | AZ43: Yes | BA43: No | BB43: Yes | BC43: No | BD43: Yes | BE43: No | BF43: No | BG43: No | BH43: No | BI43: No | BJ43: Yes | BK43: The style advisor suggested Rayban proactively along with BVLGARI. | BL43: The style advisor did not offer a trial proactively, but I tried multiple collections from all the major brands. The style advisor did not offer post-trial assistance or try to get my feedback. The styling tray was not used and the glasses were not cleaned before or after the trial as well. | BM43: Expensive products | BO43: Yes | BP43: Yes | BQ43: Yes | BR43: Invited you back for more information or another demonstration or test. Gave you their business card or contact information. | BT43: Yes | BU43: Yes | BV43: No | BW43: No | BX43: No | BY43: N/A | BZ43: Yes | CA43: No | CB43: 6 | CC43: Yes | CD43: 6
A44: 11095740 | B44: 2022-10-13 | C44: 62 | D44: 100 | E44: 80 | F44: 0 | G44: 50 | H44: 50 | I44: 100 | J44: 50 | K44: 0 | L44: Kolkatta | M44: West Bengal | N44: East | O44: IN | P44: 16:09 | Q44: 16:32 | R44: 1380 | S44: 2 | T44: 1 | U44: 27 | V44: Female | W44: I had my hair up in a ponytail and was wearing a reddish-brown Kurti with white palazzo, and black flat shoes, and carried a brown bag. | X44: Sanjit | Y44: Male, approximately 5'5' in height, with fair complexion, clean-shaven and black hair styled neatly, and was wearing the Company brand t-shirt with jeans and black shoes. He wore his ID card, a wristlet in his right hand, and a watch in his left hand. | Z44: Yes | AA44: Yes | AB44: Yes | AC44: Yes | AD44: Yes | AE44: No | AF44: Yes | AG44: Yes | AH44: Yes | AI44: The location was easy to find via Google Maps. All the products were kept and arranged well on the drawers and the overall ambiance of the store was pleasant. The store was neat and clean and was well-lit with music playing throughout the store. | AJ44: Good, looks interesting | AL44: Smile^Eye contact^Verbal greeting within 15 seconds | AM44: Within 2 minutes | AN44: Yes | AO44: Yes | AP44: Yes | AQ44: No | AR44: No | AS44: No | AT44: No | AU44: N/A. | AV44: No | AW44: The style advisor did not provide any details regarding the brands nor explain anything about them. The requirements and needs of the customers should have been asked by the style advisor. | AX44: No | AZ44: Yes | BA44: No | BB44: Yes | BC44: No | BD44: Yes | BE44: No | BF44: No | BG44: Yes | BH44: Yes | BI44: No | BJ44: Yes | BK44: The style advisor recommended a product from Michael Kors and mentioned that it was crystal glass and that it was one of the bestsellers from the luxury brand. He also mentioned the product's warranty period of 2 years but aside from that, he did not give away any more details about the said product. He did not offer me compliments or offer appropriate recommendations as per my facial characteristics. No feedback was taken from me. | BL44: The style advisor did not provide any information about any of the brands and neither did he share any of the brand's stories during the trial. Since he did not ask anything about my requirements, I had to mention them to continue the conversation. Though he did not provide any information about the products he did encourage me to touch and feel the products kept in the drawer. I had tried multiple sunglasses from different brands as the style advisor proactively gave them for me to try. | BM44: Expensive products | BO44: Yes | BP44: Yes | BQ44: Yes | BR44: Gave information about the price, payment options | BT44: Yes | BU44: Yes | BV44: No | BW44: No | BX44: No | BY44: No | BZ44: Yes | CA44: No | CB44: 6 | CC44: No | CD44: 5
A45: 11095745 | B45: 2022-10-18 | C45: 94 | D45: 100 | E45: 100 | F45: 100 | G45: 100 | H45: 100 | I45: 100 | J45: 63 | K45: 100 | L45: Bhubaneshwar | M45: Orissa | N45: East | O45: IN | P45: 17:01 | Q45: 17:52 | R45: 3060 | S45: 2 | T45: 2 | U45: 37 | V45: Male | W45: I was wearing denim jeans and a round neck t-shirt. | X45: Suman | Y45: Female, approximately 5'4' in height, fair complexion, ablack hair, wore spectacles and was wearing the Company branded t-shirt, plain jeans, and shoes, looked smart. | Z45: Yes | AA45: Yes | AB45: Yes | AC45: Yes | AD45: Yes | AE45: No | AF45: Yes | AG45: Yes | AH45: Yes | AI45: The store branding was visible and the 25% discount on 2nd pair standee was very well displayed at the storefront. There were no cartons lying around. | AJ45: Good, looks interesting | AL45: Smile^Eye contact^Verbal greeting within 15 seconds | AM45: Within 2 minutes | AN45: Yes | AO45: Yes | AP45: Yes | AQ45: Yes | AR45: N/A | AS45: Yes | AT45: Yes | AU45: The style advisor asked the kind of glasses I liked, the type for both eye-wear and sunglasses. | AV45: Yes | AW45: Ray-Ban and Armani were shown during the visit. | AX45: Yes | AY45: The style advisor asked if I had used sunglasses from Ray-Ban before or not. | AZ45: Yes | BA45: Yes | BB45: Yes | BC45: Yes | BD45: Yes | BE45: Yes | BF45: Yes | BG45: Yes | BH45: Yes | BI45: Yes | BJ45: Yes | BK45: The style advisor recommended some of the designs from Ray-Ban and Armani which were the best sellers that the store had. The style advisor also recommended some of the clip-on units which were a mix of eyewear as well as sunglasses. | BL45: The overall trial experience was good. The style advisor encouraged me to touch and try the glasses and even showed me where the mirrors were kept so that I could check how I looked. The style advisor used the styling tray and even cleaned the glasses before and after the trial. | BM45: Expensive products | BO45: Yes | BP45: Yes | BQ45: Yes | BR45: Asked if you were ready to purchase today^Offered information on another product to help you decide^Shared a personal/customer's story about the product to reassure you about your purchase^Asked if you had any further questions^Gave information about the price, payment options | BT45: Yes | BU45: Yes | BV45: No | BW45: Yes | BX45: Yes | BY45: No | BZ45: Yes | CA45: Yes | CB45: 9 | CC45: Yes | CD45: 9
A46: 11095940 | B46: 2022-10-17 | C46: 86 | D46: 100 | E46: 100 | F46: 100 | G46: 67 | H46: 63 | I46: 100 | J46: 75 | K46: 100 | L46: Vadodara | M46: Gujarat | N46: West | O46: IN | P46: 14:29 | Q46: 14:53 | R46: 1440 | S46: 2 | T46: 1 | U46: 35 | V46: Male | W46: I was wearing a white shirt that had blue strips with blue jeans and casual shoes. | X46: Yogesh | Y46: Male, approximately 5'4' in height, wheatish complexion, black hair, and was wearing the Company branded t-shirt with plain light blue jeans and closed shoes, clean-shaven and hairstyle was done in a proper manner, medium build. | Z46: Yes | AA46: Yes | AB46: Yes | AC46: Yes | AD46: Yes | AE46: No | AF46: Yes | AG46: Yes | AH46: Yes | AI46: The store exterior signage was clean and well-lit. The threshold and entrance of the store looked inviting to the customers. All the fixtures, walls, floor, and lights were in good condition. There was light music being played in the background and the store had a digital screen kept outside the store. There were no cartons found lying on the floor. The Sunglass Hut merchandise was displayed and arranged well on the shelves and the display tables. All the merchandise was arranged according to the brand and frame type. At the entrance, I felt welcomed by the style advisor and the store was spacious enough to move around freely and explore. | AJ46: Good, looks interesting | AL46: Smile^Eye contact^Verbal greeting within 15 seconds | AM46: Within 2 minutes | AN46: Yes | AO46: Yes | AP46: Yes | AQ46: Yes | AR46: N/A | AS46: Yes | AT46: Yes | AU46: The style advisor asked which brand I preferred, and the style and shapes of the sunglasses I was looking for. | AV46: Yes | AW46: The style advisor talked about the pure iconic style of Dolce and Gabbana made in Italy, Burberry's traditional classic style showcased in a modern style and Prada's trendy glasses that would fit the current market trend. | AX46: Yes | AY46: The style advisor asked what type, shape, and color of sunglasses I preferred. | AZ46: Yes | BA46: No | BB46: Yes | BC46: Yes | BD46: Yes | BE46: Yes | BF46: Yes | BG46: No | BH46: No | BI46: Yes | BJ46: No | BK46: The style advisor recommended sunglasses from different brands like Dolce and Gabbana, Prada, Burberry, and Ray-Ban. The style advisor showed me products according to my preference like the style, shape, and comfort. | BL46: The style advisor encouraged me to touch and try the products. The style advisor complimented me on the glasses I had tried and suggested I could check to see how they looked on me. The style advisor did not use the styling tray or the micro-fiber cloth to clean the sunglasses before or after the trial. The style advisor made a note of the feedback regarding the fit and shape of the glasses I provided during the trial. The style advisor did not recommend any additional product to complete the look. | BM46: Discount on the first pair | BO46: Yes | BP46: Yes | BQ46: Yes | BR46: Asked if you were ready to purchase today^Offered information on another product to help you decide^Gave information about the price, payment options | BT46: Yes | BU46: Yes | BV46: No | BW46: No | BX46: No | BY46: Yes | BZ46: Yes | CA46: Yes | CB46: 8 | CC46: Yes | CD46: 8
A47: 11095982 | B47: 2022-10-20 | C47: 94 | D47: 100 | E47: 100 | F47: 100 | G47: 67 | H47: 100 | I47: 100 | J47: 88 | K47: 100 | L47: Delhi | M47: Delhi (UT) | N47: North | O47: IN | P47: 15:15 | Q47: 15:40 | R47: 1500 | S47: 2 | T47: 1 | U47: 28 | V47: Male | W47: I was wearing jeans and shirt. | X47: Rohit | Y47: Male, approximately 5'7' in height, wheatish complexion, black hair, wearing t-shirt, properly shaven, between 25-30 years and slim. | Z47: Yes | AA47: Yes | AB47: Yes | AC47: Yes | AD47: Yes | AE47: No | AF47: Yes | AG47: Yes | AH47: Yes | AI47: The exterior signage was clean and well-lit and in good condition. There were no cartons lying around. The store was well-maintained. | AJ47: Good, looks interesting | AL47: Smile^Eye contact^Verbal greeting within 15 seconds | AM47: Within 2 minutes | AN47: Yes | AO47: Yes | AP47: Yes | AQ47: Yes | AR47: Yes | AS47: Yes | AT47: Yes | AU47: The style advisor asked about the specific size that I was looking for. | AV47: Yes | AW47: N/A | AX47: Yes | AY47: The style advisor asked what color of sunglasses I would like to look at. | AZ47: Yes | BA47: No | BB47: Yes | BC47: Yes | BD47: Yes | BE47: Yes | BF47: Yes | BG47: Yes | BH47: Yes | BI47: Yes | BJ47: Yes | BK47: The style advisor recommended Ray-Ban and Versace. | BL47: The overall trial experience was good. The style advisor gave me different types of brands to try and gave proper feedback, and compliments during the trial. The style advisor also used the styling tray and the micro-fiber cloth to clean the glasses. | BM47: Discount on the first pair | BO47: Yes | BP47: Yes | BQ47: Yes | BR47: Offered information on another product to help you decide^Asked if you had any further questions^Gave information about the price, payment options^Invited you back for more information or another demonstration or test. Gave you their business card or contact information. | BT47: Yes | BU47: Yes | BV47: Yes | BW47: Yes | BX47: Yes | BY47: Yes | BZ47: Yes | CA47: Yes | CB47: 7 | CC47: Yes | CD47: 8
A48: 11096780 | B48: 2022-10-15 | C48: 41 | D48: 78 | E48: 78 | F48: 0 | G48: 33 | H48: 25 | I48: 33 | J48: 0 | K48: 100 | L48: Indore | M48: Madhya Pradesh | N48: East | O48: IN | P48: 14:18 | Q48: 15:16 | R48: 3480 | S48: 3 | T48: 1 | U48: 66 | V48: Male | W48: I was wearing a full sleeve with narrow pink colored lines on a white base shirt, light brown trousers with a leather belt, and brown leather shoes. I wore spectacles, a titan wristwatch, and a gold chain. | X48: Muskan | Y48: Female, approximately 4'7' in height, wheatish complexion, black hair, and was wearing a black colored shirt with pants and shoes. | Z48: Yes | AA48: Yes | AB48: Yes | AC48: No | AD48: No | AE48: No | AF48: Yes | AG48: Yes | AH48: Yes | AI48: The store was compact, well-lit, and had a moderate temperature. The ambiance of the store was good. At the entrance of the store, the style advisor greeted me with a smile. The merchandise was all displayed and well arranged according to brand. The racks were dust and scratch-free, and there were no cartons lying around. Music was not played. | AJ48: Average | AL48: Smile^Eye contact | AM48: Within 2 minutes | AN48: Yes | AO48: Yes | AP48: Yes | AQ48: No | AR48: N/A | AS48: No | AT48: No | AU48: The style advisor did not ask any questions. | AV48: No | AW48: The style advisor only answered to questions being asked. | AX48: No | AZ48: No | BA48: No | BB48: Yes | BC48: No | BD48: Yes | BE48: No | BF48: No | BG48: No | BH48: No | BI48: No | BJ48: Yes | BK48: The style advisor recommended the Ray-Ban sunglasses because of their polarized lenses, however, she did not explain the benefits of polarized lenses. | BL48: The overall trial experience was okay. The style advisor neither cleaned the pair of glasses nor placed them in the tray for the trial. I tried the products that were recommended and kept them back. During and after the trial, the style advisor did not try to get my feedback on the products tried, and neither did the style advisor compliment or offer recommendations based on my facial structure. The team spirit to fetch sales was missing here. The style advisor's assistance could have been better. | BM48: Expensive products | BO48: No | BP48: No | BQ48: Yes | BR48: Offered information on another product to help you decide^Gave information about the price, payment options | BT48: No | BU48: No | BV48: No | BW48: No | BX48: Yes | BY48: No | BZ48: No | CA48: No | CB48: 5 | CC48: Yes | CD48: 4
A49: 11096807 | B49: 2022-10-16 | C49: 69 | D49: 100 | E49: 67 | F49: 80 | G49: 50 | H49: 88 | I49: 0 | J49: 50 | K49: 100 | L49: Delhi | M49: Delhi (UT) | N49: North | O49: IN | P49: 12:55 | Q49: 13:14 | R49: 1140 | S49: 2 | T49: 1 | U49: 52 | V49: Male | W49: I was wearing a formal shirt with trousers. | X49: Rahul | Y49: Male, approximately 5'10' in height, fair complexion. black hair, did not wear spectacles, and was wearing an orange coloured t-shirt. | Z49: Yes | AA49: Yes | AB49: Yes | AC49: Yes | AD49: Yes | AE49: No | AF49: Yes | AG49: Yes | AH49: Yes | AI49: The overall exterior and interior of the store were well-maintained and free of any issues. All the fixtures were lit and there was no fused bulb. No cartons were seen in the store. The merchandise was arranged well as per the brands with signages. | AJ49: WOW! Very appealing | AL49: Eye contact | AM49: Within 2 minutes | AN49: Yes | AO49: Yes | AP49: Yes | AQ49: No | AR49: N/A | AS49: Yes | AT49: Yes | AU49: The style advisor asked about my style preference, the usage and budget. | AV49: Yes | AW49: While showing the glasses, the style advisor informed me about the brand. | AX49: No | AZ49: Yes | BA49: No | BB49: Yes | BC49: No | BD49: Yes | BE49: Yes | BF49: Yes | BG49: Yes | BH49: Yes | BI49: Yes | BJ49: No | BK49: The style advisor recommended wayfarers from brands such as Versace, Armani, Ray-Ban, and Burberry. No additional product was recommended to complete the look. | BL49: The style advisor was very polite and humble. He gave multiple suggestions based on my facial structure and needs. He made sure that my needs were met and that I liked the product. All the glasses were offered for the trial after the style advisor had cleaned them with the microfiber cloth. I tried the Ray-Ban glasses and the style advisor complimented me that those looked the best on me and that I should consider getting them. | BM49: Discount on the first pair | BO49: No | BP49: No | BQ49: No | BR49: Summarized your needs and matched them to the product recommended | BT49: Yes | BU49: No | BV49: No | BW49: No | BX49: No | BY49: No | BZ49: Yes | CA49: Yes | CB49: 9 | CC49: Yes | CD49: 9
A50: 11097708 | B50: 2022-10-16 | C50: 69 | D50: 100 | E50: 78 | F50: 80 | G50: 50 | H50: 75 | I50: 0 | J50: 50 | K50: 100 | L50: Noida | M50: Uttar Pradesh | N50: North | O50: IN | P50: 13:35 | Q50: 13:55 | R50: 1200 | S50: 3 | T50: 2 | U50: 52 | V50: Male | W50: I was wearing a formal shirt and trouser. | X50: Nitesh | Y50: Male, approximately 5'7' in height, had no spectacles on, and was wearing an orange colored t-shirt. | Z50: Yes | AA50: Yes | AB50: Yes | AC50: Yes | AD50: Yes | AE50: No | AF50: Yes | AG50: Yes | AH50: Yes | AI50: The interior and exterior of the store were well maintained. The signage was clean and well-lit. The store had an inviting look and was very welcoming. All the lights and fixtures were in working condition. No cartons or clutter was seen in the store. All the merchandise was properly arranged according to the brand. | AJ50: WOW! Very appealing | AL50: Smile^Eye contact | AM50: Within 2 minutes | AN50: Yes | AO50: Yes | AP50: Yes | AQ50: No | AR50: N/A | AS50: Yes | AT50: Yes | AU50: The style advisor asked me about the usage of the product, the style of the frame and my budget. | AV50: Yes | AW50: The style advisor informed me about the brand while showing the glasses. | AX50: No | AZ50: Yes | BA50: No | BB50: Yes | BC50: No | BD50: Yes | BE50: Yes | BF50: Yes | BG50: Yes | BH50: Yes | BI50: No | BJ50: No | BK50: The style advisor recommended the Prada and Armani wayfarer and the aviators from Ray-Ban. The Armani wayfarer had grey lenses. | BL50: The style advisor prompted and offered me to try the sunglasses. He took out four glasses namely the Prada, and Armani wayfarer which had grey lenses, Versace glass with metal frames, and Ray-Ban aviators. The style advisor told me that these would suit me the best as per my facial structure. The style advisor cleaned the sunglasses before offering me the same for the trial. The style advisor was proactive during and after the trial and complimented that the Ray-Ban looked the best on me from all. However, the style advisor did not try to get my feedback on any of the products. The style advisor also mentioned that Ray-Ban had the best lens quality and that I should go with that. | BM50: Discount on the first pair | BO50: No | BP50: No | BQ50: No | BR50: Summarized your needs and matched them to the product recommended | BT50: Yes | BU50: No | BV50: No | BW50: Yes | BX50: No | BY50: No | BZ50: Yes | CA50: No | CB50: 8 | CC50: Yes | CD50: 8
A51: 11097750 | B51: 2022-10-15 | C51: 61 | D51: 78 | E51: 89 | F51: 0 | G51: 83 | H51: 38 | I51: 100 | J51: 38 | K51: 100 | L51: Hyderabad | M51: Telangana | N51: South | O51: IN | P51: 16:50 | Q51: 17:18 | R51: 1680 | S51: 2 | T51: 2 | U51: 45 | V51: Female | W51: I was wearing jeans and a top. | X51: Gouse Bhasha | Y51: Male, approximately 5'7' in height, dusky complexion, did not have any spectacles on and was wearing the Company branded orange t-shirt, light blue jeans, and black shoes, bearded, must have been around 30 years, average build | Z51: Yes | AA51: Yes | AB51: Yes | AC51: No | AD51: No | AE51: No | AF51: Yes | AG51: Yes | AH51: Yes | AI51: N/A | AJ51: Good, looks interesting | AL51: Eye contact^Verbal greeting within 15 seconds | AM51: Within 2 minutes | AN51: Yes | AO51: Yes | AP51: Yes | AQ51: Yes | AR51: N/A | AS51: No | AT51: No | AU51: No questions were asked. | AV51: No | AW51: The style adviser mentioned only the brand names and did not explain any details about the brands. | AX51: No | AZ51: Yes | BA51: Yes | BB51: Yes | BC51: No | BD51: Yes | BE51: No | BF51: No | BG51: Yes | BH51: Yes | BI51: No | BJ51: No | BK51: The style advisor did not recommend any products. | BL51: The style adviser had shown me some products and I had also picked out 3 of them from the display. The style advisor cleaned them with the micro-fiber cloth before the trial. During the entire trial session, the style advisor did not make any comments regarding the glasses that I had tried on and did not try to get my feedback as well. | BM51: Discount on the first pair | BO51: Yes | BP51: Yes | BQ51: Yes | BR51: Offered information on another product to help you decide^Gave information about the price, payment options^Other (please specify) | BS51: The style adviser gave details about the offers available at the store. | BT51: Yes | BU51: Yes | BV51: No | BW51: No | BX51: No | BY51: No | BZ51: No | CA51: No | CB51: 9 | CC51: Yes | CD51: 8
A52: 11097814 | B52: 2022-10-18 | C52: 92 | D52: 100 | E52: 100 | F52: 100 | G52: 100 | H52: 75 | I52: 100 | J52: 75 | K52: 100 | L52: Mumbai | M52: Maharashtra | N52: West | O52: IN | P52: 16:15 | Q52: 17:00 | R52: 2700 | S52: 3 | T52: 4 | U52: 32 | V52: Male | W52: I was wearing jeans and t-shirt. | X52: Suraj | Y52: Male, approximately 5'9' in height, wheatish complexion, black hair, was wearing spectacles. | Z52: Yes | AA52: Yes | AB52: Yes | AC52: Yes | AD52: Yes | AE52: No | AF52: Yes | AG52: Yes | AH52: Yes | AI52: The merchandise at the store was arranged neatly and well-displayed. The external signage was clean and well-lit. Also, the style advisor was very cordial and well-behaved. There were no cartons lying around. | AJ52: WOW! Very appealing | AL52: Smile^Eye contact^Verbal greeting within 15 seconds | AM52: Within 2 minutes | AN52: Yes | AO52: Yes | AP52: Yes | AQ52: Yes | AR52: Yes | AS52: Yes | AT52: Yes | AU52: The style advisor asked about my style preference and also asked whether I was looking for glasses to gift. | AV52: Yes | AW52: The style advisor was courteous and well behaved. | AX52: Yes | AY52: The style advisor asked whether I wanted to check the glasses for myself or for someone else. | AZ52: Yes | BA52: Yes | BB52: Yes | BC52: Yes | BD52: Yes | BE52: Yes | BF52: Yes | BG52: No | BH52: No | BI52: Yes | BJ52: Yes | BK52: The style advisor recommended Bvlgari. | BL52: The overall trial experience was good. The style advisor was very patient and gave me plenty of time to try each pair of sunglasses. The style advisor gave appropriate comments and suggestions and even tried to get my feedback. However, during the trial, the style advisor did not use the styling tray or even the micro-fiber cloth to clean the sunglasses. | BM52: Expensive products | BO52: Yes | BP52: Yes | BQ52: Yes | BR52: Asked if you were ready to purchase today^Offered information on another product to help you decide^Summarized your needs and matched them to the product recommended^Shared a personal/customer's story about the product to reassure you about your purchase^Asked if you had any further questions^Gave information about the price, payment options | BT52: Yes | BU52: Yes | BV52: No | BW52: No | BX52: No | BY52: Yes | BZ52: Yes | CA52: Yes | CB52: 9 | CC52: Yes | CD52: 8
A53: 11098282 | B53: 2022-10-20 | C53: 96 | D53: 100 | E53: 100 | F53: 80 | G53: 83 | H53: 100 | I53: 100 | J53: 100 | K53: 100 | L53: Kolkatta | M53: West Bengal | N53: East | O53: IN | P53: 15:00 | Q53: 16:16 | R53: 4560 | S53: 4 | T53: 1 | U53: 51 | V53: Female | W53: I was wearing a white printed kurti and jeans. | X53: Priyanka | Y53: Female, approximately 5 feet in height, dark complexion, was wearing the Company branded t-shirt, plain black jeans, black shoes, and hair tied in a bun. | Z53: Yes | AA53: Yes | AB53: Yes | AC53: Yes | AD53: Yes | AE53: No | AF53: Yes | AG53: Yes | AH53: Yes | AI53: When I entered the store, the style advisors were busy with their official work but within 2 minutes, one of the style advisors came and asked if I needed help. All the walls, lights, and drawers were perfect. All items were correctly arranged and kept in the drawers and on the racks according to their brands. The store looked vibrant and there were no cartons lying around. | AJ53: WOW! Very appealing | AL53: Smile^Eye contact^Verbal greeting within 15 seconds | AM53: Within 2 minutes | AN53: Yes | AO53: Yes | AP53: Yes | AQ53: Yes | AR53: N/A | AS53: Yes | AT53: Yes | AU53: The style advisor asked if I needed the glasses for maximum coverage or deep color. | AV53: Yes | AW53: The style advisor said that the glasses had a shine on them and they were ultraviolet rays protected. | AX53: No | AZ53: Yes | BA53: Yes | BB53: Yes | BC53: No | BD53: Yes | BE53: Yes | BF53: Yes | BG53: Yes | BH53: Yes | BI53: Yes | BJ53: Yes | BK53: The products recommended were hexagon-shaped Prada and Ray-Ban glasses. The style advisor also recommended glasses from Burberry and Gucci. | BL53: Overall, it was a great experience. The style advisor's friendliness and politeness were notable. I was offered Prada, Burberry, and Gucci glasses for the trial. The style advisor gave proper compliments and corrections. He even took my feedback on the products tried during the trial. | BM53: Discount on the first pair | BO53: Yes | BP53: Yes | BQ53: Yes | BR53: Asked if you were ready to purchase today^Offered information on another product to help you decide^Summarized your needs and matched them to the product recommended | BT53: Yes | BU53: Yes | BV53: Yes | BW53: Yes | BX53: No | BY53: Yes | BZ53: Yes | CA53: Yes | CB53: 9 | CC53: Yes | CD53: 9
A54: 11099765 | B54: 2022-10-18 | C54: 34 | D54: 89 | E54: 70 | F54: 0 | G54: 0 | H54: 0 | I54: 67 | J54: 0 | K54: 0 | L54: Mumbai | M54: Maharashtra | N54: West | O54: IN | P54: 14:00 | Q54: 14:22 | R54: 1320 | S54: 1 | T54: 1 | U54: 32 | V54: Male | W54: I was wearing a t-shirt with denims. | X54: Vijay K | Y54: Male, approximately 5'5' in height, fair complexion, black hair, and was wearing the Company branded t-shirt, plain jeans, and shoes. | Z54: Yes | AA54: Yes | AB54: Yes | AC54: Yes | AD54: No | AE54: No | AF54: Yes | AG54: Yes | AH54: Yes | AI54: The store was well-lit. The store did not have a digital display screen and there were no cartons lying around the store. The cash counter had lots of smudges. | AJ54: Good, looks interesting | AL54: Verbal greeting within 15 seconds | AM54: Within 2 minutes | AN54: Yes | AO54: Yes | AP54: Yes | AQ54: Yes | AR54: No | AS54: No | AT54: No | AU54: The style advisor did not ask any questions. | AV54: No | AW54: The style advisor did not discuss any specific product needs. | AX54: No | AZ54: No | BA54: No | BB54: No | BC54: No | BD54: No | BE54: No | BF54: No | BG54: No | BH54: No | BI54: No | BJ54: No | BK54: The style advisor did not recommend any products and no additional product was recommended to complete the look. | BL54: The style advisor did not recommend any products for me and neither helped with the products that I had selected. The style advisor did not encourage me to try or touch the products. The style advisor did not use the styling tray and did not clean the products that I had taken out for the trial. The style did not offer compliments or corrections during the trial as well. | BM54: Discount on the first pair | BO54: Yes | BP54: Yes | BQ54: No | BR54: Gave information about the price, payment options | BT54: No | BU54: No | BV54: No | BW54: No | BX54: Yes | BY54: No | BZ54: No | CA54: No | CB54: 5 | CC54: No | CD54: 5
A55: 11099886 | B55: 2022-10-23 | C55: 53 | D55: 89 | E55: 78 | F55: 20 | G55: 50 | H55: 13 | I55: 67 | J55: 38 | K55: 100 | L55: Bangalore | M55: Karnataka | N55: South | O55: IN | P55: 17:30 | Q55: 18:00 | R55: 1800 | S55: 2 | T55: 3 | U55: 41 | V55: Male | W55: I was wearing jeans and a t-shirt. | X55: Aneesh Jayanth | Y55: Male, approximately 5' 3' in height, wheatish complexion, black hair, wore no spectacles and was wearing the Company branded t-shirt, jeans and shoes, clean shaven and a neat hairstyle done. | Z55: Yes | AA55: Yes | AB55: Yes | AC55: No | AD55: Yes | AE55: No | AF55: Yes | AG55: Yes | AH55: Yes | AI55: The store was well-lit and looked inviting. Music was not played and there were no cartons lying around. There were 3 style advisors attending to customers at the store. There were separate displays for men's and women's sunglasses. | AJ55: WOW! Very appealing | AL55: Eye contact | AM55: Within 2 minutes | AN55: Yes | AO55: Yes | AP55: Yes | AQ55: Yes | AR55: N/A | AS55: No | AT55: No | AU55: No questions were asked by the style advisor. | AV55: Yes | AW55: The style advisor informed me that sunglasses were available for INR 8000. | AX55: No | AZ55: Yes | BA55: No | BB55: Yes | BC55: No | BD55: Yes | BE55: No | BF55: No | BG55: No | BH55: No | BI55: No | BJ55: No | BK55: The style advisor recommended sunglasses from Burberry, Emporio Armani, Dolce and Gabbana, Bvlgari, and Versace. | BL55: The overall trial experience was good. The style advisor encouraged me to try the sunglasses and helped me select the right sunglasses. However, the style advisor did not use the styling tray or the micro-fiber cloth during the trial. The style advisor did not compliment or give corrections during the trial. The style advisor also did not try to get my feedback on the products. No upselling was done. | BM55: Discount on the first pair | BO55: Yes | BP55: Yes | BQ55: No | BR55: Gave information about the price, payment options | BT55: Yes | BU55: Yes | BV55: No | BW55: No | BX55: No | BY55: No | BZ55: No | CA55: No | CB55: 9 | CC55: Yes | CD55: 8
A56: 11106986 | B56: 2022-10-27 | C56: 94 | D56: 100 | E56: 100 | F56: 100 | G56: 83 | H56: 100 | I56: 100 | J56: 75 | K56: 100 | L56: Chandigarth | M56: Punjab | N56: North | O56: IN | P56: 12:46 | Q56: 13:09 | R56: 1380 | S56: 3 | T56: 3 | U56: 33 | V56: Male | W56: I was wearing shirt with dark blue denims and white champions shoes. | X56: Varinder | Y56: Male, approximately 5'7' in height, fair complexion, was wearing the Company brand uniform, slim build, a silver chain, and a face mask. | Z56: Yes | AA56: Yes | AB56: Yes | AC56: Yes | AD56: Yes | AE56: No | AF56: Yes | AG56: Yes | AH56: Yes | AI56: The store ambiance was well-maintained. The temperature inside the store was perfect. There was no foul odor. The walls, ceiling, floor, and mirrors were present in good condition. The products were placed according to the brand. At the entrance, the glass door was clean and smudge-free. The exterior and interior signage were clean and well-maintained. There were no cartons lying around. | AJ56: WOW! Very appealing | AL56: Smile^Eye contact^Verbal greeting within 15 seconds | AM56: Within 2 minutes | AN56: Yes | AO56: Yes | AP56: Yes | AQ56: Yes | AR56: N/A | AS56: Yes | AT56: Yes | AU56: The style advisor asked what I was looking for and asked if I was interested in a particular brand. | AV56: Yes | AW56: The style advisor first told me about the brand of the sunglasses and then the shades of models that were available. | AX56: Yes | AY56: The style advisor asked me questions related to my interest and need pertaining to that brand. | AZ56: Yes | BA56: Yes | BB56: Yes | BC56: No | BD56: Yes | BE56: Yes | BF56: Yes | BG56: Yes | BH56: Yes | BI56: Yes | BJ56: Yes | BK56: The style advisor recommended sunglasses that had 100% UV protection and a polarized lens. The style advisor also recommended the latest models of aviator sunglasses from Ray-Ban and the hinge collection from Prada. The style advisor also showed different color options for the same frame glasses. | BL56: During the trial, the style advisor used the styling tray and cleaned the glasses using the micro-fiber cloth before and after the trial. The style advisor complimented me on the look of the sunglasses and said the glasses were perfect for my face structure. The style advisor commented that all the sunglasses tried in the trial were from the latest collection. The style advisor even showed me how the cleaning kit was used and that I could screw the glasses and clean them at home using the cleaning kit. | BM56: Discount on the first pair | BO56: Yes | BP56: Yes | BQ56: Yes | BR56: Asked if you were ready to purchase today^Offered information on another product to help you decide^Summarized your needs and matched them to the product recommended^Asked if you had any further questions^Gave information about the price, payment options | BT56: Yes | BU56: Yes | BV56: No | BW56: No | BX56: No | BY56: Yes | BZ56: Yes | CA56: Yes | CB56: 10 | CC56: Yes | CD56: 10
A57: 11107721 | B57: 2022-10-28 | C57: 61 | D57: 78 | E57: 67 | F57: 40 | G57: 50 | H57: 88 | I57: 33 | J57: 38 | K57: 100 | L57: Bhopal | M57: Madhya Pradesh | N57: East | O57: IN | P57: 16:51 | Q57: 17:20 | R57: 1740 | S57: 1 | T57: 2 | U57: 29 | V57: Male | W57: I was wearing formal shirt with trousers. | X57: Vasudev | Y57: Male, approximately 5'6' in height, fair complexion, black hair, wore spectacles, and was wearing a uniform, red jacket, and had a light beard. | Z57: Yes | AA57: Yes | AB57: Yes | AC57: No | AD57: N/A | AE57: No | AF57: Yes | AG57: Yes | AH57: No | AI57: The store ambiance was good. There was no music played at the store and there were no cartons lying around. I did not feel welcome to freely move and explore the store. | AJ57: Average | AL57: Eye contact | AM57: Within 2 minutes | AN57: No | AO57: Yes | AP57: Yes | AQ57: Yes | AR57: N/A | AS57: No | AT57: Yes | AU57: No questions were asked. | AV57: Yes | AW57: None. | AX57: No | AZ57: No | BA57: No | BB57: Yes | BC57: Yes | BD57: Yes | BE57: Yes | BF57: Yes | BG57: Yes | BH57: Yes | BI57: Yes | BJ57: No | BK57: I was recommended Ray-Ban sunglasses. | BL57: The style advisor offered appropriate compliments and corrections during the trial. After the trial, the style advisor tried to get my feedback on the products. The style advisor used the styling tray and the micro-fiber cloth to clean the glasses for the trial. | BM57: Discount on the first pair | BO57: No | BP57: Yes | BQ57: No | BR57: Asked if you were ready to purchase today^Summarized your needs and matched them to the product recommended | BT57: Yes | BU57: No | BV57: No | BW57: Yes | BX57: No | BY57: No | BZ57: No | CA57: No | CB57: 5 | CC57: Yes | CD57: 4
A58: 11108719 | B58: 2022-10-28 | C58: 88 | D58: 78 | E58: 100 | F58: 80 | G58: 100 | H58: 100 | I58: 100 | J58: 63 | K58: 100 | L58: Chennai | M58: Tamil Nadu | N58: South | O58: IN | P58: 16:11 | Q58: 16:32 | R58: 1260 | S58: 1 | T58: 1 | U58: 32 | V58: Male | W58: I was wearing casual shirt, jeans with causal shoes. | X58: Senthil Kumar | Y58: Male, approximately 5'5' in height, dark skin complexion, black hair did not wear spectacles, was wearing the Company orange t-shirt, plain jeans, black shoes, clean-shaven, and short hairstyle. | Z58: Yes | AA58: Yes | AB58: Yes | AC58: No | AD58: No | AE58: No | AF58: Yes | AG58: Yes | AH58: Yes | AI58: The store was well maintained and looked very clean. There were no cartons lying around. The store did not have a digital screen and music was not played. There were more than 4 brands available and displayed brand-wise. Everything was placed perfectly inside the store. | AJ58: Good, looks interesting | AL58: Smile^Eye contact^Verbal greeting within 15 seconds | AM58: Within 2 minutes | AN58: Yes | AO58: Yes | AP58: Yes | AQ58: Yes | AR58: N/A | AS58: Yes | AT58: Yes | AU58: The style advisor asked who the glasses were for, the kind of glasses I wanted to look at, and the purpose of it. | AV58: Yes | AW58: Multiple brands were showed based on my requirements. | AX58: No | AZ58: Yes | BA58: Yes | BB58: Yes | BC58: Yes | BD58: Yes | BE58: Yes | BF58: Yes | BG58: Yes | BH58: Yes | BI58: Yes | BJ58: Yes | BK58: I had asked for sun shades to wear while driving the car so the style advisor suggested multiple frames in different brands. The style advisor suggested frames that suited my facial structure and recommended RayBan and Prada. | BL58: During the trial, the style advisor asked if the products were comfortable, and encouraged me to touch and try them on and used the styling tray. The style advisor wiped the glasses with the micro-fiber cloth before and after the trial. The style advisor provided proper corrections and even asked for my feedback after the trial. | BM58: Expensive products | BO58: Yes | BP58: Yes | BQ58: Yes | BR58: Asked if you were ready to purchase today^Offered information on another product to help you decide^Gave information about the price, payment options | BT58: Yes | BU58: Yes | BV58: No | BW58: Yes | BX58: No | BY58: No | BZ58: Yes | CA58: No | CB58: 9 | CC58: Yes | CD58: 10
A59: 11108736 | B59: 2022-10-30 | C59: 77 | D59: 100 | E59: 89 | F59: 80 | G59: 17 | H59: 100 | I59: 100 | J59: 57 | K59: 0 | L59: Bangalore | M59: Karnataka | N59: South | O59: IN | P59: 15:56 | Q59: 16:50 | R59: 3240 | S59: 1 | T59: 2 | U59: 23 | V59: Male | W59: I was wearing blue jean and yellow hoodie. | X59: Anju Gurung | Y59: Female, black hair, was wearing the Company brand orange t-shirt, blue jeans and black shoes. | Z59: N/A | AA59: Yes | AB59: Yes | AC59: Yes | AD59: N/A | AE59: No | AF59: Yes | AG59: Yes | AH59: Yes | AI59: There were no cartons lying around. | AJ59: Good, looks interesting | AL59: Smile^Eye contact^Verbal greeting within 15 seconds | AM59: Within 2 minutes | AN59: Yes | AO59: Yes | AP59: No | AQ59: Yes | AR59: N/A | AS59: Yes | AT59: Yes | AU59: The style advisor asked what model I was looking for. | AV59: Yes | AW59: Good customer interaction from the style advisor. Very helpful in finding the products. | AX59: No | AZ59: Yes | BA59: No | BB59: No | BC59: No | BD59: Yes | BE59: Yes | BF59: Yes | BG59: Yes | BH59: Yes | BI59: Yes | BJ59: Yes | BK59: The style advisor suggested the Oakley brand sunglasses. | BL59: The overall trial experience was very good. The style advisor suggested all the sunglasses according to my requirements. The style advisor offered proper compliments and corrections during the trial. The style advisor also tried to get my feedback after the trial and made use of the styling tray along with the micro-fiber cloth to clean the glasses for the trial. | BM59: Expensive products | BO59: Yes | BP59: Yes | BQ59: Yes | BR59: Gave information about the price, payment options | BT59: Yes | BU59: Yes | BV59: No | BW59: No | BX59: No | BY59: Yes | BZ59: No | CA59: N/A | CB59: 10 | CC59: No | CD59: 10
A60: 11108784 | B60: 2022-10-30 | C60: 33 | D60: 78 | E60: 56 | F60: 20 | G60: 0 | H60: 0 | I60: 33 | J60: 29 | K60: 0 | L60: Bangalore | M60: Karnataka | N60: South | O60: IN | P60: 16:55 | Q60: 17:25 | R60: 1800 | S60: 4 | T60: 5 | U60: 41 | V60: Male | W60: I was wearing jeans & t-shirt. | X60: Mr. Girish | Y60: Male, approximately 5'3' in height, wheatish, black hair, no spectacles, and was wearing the Company branded t-shirt, jeans, shoes, clean-shaven, hairstyle done. | Z60: Yes | AA60: Yes | AB60: Yes | AC60: No | AD60: No | AE60: No | AF60: Yes | AG60: Yes | AH60: Yes | AI60: The Sunglass Hut store was located at a prominent location inside Phoenix City Mall. There were 2 sections inside the store, one was for Ray Ban & the other portion was for luxury sunglasses brands. The Ray Ban section was unisex and the other side with the luxury brand was Versace, Prada, and so on. The store did not have a digital screen and there was no music being played at the store. There were no cartons lying around. | AJ60: WOW! Very appealing | AL60: Verbal greeting within 15 seconds | AM60: Within 2 minutes | AN60: Yes | AO60: No | AP60: Yes | AQ60: No | AR60: N/A | AS60: No | AT60: No | AU60: No questions were asked by the style advisor | AV60: Yes | AW60: The style advisor informed that the sunglasses were available from INR 8000. | AX60: No | AZ60: No | BA60: No | BB60: No | BC60: No | BD60: No | BE60: No | BF60: No | BG60: No | BH60: No | BI60: No | BJ60: No | BK60: The style advisor did not recommend any product. | BL60: The style advisor did not offer a trial session. | BM60: Expensive products | BO60: No | BP60: Yes | BQ60: No | BR60: None of the above | BT60: No | BU60: Yes | BV60: No | BW60: No | BX60: No | BY60: N/A | BZ60: No | CA60: No | CB60: 7 | CC60: No | CD60: 6
A61: 11108785 | B61: 2022-10-30 | C61: 35 | D61: 78 | E61: 67 | F61: 40 | G61: 0 | H61: 0 | I61: 0 | J61: 25 | K61: 0 | L61: Bangalore | M61: Karnataka | N61: South | O61: IN | P61: 17:28 | Q61: 17:58 | R61: 1800 | S61: 2 | T61: 2 | U61: 41 | V61: Male | W61: I was wearing jeans & t-shirt. | X61: Yash | Y61: Male, approximately 5' 4' in height, wheatish complexion, black hair, no spectacles, and was wearing the Company branded t-shirt, jeans, shoes, unshaven, hairstyle done. | Z61: Yes | AA61: Yes | AB61: Yes | AC61: No | AD61: No | AE61: No | AF61: Yes | AG61: Yes | AH61: Yes | AI61: The Sunglass Hut store was located at a prominent location inside VR Mall. The store did not have a digital screen and there was no music being played. There were no cartons lying around. | AJ61: Good, looks interesting | AL61: Verbal greeting within 15 seconds | AM61: Within 2 minutes | AN61: Yes | AO61: No | AP61: Yes | AQ61: Yes | AR61: N/A | AS61: No | AT61: Yes | AU61: No questions were asked by the Style Advisor. | AV61: Yes | AW61: The Style Advisor informed me that the sunglasses were available from INR 8000. | AX61: No | AZ61: No | BA61: No | BB61: No | BC61: No | BD61: No | BE61: No | BF61: No | BG61: No | BH61: No | BI61: No | BJ61: No | BK61: The style advisor did not recommend any products. | BL61: The style advisor did not suggest a trial. | BM61: Expensive products | BO61: No | BP61: No | BQ61: No | BR61: None of the above | BT61: No | BU61: No | BV61: No | BW61: No | BX61: No | BY61: No | BZ61: Yes | CA61: No | CB61: 7 | CC61: No | CD61: 6
A62: 11108850 | B62: 2022-10-29 | C62: 65 | D62: 89 | E62: 78 | F62: 40 | G62: 50 | H62: 63 | I62: 67 | J62: 43 | K62: 100 | L62: Mumbai | M62: Maharashtra | N62: West | O62: IN | P62: 16:53 | Q62: 17:05 | R62: 720 | S62: 3 | T62: 1 | U62: 25 | V62: Female | W62: I was wearing a black and grey checked shirt with blue jeans, spectacles and short hair. | X62: Arbaaz | Y62: Male, approximately 5'3' in height, fair complexion, and was wearing a plain white formal shirt with black trousers, slender build, in his 30s. | Z62: Yes | AA62: Yes | AB62: Yes | AC62: No | AD62: Yes | AE62: No | AF62: Yes | AG62: Yes | AH62: Yes | AI62: The store ambiance was welcoming. The signage was clean and well-lit. Music was not played and there were no cartons lying around. | AJ62: WOW! Very appealing | AL62: Smile^Eye contact | AM62: Within 2 minutes | AN62: Yes | AO62: Yes | AP62: Yes | AQ62: No | AR62: N/A | AS62: No | AT62: Yes | AU62: The style advisor asked about the shape of the glasses I wanted. | AV62: Yes | AW62: The style advisor mentioned the brand name only. | AX62: No | AZ62: Yes | BA62: No | BB62: Yes | BC62: No | BD62: Yes | BE62: No | BF62: Yes | BG62: No | BH62: No | BI62: Yes | BJ62: Yes | BK62: The style advisor recommended products from Versace, Gucci, and Rayban. | BL62: The style advisor did not proactively show me the products however the style advisor did let me try the products that I had selected. The style advisor did not compliment me or suggest any corrections but did try to get my feedback. The styling tray and the micro-fiber cloth were not used to clean the glasses before and after the trial. | BM62: Discount on the first pair | BO62: No | BP62: Yes | BQ62: Yes | BR62: Asked if you had any further questions^Invited you back for more information or another demonstration or test. Gave you their business card or contact information. | BT62: Yes | BU62: Yes | BV62: No | BW62: No | BX62: No | BY62: N/A | BZ62: No | CA62: No | CB62: 6 | CC62: Yes | CD62: 7

Sheet Task 1 Sheet
A1: Evaluation Grading | B1: Evaluation Grading Bar
A2: =IF(AND('CX_Junior BI Analyst_Test'!C2>=90,'CX_Junior BI Analyst_Test'!C2<=100),"High Performer",IF(AND('CX_Junior BI Analyst_Test'!C2>=70,'CX_Junior BI Analyst_Test'!C2<=89),"Average Performer",IF(AND('CX_Junior BI Analyst_Test'!C2>=50,'CX_Junior BI Analyst_Test'!C2<=69),"Low Performer","Bottom Performer"))) -> Low Performer | B2: ='CX_Junior BI Analyst_Test'!C2 -> 58 | E2: Task 1 - Performance Grading
A3: =IF(AND('CX_Junior BI Analyst_Test'!C3>=90,'CX_Junior BI Analyst_Test'!C3<=100),"High Performer",IF(AND('CX_Junior BI Analyst_Test'!C3>=70,'CX_Junior BI Analyst_Test'!C3<=89),"Average Performer",IF(AND('CX_Junior BI Analyst_Test'!C3>=50,'CX_Junior BI Analyst_Test'!C3<=69),"Low Performer","Bottom Performer"))) -> Average Performer | B3: ='CX_Junior BI Analyst_Test'!C3 -> 86 | E3: High Performer | F3: 90 | G3: 100
A4: =IF(AND('CX_Junior BI Analyst_Test'!C4>=90,'CX_Junior BI Analyst_Test'!C4<=100),"High Performer",IF(AND('CX_Junior BI Analyst_Test'!C4>=70,'CX_Junior BI Analyst_Test'!C4<=89),"Average Performer",IF(AND('CX_Junior BI Analyst_Test'!C4>=50,'CX_Junior BI Analyst_Test'!C4<=69),"Low Performer","Bottom Performer"))) -> Average Performer | B4: ='CX_Junior BI Analyst_Test'!C4 -> 72 | E4: Average Performer | F4: 70 | G4: 89
A5: =IF(AND('CX_Junior BI Analyst_Test'!C5>=90,'CX_Junior BI Analyst_Test'!C5<=100),"High Performer",IF(AND('CX_Junior BI Analyst_Test'!C5>=70,'CX_Junior BI Analyst_Test'!C5<=89),"Average Performer",IF(AND('CX_Junior BI Analyst_Test'!C5>=50,'CX_Junior BI Analyst_Test'!C5<=69),"Low Performer","Bottom Performer"))) -> Average Performer | B5: ='CX_Junior BI Analyst_Test'!C5 -> 84 | E5: Low Performer | F5: 50 | G5: 69
A6: =IF(AND('CX_Junior BI Analyst_Test'!C6>=90,'CX_Junior BI Analyst_Test'!C6<=100),"High Performer",IF(AND('CX_Junior BI Analyst_Test'!C6>=70,'CX_Junior BI Analyst_Test'!C6<=89),"Average Performer",IF(AND('CX_Junior BI Analyst_Test'!C6>=50,'CX_Junior BI Analyst_Test'!C6<=69),"Low Performer","Bottom Performer"))) -> Average Performer | B6: ='CX_Junior BI Analyst_Test'!C6 -> 84 | E6: Bottom Performer | G6: 50
A7: =IF(AND('CX_Junior BI Analyst_Test'!C7>=90,'CX_Junior BI Analyst_Test'!C7<=100),"High Performer",IF(AND('CX_Junior BI Analyst_Test'!C7>=70,'CX_Junior BI Analyst_Test'!C7<=89),"Average Performer",IF(AND('CX_Junior BI Analyst_Test'!C7>=50,'CX_Junior BI Analyst_Test'!C7<=69),"Low Performer","Bottom Performer"))) -> High Performer | B7: ='CX_Junior BI Analyst_Test'!C7 -> 90
A8: =IF(AND('CX_Junior BI Analyst_Test'!C8>=90,'CX_Junior BI Analyst_Test'!C8<=100),"High Performer",IF(AND('CX_Junior BI Analyst_Test'!C8>=70,'CX_Junior BI Analyst_Test'!C8<=89),"Average Performer",IF(AND('CX_Junior BI Analyst_Test'!C8>=50,'CX_Junior BI Analyst_Test'!C8<=69),"Low Performer","Bottom Performer"))) -> Bottom Performer | B8: ='CX_Junior BI Analyst_Test'!C8 -> 36
A9: =IF(AND('CX_Junior BI Analyst_Test'!C9>=90,'CX_Junior BI Analyst_Test'!C9<=100),"High Performer",IF(AND('CX_Junior BI Analyst_Test'!C9>=70,'CX_Junior BI Analyst_Test'!C9<=89),"Average Performer",IF(AND('CX_Junior BI Analyst_Test'!C9>=50,'CX_Junior BI Analyst_Test'!C9<=69),"Low Performer","Bottom Performer"))) -> Bottom Performer | B9: ='CX_Junior BI Analyst_Test'!C9 -> 34
A10: =IF(AND('CX_Junior BI Analyst_Test'!C10>=90,'CX_Junior BI Analyst_Test'!C10<=100),"High Performer",IF(AND('CX_Junior BI Analyst_Test'!C10>=70,'CX_Junior BI Analyst_Test'!C10<=89),"Average Performer",IF(AND('CX_Junior BI Analyst_Test'!C10>=50,'CX_Junior BI Analyst_Test'!C10<=69),"Low Performer","Bottom Performer"))) -> Average Performer | B10: ='CX_Junior BI Analyst_Test'!C10 -> 74
A11: =IF(AND('CX_Junior BI Analyst_Test'!C11>=90,'CX_Junior BI Analyst_Test'!C11<=100),"High Performer",IF(AND('CX_Junior BI Analyst_Test'!C11>=70,'CX_Junior BI Analyst_Test'!C11<=89),"Average Performer",IF(AND('CX_Junior BI Analyst_Test'!C11>=50,'CX_Junior BI Analyst_Test'!C11<=69),"Low Performer","Bottom Performer"))) -> Average Performer | B11: ='CX_Junior BI Analyst_Test'!C11 -> 74
A12: =IF(AND('CX_Junior BI Analyst_Test'!C12>=90,'CX_Junior BI Analyst_Test'!C12<=100),"High Performer",IF(AND('CX_Junior BI Analyst_Test'!C12>=70,'CX_Junior BI Analyst_Test'!C12<=89),"Average Performer",IF(AND('CX_Junior BI Analyst_Test'!C12>=50,'CX_Junior BI Analyst_Test'!C12<=69),"Low Performer","Bottom Performer"))) -> Average Performer | B12: ='CX_Junior BI Analyst_Test'!C12 -> 86
A13: =IF(AND('CX_Junior BI Analyst_Test'!C13>=90,'CX_Junior BI Analyst_Test'!C13<=100),"High Performer",IF(AND('CX_Junior BI Analyst_Test'!C13>=70,'CX_Junior BI Analyst_Test'!C13<=89),"Average Performer",IF(AND('CX_Junior BI Analyst_Test'!C13>=50,'CX_Junior BI Analyst_Test'!C13<=69),"Low Performer","Bottom Performer"))) -> Average Performer | B13: ='CX_Junior BI Analyst_Test'!C13 -> 70
A14: =IF(AND('CX_Junior BI Analyst_Test'!C14>=90,'CX_Junior BI Analyst_Test'!C14<=100),"High Performer",IF(AND('CX_Junior BI Analyst_Test'!C14>=70,'CX_Junior BI Analyst_Test'!C14<=89),"Average Performer",IF(AND('CX_Junior BI Analyst_Test'!C14>=50,'CX_Junior BI Analyst_Test'!C14<=69),"Low Performer","Bottom Performer"))) -> Average Performer | B14: ='CX_Junior BI Analyst_Test'!C14 -> 84
A15: =IF(AND('CX_Junior BI Analyst_Test'!C15>=90,'CX_Junior BI Analyst_Test'!C15<=100),"High Performer",IF(AND('CX_Junior BI Analyst_Test'!C15>=70,'CX_Junior BI Analyst_Test'!C15<=89),"Average Performer",IF(AND('CX_Junior BI Analyst_Test'!C15>=50,'CX_Junior BI Analyst_Test'!C15<=69),"Low Performer","Bottom Performer"))) -> Average Performer | B15: ='CX_Junior BI Analyst_Test'!C15 -> 78
A16: =IF(AND('CX_Junior BI Analyst_Test'!C16>=90,'CX_Junior BI Analyst_Test'!C16<=100),"High Performer",IF(AND('CX_Junior BI Analyst_Test'!C16>=70,'CX_Junior BI Analyst_Test'!C16<=89),"Average Performer",IF(AND('CX_Junior BI Analyst_Test'!C16>=50,'CX_Junior BI Analyst_Test'!C16<=69),"Low Performer","Bottom Performer"))) -> Low Performer | B16: ='CX_Junior BI Analyst_Test'!C16 -> 61
A17: =IF(AND('CX_Junior BI Analyst_Test'!C17>=90,'CX_Junior BI Analyst_Test'!C17<=100),"High Performer",IF(AND('CX_Junior BI Analyst_Test'!C17>=70,'CX_Junior BI Analyst_Test'!C17<=89),"Average Performer",IF(AND('CX_Junior BI Analyst_Test'!C17>=50,'CX_Junior BI Analyst_Test'!C17<=69),"Low Performer","Bottom Performer"))) -> Average Performer | B17: ='CX_Junior BI Analyst_Test'!C17 -> 78
A18: =IF(AND('CX_Junior BI Analyst_Test'!C18>=90,'CX_Junior BI Analyst_Test'!C18<=100),"High Performer",IF(AND('CX_Junior BI Analyst_Test'!C18>=70,'CX_Junior BI Analyst_Test'!C18<=89),"Average Performer",IF(AND('CX_Junior BI Analyst_Test'!C18>=50,'CX_Junior BI Analyst_Test'!C18<=69),"Low Performer","Bottom Performer"))) -> Average Performer | B18: ='CX_Junior BI Analyst_Test'!C18 -> 89
... A62: =IF(AND('CX_Junior BI Analyst_Test'!C62>=90,'CX_Junior BI Analyst_Test'!C62<=100),"High Performer",IF(AND('CX_Junior BI Analyst_Test'!C62>=70,'CX_Junior BI Analyst_Test'!C62<=89),"Average Performer",IF(AND('CX_Junior BI Analyst_Test'!C62>=50,'CX_Junior BI Analyst_Test'!C62<=69),"Low Performer","Bottom Performer"))) -> Low Performer | B62: ='CX_Junior BI Analyst_Test'!C62 -> 65

Sheet Task 2 Sheet2
B3: Zone | C3: Average of Evaluation_Score
B4: East | C4: 71.571429
B5: North | C5: 76.736842
B6: South | C6: 66.611111
B7: West | C7: 71.823529
B8: Grand Total | C8: 71.786885
B12: Sum of Evaluation_Score | C12: Column Labels
B13: Row Labels | C13: East | D13: North | E13: South | F13: West | G13: Grand Total
B14: Abhay | D14: 94 | G14: 94
B15: Ajeet | D15: 60 | G15: 60
B16: Ali | E16: 71 | G16: 71
B17: Aneesh Jayanth | E17: 53 | G17: 53
B18: Anju Gurung | E18: 77 | G18: 77
B19: Arbaaz | F19: 65 | G19: 65
B20: Ashish | E20: 65 | G20: 65
B21: Asif | E21: 78 | G21: 78
B22: Bablu | F22: 78 | G22: 78
B23: Deepak | D23: 81 | G23: 81
B24: Fariz | D24: 100 | G24: 100
B25: Gaurav | F25: 86 | G25: 86
B26: Gouse Bhasha | E26: 61 | G26: 61
B27: Hari | E27: 59 | G27: 59
B28: Jateen | D28: 84 | G28: 84
B29: Kamal | D29: 140 | G29: 140
B30: Keneth | F30: 34 | G30: 34
B31: Kiran | F31: 70 | G31: 70
B32: Lukman | E32: 69 | G32: 69
B33: Mahesh | D33: 72 | G33: 72
B34: Mohsin | F34: 36 | G34: 36
B35: Mr. Girish | E35: 33 | G35: 33
B36: Muskan | C36: 41 | G36: 41
B37: Nagraj | F37: 89 | G37: 89
B38: Neeraj | D38: 155 | G38: 155
B39: Nitesh | D39: 69 | G39: 69
B40: Priyanka | C40: 96 | G40: 96
B41: Probin | D41: 33 | G41: 33
B42: Rafi | E42: 52 | G42: 52
B43: Rahul | D43: 69 | G43: 69
B44: Raj Roushan | C44: 64 | G44: 64
B45: Rajiv | E45: 78 | G45: 78
B46: Rakesh | F46: 74 | G46: 74
B47: Rashid | F47: 74 | G47: 74
B48: Rizwan | E48: 90 | G48: 90
B49: Rohit | C49: 83 | D49: 94 | G49: 177
B50: Sagar Prathak | D50: 82 | G50: 82
B51: Samir Pathan | F51: 80 | G51: 80
B52: Sanit Saji | E52: 84 | G52: 84
B53: Sanjeev | D53: 71 | G53: 71
B54: Sanjit | C54: 62 | G54: 62
B55: Sanket Patel | F55: 86 | G55: 86
B56: Santosh | E56: 94 | G56: 94
B57: Santosh Jadhav | F57: 84 | G57: 84
B58: Satyam | F58: 92 | G58: 92
B59: Senthil Kumar | E59: 88 | G59: 88
B60: Sonali | D60: 84 | G60: 84
B61: Suman | C61: 94 | G61: 94
B62: Sunil | D62: 76 | G62: 76
B63: Suraj | F63: 92 | G63: 92
B64: Suresh | E64: 73 | G64: 73
B65: The style advisor did not mention his name. | E65: 39 | G65: 39
B66: Varinder | D66: 94 | G66: 94
B67: Vasudev | C67: 61 | G67: 61
B68: Vijay K | F68: 34 | G68: 34
B69: Yash | E69: 35 | G69: 35
B70: Yasin Kaif | F70: 61 | G70: 61
B71: Yogesh | F71: 86 | G71: 86
B72: Grand Total | C72: 501 | D72: 1458 | E72: 1199 | F72: 1221 | G72: 4379
B75: Particulars | C75: East | D75: North | E75: South | F75: West
B76: Top Performers | C76: =COUNTIFS(C14:C71,">90") -> 2 | D76: =COUNTIFS(D14:D71,">90") -> 6 | E76: =COUNTIFS(E14:E71,">90") -> 1 | F76: =COUNTIFS(F14:F71,">90") -> 2
B77: Total Style Advisors | C77: =COUNT(C14:C71) -> 7 | D77: =COUNT(D14:D71) -> 17 | E77: =COUNT(E14:E71) -> 18 | F77: =COUNT(F14:F71) -> 17
B78: % of Top Performers | C78: =C76/C77 -> 0.28571429 | D78: =D76/D77 -> 0.35294118 | E78: =E76/E77 -> 0.055555556 | F78: =F76/F77 -> 0.11764706
B79: % of Others | C79: =100%-C78 -> 0.71428571 | D79: =100%-D78 -> 0.64705882 | E79: =100%-E78 -> 0.94444444 | F79: =100%-F78 -> 0.88235294

Sheet Task 3 Sheet3
D2: Bare International Visualization Project
A15: 1)
A32: 2)
A48: 3)
A65: 4)
A89: 5)

Sheet Calculation Pivot Table
B4: Row Labels | C4: Average of Evaluation_Score
B5: East | C5: 71.571429
B6: North | C6: 76.736842
B7: South | C7: 66.611111
B8: West | C8: 71.823529
B9: Grand Total | C9: 71.786885
B12: Name of Style Advisors | C12: Region | D12: Time Duration in Mins | E12: Performance Score | G12: Name of Style Advisors | H12: Region | I12: Time Duration in Mins ASC | J12: Performance Score
B13: ='CX_Junior BI Analyst_Test'!X2 -> Kamal | C13: ='CX_Junior BI Analyst_Test'!N2 -> North | D13: ='CX_Junior BI Analyst_Test'!R2/60 -> 17 | E13: =AVERAGE('CX_Junior BI Analyst_Test'!D2:K2) -> 57.5 | G13: ='CX_Junior BI Analyst_Test'!X29 -> Hari | H13: ='CX_Junior BI Analyst_Test'!N29 -> South | I13: ='CX_Junior BI Analyst_Test'!R29/60 -> 10 | J13: =AVERAGE('CX_Junior BI Analyst_Test'!D29:K29) -> 65.875
B14: ='CX_Junior BI Analyst_Test'!X3 -> Sanket Patel | C14: ='CX_Junior BI Analyst_Test'!N3 -> West | D14: ='CX_Junior BI Analyst_Test'!R3/60 -> 22 | E14: =AVERAGE('CX_Junior BI Analyst_Test'!D3:K3) -> 88.125 | G14: ='CX_Junior BI Analyst_Test'!X30 -> Probin | H14: ='CX_Junior BI Analyst_Test'!N30 -> North | I14: ='CX_Junior BI Analyst_Test'!R30/60 -> 10 | J14: =AVERAGE('CX_Junior BI Analyst_Test'!D30:K30) -> 26.375
B15: ='CX_Junior BI Analyst_Test'!X4 -> Mahesh | C15: ='CX_Junior BI Analyst_Test'!N4 -> North | D15: ='CX_Junior BI Analyst_Test'!R4/60 -> 18 | E15: =AVERAGE('CX_Junior BI Analyst_Test'!D4:K4) -> 74.625 | G15: ='CX_Junior BI Analyst_Test'!X62 -> Arbaaz | H15: ='CX_Junior BI Analyst_Test'!N62 -> West | I15: ='CX_Junior BI Analyst_Test'!R62/60 -> 12 | J15: =AVERAGE('CX_Junior BI Analyst_Test'!D62:K62) -> 66.25
B16: ='CX_Junior BI Analyst_Test'!X5 -> Sonali | C16: ='CX_Junior BI Analyst_Test'!N5 -> North | D16: ='CX_Junior BI Analyst_Test'!R5/60 -> 31 | E16: =AVERAGE('CX_Junior BI Analyst_Test'!D5:K5) -> 87.5 | G16: ='CX_Junior BI Analyst_Test'!X8 -> Mohsin | H16: ='CX_Junior BI Analyst_Test'!N8 -> West | I16: ='CX_Junior BI Analyst_Test'!R8/60 -> 15 | J16: =AVERAGE('CX_Junior BI Analyst_Test'!D8:K8) -> 24.125
B17: ='CX_Junior BI Analyst_Test'!X6 -> Jateen | C17: ='CX_Junior BI Analyst_Test'!N6 -> North | D17: ='CX_Junior BI Analyst_Test'!R6/60 -> 35 | E17: =AVERAGE('CX_Junior BI Analyst_Test'!D6:K6) -> 87.5 | G17: ='CX_Junior BI Analyst_Test'!X9 -> Keneth | H17: ='CX_Junior BI Analyst_Test'!N9 -> West | I17: ='CX_Junior BI Analyst_Test'!R9/60 -> 15 | J17: =AVERAGE('CX_Junior BI Analyst_Test'!D9:K9) -> 28
B18: ='CX_Junior BI Analyst_Test'!X7 -> Rizwan | C18: ='CX_Junior BI Analyst_Test'!N7 -> South | D18: ='CX_Junior BI Analyst_Test'!R7/60 -> 16 | E18: =AVERAGE('CX_Junior BI Analyst_Test'!D7:K7) -> 91.75 | G18: ='CX_Junior BI Analyst_Test'!X10 -> Rakesh | H18: ='CX_Junior BI Analyst_Test'!N10 -> West | I18: ='CX_Junior BI Analyst_Test'!R10/60 -> 15 | J18: =AVERAGE('CX_Junior BI Analyst_Test'!D10:K10) -> 76
B19: ='CX_Junior BI Analyst_Test'!X8 -> Mohsin | C19: ='CX_Junior BI Analyst_Test'!N8 -> West | D19: ='CX_Junior BI Analyst_Test'!R8/60 -> 15 | E19: =AVERAGE('CX_Junior BI Analyst_Test'!D8:K8) -> 24.125 | G19: ='CX_Junior BI Analyst_Test'!X11 -> Rashid | H19: ='CX_Junior BI Analyst_Test'!N11 -> West | I19: ='CX_Junior BI Analyst_Test'!R11/60 -> 15 | J19: =AVERAGE('CX_Junior BI Analyst_Test'!D11:K11) -> 76
B20: ='CX_Junior BI Analyst_Test'!X9 -> Keneth | C20: ='CX_Junior BI Analyst_Test'!N9 -> West | D20: ='CX_Junior BI Analyst_Test'!R9/60 -> 15 | E20: =AVERAGE('CX_Junior BI Analyst_Test'!D9:K9) -> 28 | G20: ='CX_Junior BI Analyst_Test'!X13 -> Kiran | H20: ='CX_Junior BI Analyst_Test'!N13 -> West | I20: ='CX_Junior BI Analyst_Test'!R13/60 -> 15 | J20: =AVERAGE('CX_Junior BI Analyst_Test'!D13:K13) -> 76.75
B21: ='CX_Junior BI Analyst_Test'!X10 -> Rakesh | C21: ='CX_Junior BI Analyst_Test'!N10 -> West | D21: ='CX_Junior BI Analyst_Test'!R10/60 -> 15 | E21: =AVERAGE('CX_Junior BI Analyst_Test'!D10:K10) -> 76 | G21: ='CX_Junior BI Analyst_Test'!X7 -> Rizwan | H21: ='CX_Junior BI Analyst_Test'!N7 -> South | I21: ='CX_Junior BI Analyst_Test'!R7/60 -> 16 | J21: =AVERAGE('CX_Junior BI Analyst_Test'!D7:K7) -> 91.75
B22: ='CX_Junior BI Analyst_Test'!X11 -> Rashid | C22: ='CX_Junior BI Analyst_Test'!N11 -> West | D22: ='CX_Junior BI Analyst_Test'!R11/60 -> 15 | E22: =AVERAGE('CX_Junior BI Analyst_Test'!D11:K11) -> 76 | G22: ='CX_Junior BI Analyst_Test'!X25 -> Ajeet | H22: ='CX_Junior BI Analyst_Test'!N25 -> North | I22: ='CX_Junior BI Analyst_Test'!R25/60 -> 16 | J22: =AVERAGE('CX_Junior BI Analyst_Test'!D25:K25) -> 64.25
B23: ='CX_Junior BI Analyst_Test'!X12 -> Gaurav | C23: ='CX_Junior BI Analyst_Test'!N12 -> West | D23: ='CX_Junior BI Analyst_Test'!R12/60 -> 26 | E23: =AVERAGE('CX_Junior BI Analyst_Test'!D12:K12) -> 90.125 | G23: ='CX_Junior BI Analyst_Test'!X2 -> Kamal | H23: ='CX_Junior BI Analyst_Test'!N2 -> North | I23: ='CX_Junior BI Analyst_Test'!R2/60 -> 17 | J23: =AVERAGE('CX_Junior BI Analyst_Test'!D2:K2) -> 57.5
B24: ='CX_Junior BI Analyst_Test'!X13 -> Kiran | C24: ='CX_Junior BI Analyst_Test'!N13 -> West | D24: ='CX_Junior BI Analyst_Test'!R13/60 -> 15 | E24: =AVERAGE('CX_Junior BI Analyst_Test'!D13:K13) -> 76.75 | G24: ='CX_Junior BI Analyst_Test'!X24 -> Neeraj | H24: ='CX_Junior BI Analyst_Test'!N24 -> North | I24: ='CX_Junior BI Analyst_Test'!R24/60 -> 17 | J24: =AVERAGE('CX_Junior BI Analyst_Test'!D24:K24) -> 64.375
B25: ='CX_Junior BI Analyst_Test'!X14 -> Sanit Saji | C25: ='CX_Junior BI Analyst_Test'!N14 -> South | D25: ='CX_Junior BI Analyst_Test'!R14/60 -> 25 | E25: =AVERAGE('CX_Junior BI Analyst_Test'!D14:K14) -> 86.375 | G25: ='CX_Junior BI Analyst_Test'!X4 -> Mahesh | H25: ='CX_Junior BI Analyst_Test'!N4 -> North | I25: ='CX_Junior BI Analyst_Test'!R4/60 -> 18 | J25: =AVERAGE('CX_Junior BI Analyst_Test'!D4:K4) -> 74.625
B26: ='CX_Junior BI Analyst_Test'!X15 -> Asif | C26: ='CX_Junior BI Analyst_Test'!N15 -> South | D26: ='CX_Junior BI Analyst_Test'!R15/60 -> 34 | E26: =AVERAGE('CX_Junior BI Analyst_Test'!D15:K15) -> 81.75 | G26: ='CX_Junior BI Analyst_Test'!X49 -> Rahul | H26: ='CX_Junior BI Analyst_Test'!N49 -> North | I26: ='CX_Junior BI Analyst_Test'!R49/60 -> 19 | J26: =AVERAGE('CX_Junior BI Analyst_Test'!D49:K49) -> 66.875
B27: ='CX_Junior BI Analyst_Test'!X16 -> Yasin Kaif | C27: ='CX_Junior BI Analyst_Test'!N16 -> West | D27: ='CX_Junior BI Analyst_Test'!R16/60 -> 28 | E27: =AVERAGE('CX_Junior BI Analyst_Test'!D16:K16) -> 66.375 | G27: ='CX_Junior BI Analyst_Test'!X26 -> Deepak | H27: ='CX_Junior BI Analyst_Test'!N26 -> North | I27: ='CX_Junior BI Analyst_Test'!R26/60 -> 20 | J27: =AVERAGE('CX_Junior BI Analyst_Test'!D26:K26) -> 81.75
B28: ='CX_Junior BI Analyst_Test'!X17 -> Bablu | C28: ='CX_Junior BI Analyst_Test'!N17 -> West | D28: ='CX_Junior BI Analyst_Test'!R17/60 -> 38 | E28: =AVERAGE('CX_Junior BI Analyst_Test'!D17:K17) -> 78 | G28: ='CX_Junior BI Analyst_Test'!X50 -> Nitesh | H28: ='CX_Junior BI Analyst_Test'!N50 -> North | I28: ='CX_Junior BI Analyst_Test'!R50/60 -> 20 | J28: =AVERAGE('CX_Junior BI Analyst_Test'!D50:K50) -> 66.625
B29: ='CX_Junior BI Analyst_Test'!X18 -> Nagraj | C29: ='CX_Junior BI Analyst_Test'!N18 -> West | D29: ='CX_Junior BI Analyst_Test'!R18/60 -> 40 | E29: =AVERAGE('CX_Junior BI Analyst_Test'!D18:K18) -> 88.375 | G29: ='CX_Junior BI Analyst_Test'!X21 -> Kamal | H29: ='CX_Junior BI Analyst_Test'!N21 -> North | I29: ='CX_Junior BI Analyst_Test'!R21/60 -> 21 | J29: =AVERAGE('CX_Junior BI Analyst_Test'!D21:K21) -> 84
B30: ='CX_Junior BI Analyst_Test'!X19 -> Ashish | C30: ='CX_Junior BI Analyst_Test'!N19 -> South | D30: ='CX_Junior BI Analyst_Test'!R19/60 -> 25 | E30: =AVERAGE('CX_Junior BI Analyst_Test'!D19:K19) -> 66.125 | G30: ='CX_Junior BI Analyst_Test'!X34 -> Santosh | H30: ='CX_Junior BI Analyst_Test'!N34 -> South | I30: ='CX_Junior BI Analyst_Test'!R34/60 -> 21 | J30: =AVERAGE('CX_Junior BI Analyst_Test'!D34:K34) -> 95.5
B31: ='CX_Junior BI Analyst_Test'!X20 -> Sunil | C31: ='CX_Junior BI Analyst_Test'!N20 -> North | D31: ='CX_Junior BI Analyst_Test'!R20/60 -> 25 | E31: =AVERAGE('CX_Junior BI Analyst_Test'!D20:K20) -> 68.25 | G31: ='CX_Junior BI Analyst_Test'!X58 -> Senthil Kumar | H31: ='CX_Junior BI Analyst_Test'!N58 -> South | I31: ='CX_Junior BI Analyst_Test'!R58/60 -> 21 | J31: =AVERAGE('CX_Junior BI Analyst_Test'!D58:K58) -> 90.125
B32: ='CX_Junior BI Analyst_Test'!X21 -> Kamal | C32: ='CX_Junior BI Analyst_Test'!N21 -> North | D32: ='CX_Junior BI Analyst_Test'!R21/60 -> 21 | E32: =AVERAGE('CX_Junior BI Analyst_Test'!D21:K21) -> 84 | G32: ='CX_Junior BI Analyst_Test'!X3 -> Sanket Patel | H32: ='CX_Junior BI Analyst_Test'!N3 -> West | I32: ='CX_Junior BI Analyst_Test'!R3/60 -> 22 | J32: =AVERAGE('CX_Junior BI Analyst_Test'!D3:K3) -> 88.125
B33: ='CX_Junior BI Analyst_Test'!X22 -> Neeraj | C33: ='CX_Junior BI Analyst_Test'!N22 -> North | D33: ='CX_Junior BI Analyst_Test'!R22/60 -> 25 | E33: =AVERAGE('CX_Junior BI Analyst_Test'!D22:K22) -> 90.375 | G33: ='CX_Junior BI Analyst_Test'!X41 -> Fariz | H33: ='CX_Junior BI Analyst_Test'!N41 -> North | I33: ='CX_Junior BI Analyst_Test'!R41/60 -> 22 | J33: =AVERAGE('CX_Junior BI Analyst_Test'!D41:K41) -> 100
B34: ='CX_Junior BI Analyst_Test'!X23 -> Sanjeev | C34: ='CX_Junior BI Analyst_Test'!N23 -> North | D34: ='CX_Junior BI Analyst_Test'!R23/60 -> 28 | E34: =AVERAGE('CX_Junior BI Analyst_Test'!D23:K23) -> 67.75 | G34: ='CX_Junior BI Analyst_Test'!X54 -> Vijay K | H34: ='CX_Junior BI Analyst_Test'!N54 -> West | I34: ='CX_Junior BI Analyst_Test'!R54/60 -> 22 | J34: =AVERAGE('CX_Junior BI Analyst_Test'!D54:K54) -> 28.25
B35: ='CX_Junior BI Analyst_Test'!X24 -> Neeraj | C35: ='CX_Junior BI Analyst_Test'!N24 -> North | D35: ='CX_Junior BI Analyst_Test'!R24/60 -> 17 | E35: =AVERAGE('CX_Junior BI Analyst_Test'!D24:K24) -> 64.375 | G35: ='CX_Junior BI Analyst_Test'!X44 -> Sanjit | H35: ='CX_Junior BI Analyst_Test'!N44 -> East | I35: ='CX_Junior BI Analyst_Test'!R44/60 -> 23 | J35: =AVERAGE('CX_Junior BI Analyst_Test'!D44:K44) -> 53.75
B36: ='CX_Junior BI Analyst_Test'!X25 -> Ajeet | C36: ='CX_Junior BI Analyst_Test'!N25 -> North | D36: ='CX_Junior BI Analyst_Test'!R25/60 -> 16 | E36: =AVERAGE('CX_Junior BI Analyst_Test'!D25:K25) -> 64.25 | G36: ='CX_Junior BI Analyst_Test'!X56 -> Varinder | H36: ='CX_Junior BI Analyst_Test'!N56 -> North | I36: ='CX_Junior BI Analyst_Test'!R56/60 -> 23 | J36: =AVERAGE('CX_Junior BI Analyst_Test'!D56:K56) -> 94.75
B37: ='CX_Junior BI Analyst_Test'!X26 -> Deepak | C37: ='CX_Junior BI Analyst_Test'!N26 -> North | D37: ='CX_Junior BI Analyst_Test'!R26/60 -> 20 | E37: =AVERAGE('CX_Junior BI Analyst_Test'!D26:K26) -> 81.75 | G37: ='CX_Junior BI Analyst_Test'!X31 -> Raj Roushan | H37: ='CX_Junior BI Analyst_Test'!N31 -> East | I37: ='CX_Junior BI Analyst_Test'!R31/60 -> 24 | J37: =AVERAGE('CX_Junior BI Analyst_Test'!D31:K31) -> 56.625
B38: ='CX_Junior BI Analyst_Test'!X27 -> Rajiv | C38: ='CX_Junior BI Analyst_Test'!N27 -> South | D38: ='CX_Junior BI Analyst_Test'!R27/60 -> 32 | E38: =AVERAGE('CX_Junior BI Analyst_Test'!D27:K27) -> 81.75 | G38: ='CX_Junior BI Analyst_Test'!X42 -> Abhay | H38: ='CX_Junior BI Analyst_Test'!N42 -> North | I38: ='CX_Junior BI Analyst_Test'!R42/60 -> 24 | J38: =AVERAGE('CX_Junior BI Analyst_Test'!D42:K42) -> 95.875
B39: ='CX_Junior BI Analyst_Test'!X28 -> Satyam | C39: ='CX_Junior BI Analyst_Test'!N28 -> West | D39: ='CX_Junior BI Analyst_Test'!R28/60 -> 25 | E39: =AVERAGE('CX_Junior BI Analyst_Test'!D28:K28) -> 94.125 | G39: ='CX_Junior BI Analyst_Test'!X46 -> Yogesh | H39: ='CX_Junior BI Analyst_Test'!N46 -> West | I39: ='CX_Junior BI Analyst_Test'!R46/60 -> 24 | J39: =AVERAGE('CX_Junior BI Analyst_Test'!D46:K46) -> 88.125
B40: ='CX_Junior BI Analyst_Test'!X29 -> Hari | C40: ='CX_Junior BI Analyst_Test'!N29 -> South | D40: ='CX_Junior BI Analyst_Test'!R29/60 -> 10 | E40: =AVERAGE('CX_Junior BI Analyst_Test'!D29:K29) -> 65.875 | G40: ='CX_Junior BI Analyst_Test'!X14 -> Sanit Saji | H40: ='CX_Junior BI Analyst_Test'!N14 -> South | I40: ='CX_Junior BI Analyst_Test'!R14/60 -> 25 | J40: =AVERAGE('CX_Junior BI Analyst_Test'!D14:K14) -> 86.375
B41: ='CX_Junior BI Analyst_Test'!X30 -> Probin | C41: ='CX_Junior BI Analyst_Test'!N30 -> North | D41: ='CX_Junior BI Analyst_Test'!R30/60 -> 10 | E41: =AVERAGE('CX_Junior BI Analyst_Test'!D30:K30) -> 26.375 | G41: ='CX_Junior BI Analyst_Test'!X19 -> Ashish | H41: ='CX_Junior BI Analyst_Test'!N19 -> South | I41: ='CX_Junior BI Analyst_Test'!R19/60 -> 25 | J41: =AVERAGE('CX_Junior BI Analyst_Test'!D19:K19) -> 66.125
B42: ='CX_Junior BI Analyst_Test'!X31 -> Raj Roushan | C42: ='CX_Junior BI Analyst_Test'!N31 -> East | D42: ='CX_Junior BI Analyst_Test'!R31/60 -> 24 | E42: =AVERAGE('CX_Junior BI Analyst_Test'!D31:K31) -> 56.625 | G42: ='CX_Junior BI Analyst_Test'!X20 -> Sunil | H42: ='CX_Junior BI Analyst_Test'!N20 -> North | I42: ='CX_Junior BI Analyst_Test'!R20/60 -> 25 | J42: =AVERAGE('CX_Junior BI Analyst_Test'!D20:K20) -> 68.25
B43: ='CX_Junior BI Analyst_Test'!X32 -> Lukman | C43: ='CX_Junior BI Analyst_Test'!N32 -> South | D43: ='CX_Junior BI Analyst_Test'!R32/60 -> 35 | E43: =AVERAGE('CX_Junior BI Analyst_Test'!D32:K32) -> 75.625 | G43: ='CX_Junior BI Analyst_Test'!X22 -> Neeraj | H43: ='CX_Junior BI Analyst_Test'!N22 -> North | I43: ='CX_Junior BI Analyst_Test'!R22/60 -> 25 | J43: =AVERAGE('CX_Junior BI Analyst_Test'!D22:K22) -> 90.375
B44: ='CX_Junior BI Analyst_Test'!X33 -> Rohit | C44: ='CX_Junior BI Analyst_Test'!N33 -> East | D44: ='CX_Junior BI Analyst_Test'!R33/60 -> 25 | E44: =AVERAGE('CX_Junior BI Analyst_Test'!D33:K33) -> 87.75 | G44: ='CX_Junior BI Analyst_Test'!X28 -> Satyam | H44: ='CX_Junior BI Analyst_Test'!N28 -> West | I44: ='CX_Junior BI Analyst_Test'!R28/60 -> 25 | J44: =AVERAGE('CX_Junior BI Analyst_Test'!D28:K28) -> 94.125
B45: ='CX_Junior BI Analyst_Test'!X34 -> Santosh | C45: ='CX_Junior BI Analyst_Test'!N34 -> South | D45: ='CX_Junior BI Analyst_Test'!R34/60 -> 21 | E45: =AVERAGE('CX_Junior BI Analyst_Test'!D34:K34) -> 95.5 | G45: ='CX_Junior BI Analyst_Test'!X33 -> Rohit | H45: ='CX_Junior BI Analyst_Test'!N33 -> East | I45: ='CX_Junior BI Analyst_Test'!R33/60 -> 25 | J45: =AVERAGE('CX_Junior BI Analyst_Test'!D33:K33) -> 87.75
B46: ='CX_Junior BI Analyst_Test'!X35 -> Samir Pathan | C46: ='CX_Junior BI Analyst_Test'!N35 -> West | D46: ='CX_Junior BI Analyst_Test'!R35/60 -> 34 | E46: =AVERAGE('CX_Junior BI Analyst_Test'!D35:K35) -> 83.875 | G46: ='CX_Junior BI Analyst_Test'!X39 -> The style advisor did not mention his name. | H46: ='CX_Junior BI Analyst_Test'!N39 -> South | I46: ='CX_Junior BI Analyst_Test'!R39/60 -> 25 | J46: =AVERAGE('CX_Junior BI Analyst_Test'!D39:K39) -> 33.375
B47: ='CX_Junior BI Analyst_Test'!X36 -> Sagar Prathak | C47: ='CX_Junior BI Analyst_Test'!N36 -> North | D47: ='CX_Junior BI Analyst_Test'!R36/60 -> 31 | E47: =AVERAGE('CX_Junior BI Analyst_Test'!D36:K36) -> 84.75 | G47: ='CX_Junior BI Analyst_Test'!X43 -> Rafi | H47: ='CX_Junior BI Analyst_Test'!N43 -> South | I47: ='CX_Junior BI Analyst_Test'!R43/60 -> 25 | J47: =AVERAGE('CX_Junior BI Analyst_Test'!D43:K43) -> 60.375
B48: ='CX_Junior BI Analyst_Test'!X37 -> Santosh Jadhav | C48: ='CX_Junior BI Analyst_Test'!N37 -> West | D48: ='CX_Junior BI Analyst_Test'!R37/60 -> 32 | E48: =AVERAGE('CX_Junior BI Analyst_Test'!D37:K37) -> 87.125 | G48: ='CX_Junior BI Analyst_Test'!X47 -> Rohit | H48: ='CX_Junior BI Analyst_Test'!N47 -> North | I48: ='CX_Junior BI Analyst_Test'!R47/60 -> 25 | J48: =AVERAGE('CX_Junior BI Analyst_Test'!D47:K47) -> 94.375
B49: ='CX_Junior BI Analyst_Test'!X38 -> Suresh | C49: ='CX_Junior BI Analyst_Test'!N38 -> South | D49: ='CX_Junior BI Analyst_Test'!R38/60 -> 29 | E49: =AVERAGE('CX_Junior BI Analyst_Test'!D38:K38) -> 77.625 | G49: ='CX_Junior BI Analyst_Test'!X12 -> Gaurav | H49: ='CX_Junior BI Analyst_Test'!N12 -> West | I49: ='CX_Junior BI Analyst_Test'!R12/60 -> 26 | J49: =AVERAGE('CX_Junior BI Analyst_Test'!D12:K12) -> 90.125
B50: ='CX_Junior BI Analyst_Test'!X39 -> The style advisor did not mention his name. | C50: ='CX_Junior BI Analyst_Test'!N39 -> South | D50: ='CX_Junior BI Analyst_Test'!R39/60 -> 25 | E50: =AVERAGE('CX_Junior BI Analyst_Test'!D39:K39) -> 33.375 | G50: ='CX_Junior BI Analyst_Test'!X16 -> Yasin Kaif | H50: ='CX_Junior BI Analyst_Test'!N16 -> West | I50: ='CX_Junior BI Analyst_Test'!R16/60 -> 28 | J50: =AVERAGE('CX_Junior BI Analyst_Test'!D16:K16) -> 66.375
B51: ='CX_Junior BI Analyst_Test'!X40 -> Ali | C51: ='CX_Junior BI Analyst_Test'!N40 -> South | D51: ='CX_Junior BI Analyst_Test'!R40/60 -> 28 | E51: =AVERAGE('CX_Junior BI Analyst_Test'!D40:K40) -> 72.75 | G51: ='CX_Junior BI Analyst_Test'!X23 -> Sanjeev | H51: ='CX_Junior BI Analyst_Test'!N23 -> North | I51: ='CX_Junior BI Analyst_Test'!R23/60 -> 28 | J51: =AVERAGE('CX_Junior BI Analyst_Test'!D23:K23) -> 67.75
B52: ='CX_Junior BI Analyst_Test'!X41 -> Fariz | C52: ='CX_Junior BI Analyst_Test'!N41 -> North | D52: ='CX_Junior BI Analyst_Test'!R41/60 -> 22 | E52: =AVERAGE('CX_Junior BI Analyst_Test'!D41:K41) -> 100 | G52: ='CX_Junior BI Analyst_Test'!X40 -> Ali | H52: ='CX_Junior BI Analyst_Test'!N40 -> South | I52: ='CX_Junior BI Analyst_Test'!R40/60 -> 28 | J52: =AVERAGE('CX_Junior BI Analyst_Test'!D40:K40) -> 72.75
B53: ='CX_Junior BI Analyst_Test'!X42 -> Abhay | C53: ='CX_Junior BI Analyst_Test'!N42 -> North | D53: ='CX_Junior BI Analyst_Test'!R42/60 -> 24 | E53: =AVERAGE('CX_Junior BI Analyst_Test'!D42:K42) -> 95.875 | G53: ='CX_Junior BI Analyst_Test'!X51 -> Gouse Bhasha | H53: ='CX_Junior BI Analyst_Test'!N51 -> South | I53: ='CX_Junior BI Analyst_Test'!R51/60 -> 28 | J53: =AVERAGE('CX_Junior BI Analyst_Test'!D51:K51) -> 65.75
B54: ='CX_Junior BI Analyst_Test'!X43 -> Rafi | C54: ='CX_Junior BI Analyst_Test'!N43 -> South | D54: ='CX_Junior BI Analyst_Test'!R43/60 -> 25 | E54: =AVERAGE('CX_Junior BI Analyst_Test'!D43:K43) -> 60.375 | G54: ='CX_Junior BI Analyst_Test'!X38 -> Suresh | H54: ='CX_Junior BI Analyst_Test'!N38 -> South | I54: ='CX_Junior BI Analyst_Test'!R38/60 -> 29 | J54: =AVERAGE('CX_Junior BI Analyst_Test'!D38:K38) -> 77.625
B55: ='CX_Junior BI Analyst_Test'!X44 -> Sanjit | C55: ='CX_Junior BI Analyst_Test'!N44 -> East | D55: ='CX_Junior BI Analyst_Test'!R44/60 -> 23 | E55: =AVERAGE('CX_Junior BI Analyst_Test'!D44:K44) -> 53.75 | G55: ='CX_Junior BI Analyst_Test'!X57 -> Vasudev | H55: ='CX_Junior BI Analyst_Test'!N57 -> East | I55: ='CX_Junior BI Analyst_Test'!R57/60 -> 29 | J55: =AVERAGE('CX_Junior BI Analyst_Test'!D57:K57) -> 61.75
B56: ='CX_Junior BI Analyst_Test'!X45 -> Suman | C56: ='CX_Junior BI Analyst_Test'!N45 -> East | D56: ='CX_Junior BI Analyst_Test'!R45/60 -> 51 | E56: =AVERAGE('CX_Junior BI Analyst_Test'!D45:K45) -> 95.375 | G56: ='CX_Junior BI Analyst_Test'!X55 -> Aneesh Jayanth | H56: ='CX_Junior BI Analyst_Test'!N55 -> South | I56: ='CX_Junior BI Analyst_Test'!R55/60 -> 30 | J56: =AVERAGE('CX_Junior BI Analyst_Test'!D55:K55) -> 56.875
B57: ='CX_Junior BI Analyst_Test'!X46 -> Yogesh | C57: ='CX_Junior BI Analyst_Test'!N46 -> West | D57: ='CX_Junior BI Analyst_Test'!R46/60 -> 24 | E57: =AVERAGE('CX_Junior BI Analyst_Test'!D46:K46) -> 88.125 | G57: ='CX_Junior BI Analyst_Test'!X60 -> Mr. Girish | H57: ='CX_Junior BI Analyst_Test'!N60 -> South | I57: ='CX_Junior BI Analyst_Test'!R60/60 -> 30 | J57: =AVERAGE('CX_Junior BI Analyst_Test'!D60:K60) -> 27
B58: ='CX_Junior BI Analyst_Test'!X47 -> Rohit | C58: ='CX_Junior BI Analyst_Test'!N47 -> North | D58: ='CX_Junior BI Analyst_Test'!R47/60 -> 25 | E58: =AVERAGE('CX_Junior BI Analyst_Test'!D47:K47) -> 94.375 | G58: ='CX_Junior BI Analyst_Test'!X61 -> Yash | H58: ='CX_Junior BI Analyst_Test'!N61 -> South | I58: ='CX_Junior BI Analyst_Test'!R61/60 -> 30 | J58: =AVERAGE('CX_Junior BI Analyst_Test'!D61:K61) -> 26.25
B59: ='CX_Junior BI Analyst_Test'!X48 -> Muskan | C59: ='CX_Junior BI Analyst_Test'!N48 -> East | D59: ='CX_Junior BI Analyst_Test'!R48/60 -> 58 | E59: =AVERAGE('CX_Junior BI Analyst_Test'!D48:K48) -> 43.375 | G59: ='CX_Junior BI Analyst_Test'!X5 -> Sonali | H59: ='CX_Junior BI Analyst_Test'!N5 -> North | I59: ='CX_Junior BI Analyst_Test'!R5/60 -> 31 | J59: =AVERAGE('CX_Junior BI Analyst_Test'!D5:K5) -> 87.5
B60: ='CX_Junior BI Analyst_Test'!X49 -> Rahul | C60: ='CX_Junior BI Analyst_Test'!N49 -> North | D60: ='CX_Junior BI Analyst_Test'!R49/60 -> 19 | E60: =AVERAGE('CX_Junior BI Analyst_Test'!D49:K49) -> 66.875 | G60: ='CX_Junior BI Analyst_Test'!X36 -> Sagar Prathak | H60: ='CX_Junior BI Analyst_Test'!N36 -> North | I60: ='CX_Junior BI Analyst_Test'!R36/60 -> 31 | J60: =AVERAGE('CX_Junior BI Analyst_Test'!D36:K36) -> 84.75
B61: ='CX_Junior BI Analyst_Test'!X50 -> Nitesh | C61: ='CX_Junior BI Analyst_Test'!N50 -> North | D61: ='CX_Junior BI Analyst_Test'!R50/60 -> 20 | E61: =AVERAGE('CX_Junior BI Analyst_Test'!D50:K50) -> 66.625 | G61: ='CX_Junior BI Analyst_Test'!X27 -> Rajiv | H61: ='CX_Junior BI Analyst_Test'!N27 -> South | I61: ='CX_Junior BI Analyst_Test'!R27/60 -> 32 | J61: =AVERAGE('CX_Junior BI Analyst_Test'!D27:K27) -> 81.75
B62: ='CX_Junior BI Analyst_Test'!X51 -> Gouse Bhasha | C62: ='CX_Junior BI Analyst_Test'!N51 -> South | D62: ='CX_Junior BI Analyst_Test'!R51/60 -> 28 | E62: =AVERAGE('CX_Junior BI Analyst_Test'!D51:K51) -> 65.75 | G62: ='CX_Junior BI Analyst_Test'!X37 -> Santosh Jadhav | H62: ='CX_Junior BI Analyst_Test'!N37 -> West | I62: ='CX_Junior BI Analyst_Test'!R37/60 -> 32 | J62: =AVERAGE('CX_Junior BI Analyst_Test'!D37:K37) -> 87.125
B63: ='CX_Junior BI Analyst_Test'!X52 -> Suraj | C63: ='CX_Junior BI Analyst_Test'!N52 -> West | D63: ='CX_Junior BI Analyst_Test'!R52/60 -> 45 | E63: =AVERAGE('CX_Junior BI Analyst_Test'!D52:K52) -> 93.75 | G63: ='CX_Junior BI Analyst_Test'!X15 -> Asif | H63: ='CX_Junior BI Analyst_Test'!N15 -> South | I63: ='CX_Junior BI Analyst_Test'!R15/60 -> 34 | J63: =AVERAGE('CX_Junior BI Analyst_Test'!D15:K15) -> 81.75
B64: ='CX_Junior BI Analyst_Test'!X53 -> Priyanka | C64: ='CX_Junior BI Analyst_Test'!N53 -> East | D64: ='CX_Junior BI Analyst_Test'!R53/60 -> 76 | E64: =AVERAGE('CX_Junior BI Analyst_Test'!D53:K53) -> 95.375 | G64: ='CX_Junior BI Analyst_Test'!X35 -> Samir Pathan | H64: ='CX_Junior BI Analyst_Test'!N35 -> West | I64: ='CX_Junior BI Analyst_Test'!R35/60 -> 34 | J64: =AVERAGE('CX_Junior BI Analyst_Test'!D35:K35) -> 83.875
B65: ='CX_Junior BI Analyst_Test'!X54 -> Vijay K | C65: ='CX_Junior BI Analyst_Test'!N54 -> West | D65: ='CX_Junior BI Analyst_Test'!R54/60 -> 22 | E65: =AVERAGE('CX_Junior BI Analyst_Test'!D54:K54) -> 28.25 | G65: ='CX_Junior BI Analyst_Test'!X6 -> Jateen | H65: ='CX_Junior BI Analyst_Test'!N6 -> North | I65: ='CX_Junior BI Analyst_Test'!R6/60 -> 35 | J65: =AVERAGE('CX_Junior BI Analyst_Test'!D6:K6) -> 87.5
B66: ='CX_Junior BI Analyst_Test'!X55 -> Aneesh Jayanth | C66: ='CX_Junior BI Analyst_Test'!N55 -> South | D66: ='CX_Junior BI Analyst_Test'!R55/60 -> 30 | E66: =AVERAGE('CX_Junior BI Analyst_Test'!D55:K55) -> 56.875 | G66: ='CX_Junior BI Analyst_Test'!X32 -> Lukman | H66: ='CX_Junior BI Analyst_Test'!N32 -> South | I66: ='CX_Junior BI Analyst_Test'!R32/60 -> 35 | J66: =AVERAGE('CX_Junior BI Analyst_Test'!D32:K32) -> 75.625
B67: ='CX_Junior BI Analyst_Test'!X56 -> Varinder | C67: ='CX_Junior BI Analyst_Test'!N56 -> North | D67: ='CX_Junior BI Analyst_Test'!R56/60 -> 23 | E67: =AVERAGE('CX_Junior BI Analyst_Test'!D56:K56) -> 94.75 | G67: ='CX_Junior BI Analyst_Test'!X17 -> Bablu | H67: ='CX_Junior BI Analyst_Test'!N17 -> West | I67: ='CX_Junior BI Analyst_Test'!R17/60 -> 38 | J67: =AVERAGE('CX_Junior BI Analyst_Test'!D17:K17) -> 78
B68: ='CX_Junior BI Analyst_Test'!X57 -> Vasudev | C68: ='CX_Junior BI Analyst_Test'!N57 -> East | D68: ='CX_Junior BI Analyst_Test'!R57/60 -> 29 | E68: =AVERAGE('CX_Junior BI Analyst_Test'!D57:K57) -> 61.75 | G68: ='CX_Junior BI Analyst_Test'!X18 -> Nagraj | H68: ='CX_Junior BI Analyst_Test'!N18 -> West | I68: ='CX_Junior BI Analyst_Test'!R18/60 -> 40 | J68: =AVERAGE('CX_Junior BI Analyst_Test'!D18:K18) -> 88.375
B69: ='CX_Junior BI Analyst_Test'!X58 -> Senthil Kumar | C69: ='CX_Junior BI Analyst_Test'!N58 -> South | D69: ='CX_Junior BI Analyst_Test'!R58/60 -> 21 | E69: =AVERAGE('CX_Junior BI Analyst_Test'!D58:K58) -> 90.125 | G69: ='CX_Junior BI Analyst_Test'!X52 -> Suraj | H69: ='CX_Junior BI Analyst_Test'!N52 -> West | I69: ='CX_Junior BI Analyst_Test'!R52/60 -> 45 | J69: =AVERAGE('CX_Junior BI Analyst_Test'!D52:K52) -> 93.75
B70: ='CX_Junior BI Analyst_Test'!X59 -> Anju Gurung | C70: ='CX_Junior BI Analyst_Test'!N59 -> South | D70: ='CX_Junior BI Analyst_Test'!R59/60 -> 54 | E70: =AVERAGE('CX_Junior BI Analyst_Test'!D59:K59) -> 67.875 | G70: ='CX_Junior BI Analyst_Test'!X45 -> Suman | H70: ='CX_Junior BI Analyst_Test'!N45 -> East | I70: ='CX_Junior BI Analyst_Test'!R45/60 -> 51 | J70: =AVERAGE('CX_Junior BI Analyst_Test'!D45:K45) -> 95.375
B71: ='CX_Junior BI Analyst_Test'!X60 -> Mr. Girish | C71: ='CX_Junior BI Analyst_Test'!N60 -> South | D71: ='CX_Junior BI Analyst_Test'!R60/60 -> 30 | E71: =AVERAGE('CX_Junior BI Analyst_Test'!D60:K60) -> 27 | G71: ='CX_Junior BI Analyst_Test'!X59 -> Anju Gurung | H71: ='CX_Junior BI Analyst_Test'!N59 -> South | I71: ='CX_Junior BI Analyst_Test'!R59/60 -> 54 | J71: =AVERAGE('CX_Junior BI Analyst_Test'!D59:K59) -> 67.875
B72: ='CX_Junior BI Analyst_Test'!X61 -> Yash | C72: ='CX_Junior BI Analyst_Test'!N61 -> South | D72: ='CX_Junior BI Analyst_Test'!R61/60 -> 30 | E72: =AVERAGE('CX_Junior BI Analyst_Test'!D61:K61) -> 26.25 | G72: ='CX_Junior BI Analyst_Test'!X48 -> Muskan | H72: ='CX_Junior BI Analyst_Test'!N48 -> East | I72: ='CX_Junior BI Analyst_Test'!R48/60 -> 58 | J72: =AVERAGE('CX_Junior BI Analyst_Test'!D48:K48) -> 43.375
B73: ='CX_Junior BI Analyst_Test'!X62 -> Arbaaz | C73: ='CX_Junior BI Analyst_Test'!N62 -> West | D73: ='CX_Junior BI Analyst_Test'!R62/60 -> 12 | E73: =AVERAGE('CX_Junior BI Analyst_Test'!D62:K62) -> 66.25 | G73: ='CX_Junior BI Analyst_Test'!X53 -> Priyanka | H73: ='CX_Junior BI Analyst_Test'!N53 -> East | I73: ='CX_Junior BI Analyst_Test'!R53/60 -> 76 | J73: =AVERAGE('CX_Junior BI Analyst_Test'!D53:K53) -> 95.375
B77: Name of the Style Advisor who attended to you: | C77: Evaluation_Score | D77: Performance Score
B78: ='CX_Junior BI Analyst_Test'!X2 -> Kamal | C78: ='CX_Junior BI Analyst_Test'!C2 -> 58 | D78: =E13 -> 57.5
B79: ='CX_Junior BI Analyst_Test'!X3 -> Sanket Patel | C79: ='CX_Junior BI Analyst_Test'!C3 -> 86 | D79: =E14 -> 88.125
B80: ='CX_Junior BI Analyst_Test'!X4 -> Mahesh | C80: ='CX_Junior BI Analyst_Test'!C4 -> 72 | D80: =E15 -> 74.625
B81: ='CX_Junior BI Analyst_Test'!X5 -> Sonali | C81: ='CX_Junior BI Analyst_Test'!C5 -> 84 | D81: =E16 -> 87.5
B82: ='CX_Junior BI Analyst_Test'!X6 -> Jateen | C82: ='CX_Junior BI Analyst_Test'!C6 -> 84 | D82: =E17 -> 87.5
B83: ='CX_Junior BI Analyst_Test'!X7 -> Rizwan | C83: ='CX_Junior BI Analyst_Test'!C7 -> 90 | D83: =E18 -> 91.75
B84: ='CX_Junior BI Analyst_Test'!X8 -> Mohsin | C84: ='CX_Junior BI Analyst_Test'!C8 -> 36 | D84: =E19 -> 24.125
B85: ='CX_Junior BI Analyst_Test'!X9 -> Keneth | C85: ='CX_Junior BI Analyst_Test'!C9 -> 34 | D85: =E20 -> 28
B86: ='CX_Junior BI Analyst_Test'!X10 -> Rakesh | C86: ='CX_Junior BI Analyst_Test'!C10 -> 74 | D86: =E21 -> 76
B87: ='CX_Junior BI Analyst_Test'!X11 -> Rashid | C87: ='CX_Junior BI Analyst_Test'!C11 -> 74 | D87: =E22 -> 76
B88: ='CX_Junior BI Analyst_Test'!X12 -> Gaurav | C88: ='CX_Junior BI Analyst_Test'!C12 -> 86 | D88: =E23 -> 90.125
B89: ='CX_Junior BI Analyst_Test'!X13 -> Kiran | C89: ='CX_Junior BI Analyst_Test'!C13 -> 70 | D89: =E24 -> 76.75
... B138: ='CX_Junior BI Analyst_Test'!X62 -> Arbaaz | C138: ='CX_Junior BI Analyst_Test'!C62 -> 65 | D138: =E73 -> 66.25
B142: Particulars | C142: East_Region | D142: North _Region | E142: South _Region | F142: West _Region
B143: Top Performers | C143: =COUNTIFS('Task 2 Sheet2'!C14:C71, ">=90", 'Task 2 Sheet2'!C14:C71, "<=100") -> 2 | D143: =COUNTIFS('Task 2 Sheet2'!D14:D71, ">=90", 'Task 2 Sheet2'!D14:D71, "<=100") -> 4 | E143: =COUNTIFS('Task 2 Sheet2'!E14:E71, ">=90", 'Task 2 Sheet2'!E14:E71, "<=100") -> 2 | F143: =COUNTIFS('Task 2 Sheet2'!F14:F71, ">=90", 'Task 2 Sheet2'!F14:F71, "<=100") -> 2
B144: Average Performer | C144: =COUNTIFS('Task 2 Sheet2'!C14:C71,">70", 'Task 2 Sheet2'!C14:C71,"<90") -> 1 | D144: =COUNTIFS('Task 2 Sheet2'!D14:D71,">70", 'Task 2 Sheet2'!D14:D71,"<90") -> 7 | E144: =COUNTIFS('Task 2 Sheet2'!E14:E71,">70", 'Task 2 Sheet2'!E14:E71,"<90") -> 7 | F144: =COUNTIFS('Task 2 Sheet2'!F14:F71,">70", 'Task 2 Sheet2'!F14:F71,"<90") -> 9
B145: Low Performer | C145: =COUNTIFS('Task 2 Sheet2'!C14:C71,">=50", 'Task 2 Sheet2'!C14:C71, "<70") -> 3 | D145: =COUNTIFS('Task 2 Sheet2'!D14:D71,">=50", 'Task 2 Sheet2'!D14:D71, "<70") -> 3 | E145: =COUNTIFS('Task 2 Sheet2'!E14:E71,">=50", 'Task 2 Sheet2'!E14:E71, "<70") -> 6 | F145: =COUNTIFS('Task 2 Sheet2'!F14:F71,">=50", 'Task 2 Sheet2'!F14:F71, "<70") -> 2
B146: Bottom Performer | C146: =COUNTIF('Task 2 Sheet2'!C14:C71, "<50") -> 1 | D146: =COUNTIF('Task 2 Sheet2'!D14:D71, "<50") -> 1 | E146: =COUNTIF('Task 2 Sheet2'!E14:E71, "<50") -> 3 | F146: =COUNTIF('Task 2 Sheet2'!F14:F71, "<50") -> 3
B147: Total Style Advisors | C147: =SUM(C143:C146) -> 7 | D147: =SUM(D143:D146) -> 15 | E147: =SUM(E143:E146) -> 18 | F147: =SUM(F143:F146) -> 16
